Workbook

Sheet Summary
A1: OpHUB review v3 — 27 Oct 2026
A2: Everything since v2 (24 Oct evening): fix round 2, three database security batches, 15 server functions redeployed, and the new features you asked for. Every v2 row is carried forward with its status now.
A4: At a glance
B5: v2 (24 Oct) | C5: Now (27 Oct) | D5: Notes
A6: Bugs (137 from the 23 Oct review)
A7: Fixed | B7: 52 | C7: =COUNTIF('Bugs Now'!$G$5:$G$141,"Fixed") -> 128 | D7: Fix round 2 (25 Oct) fixed almost all the rest.
A8: Partly fixed | B8: 8 | C8: =COUNTIF('Bugs Now'!$G$5:$G$141,"Partly fixed") -> 4 | D8: CORE-M3, CORE-L11, PA-38, FA-15: see Still to do.
A9: Open | B9: 73 | C9: =COUNTIF('Bugs Now'!$G$5:$G$141,"Open") -> 1 | D9: CORE-M7 (holiday approvals need a database rule).
A10: Was wrong (not a real bug) | B10: 4 | C10: =COUNTIF('Bugs Now'!$G$5:$G$141,"Was wrong") -> 4
A11: Open or partly fixed, Critical/High | B11: 2 | C11: =COUNTIFS('Bugs Now'!$G$5:$G$141,"Open",'Bugs Now'!$B$5:$B$141,"Critical")+COUNTIFS('Bugs Now'!$G$5:$G$141,"Open",'Bugs Now'!$B$5:$B$141,"High")+COUNTIFS('Bugs Now'!$G$5:$G$141,"Partly fixed",'Bugs Now'!$B$5:$B$141,"Critical")+COUNTIFS('Bugs Now'!$G$5:$G$141,"Partly fixed",'Bugs Now'!$B$5:$B$141,"High") -> 0
A12: Security (33: 30 from 23 Oct + 3 from 24 Oct)
A13: Fixed | B13: 2 | C13: =COUNTIF('Security Now'!$F$6:$F$38,"Fixed") -> 27 | D13: Batches 1–3 applied and server functions redeployed.
A14: Partly fixed | B14: 1 | C14: =COUNTIF('Security Now'!$F$6:$F$38,"Partly fixed") -> 4 | D14: C1 and L10 wait on you; H3 needs private buckets; N3 needs the repo copy updated.
A15: Open | B15: 28 | C15: =COUNTIF('Security Now'!$F$6:$F$38,"Open") -> 0
A16: Info / needs check | B16: 2 | C16: =COUNTIF('Security Now'!$F$6:$F$38,"Info*") -> 2
A17: Open or partly fixed, Critical/High | B17: 6 | C17: =COUNTIFS('Security Now'!$F$6:$F$38,"Open",'Security Now'!$B$6:$B$38,"Critical")+COUNTIFS('Security Now'!$F$6:$F$38,"Open",'Security Now'!$B$6:$B$38,"High")+COUNTIFS('Security Now'!$F$6:$F$38,"Partly fixed",'Security Now'!$B$6:$B$38,"Critical")+COUNTIFS('Security Now'!$F$6:$F$38,"Partly fixed",'Security Now'!$B$6:$B$38,"High") -> 2 | D17: C1 (your task) and H3.
A18: New issues (37 found 24 Oct evening)
A19: Fixed | B19: 16 (waiting for Push origin) | C19: =COUNTIF('New Issues'!$G$5:$G$41,"Fixed") -> 35
A20: Partly fixed | B20: 0 | C20: =COUNTIF('New Issues'!$G$5:$G$41,"Partly fixed") -> 1 | D20: SEC-N3: repo copy of the Xero function.
A21: Open | B21: 15 | C21: =COUNTIF('New Issues'!$G$5:$G$41,"Open") -> 1 | D21: CP-NEW-1 (OneDrive "Connected" check).
A22: Andy to decide | B22: 3 | C22: =COUNTIF('New Issues'!$G$5:$G$41,"Andy to decide") -> 0 | D22: Contra to Xero decided and done (minus line).
A23: Needs check | B23: 3 | C23: =COUNTIF('New Issues'!$G$5:$G$41,"Needs check") -> 0
A24: Finance ↔ Projects links (88)
A25: Working | B25: 30 | C25: =COUNTIF('Finance-Projects Map v3'!$J$5:$J$92,"Working") -> 40 | D25: 13 links changed: materials ↔ PO links, calendars, proof of works, retention dates, Getting Started.
A26: Partial | B26: 19 | C26: =COUNTIF('Finance-Projects Map v3'!$J$5:$J$92,"Partial") -> 20
A27: Broken | B27: 4 | C27: =COUNTIF('Finance-Projects Map v3'!$J$5:$J$92,"Broken") -> 4
A28: Missing | B28: 29 | C28: =COUNTIF('Finance-Projects Map v3'!$J$5:$J$92,"Missing") -> 18 | D28: See the map page and Proposals.
A29: Needs check | B29: 6 | C29: =COUNTIF('Finance-Projects Map v3'!$J$5:$J$92,"Needs check") -> 5
A30: Not needed | B30: 0 | C30: =COUNTIF('Finance-Projects Map v3'!$J$5:$J$92,"Not needed") -> 1 | D30: L43 (SoW waste → yard).
A31: Still to do
A32: Items on the list | B32: n/a | C32: =COUNTA('Still to do'!$B$5:$B$36) -> 32
A33: …your tasks | B33: n/a | C33: =COUNTIF('Still to do'!$D$5:$D$36,"You (Andy)") -> 5 | D33: 3 now + 2 waiting for you to ask.
A34: Blue = typed in from v2. Black = worked out live from the other tabs (they update if you change a status).
A36: What you need to do
A37: 1. Turn on leaked-password protection | B37: Supabase › Authentication › Attack Protection. One switch (SEC-L10).
A38: 2. Reconnect OneDrive and revoke the old Microsoft sessions | B38: The database now hides the tokens, but old ones may have been read before 25 Oct (SEC-C1). Admin Centre › Integrations, then Microsoft Entra › Revoke sessions.
A39: 3. Press Push origin for the 26–27 Oct changes, if you haven't | B39: Send pop-up, invoice jobs, purchase invoices table, driver time off, laptop polish, Sales column.
A41: What's left (top of the Still to do tab)
A42: Private file storage (SEC-H3) | B42: Files are limited to your company in the app, but a file's exact web link still opens for anyone.
A43: Repo copy of the Xero function (SEC-N3) | B43: Copy the live version in, so a redeploy can't undo the contra line.
A44: Driver "received" mark (map L41) | B44: Check the database lets a driver write it; otherwise move it to the server.
A45: Site variations at £0 (map L22) | B45: The last Broken money link that reaches the client.
A46: Holiday approvals and device lock (CORE-M7, CORE-M3) | B46: Both are only checked in the app; each needs a database rule.
A48: Tabs in this workbook
A49: Changes since v2 | B49: Every change from 25 to 27 Oct: date, area, what changed, where to see it, and whether it is live.
A50: Bugs Now | B50: The 137 bugs: status in v2, status now, what changed and the evidence. Open first.
A51: Security Now | B51: The 33 security items against the database and server as they are now.
A52: New Issues | B52: The 37 issues found on 24 Oct evening, with their status now.
A53: Still to do | B53: One list of everything open or partly fixed, plus your tasks, most important first.
A54: Finance-Projects Map v3 | B54: The 88 links, as on the "Projects ⇄ Finance" map page, with v2 and current status.
A55: Proposals, Competitors, Capability Gap, Top 25 Ideas | B55: Copied from v2 unchanged.
A56: Roadmap | B56: The v2 order of work, with what is done now.

Sheet Changes since v2
A1: Changes since v2 (24 Oct evening) up to 27 Oct morning
A2: Everything up to the 27 Oct change is on your laptop. "Live" = pushed (or a database/server change, live straight away). "Live after Push origin" = on the laptop; it goes live when you press Push origin, if you haven't already.
A4: Date | B4: Area | C4: What changed | D4: Where to see it | E4: Live? | F4: Evidence
A5: 25 Oct | B5: Whole app | C5: Fix round 2, core: links that could run a script are closed; "Remember me" keeps the email only; big lists load in pages; bank holidays after 2028; offline page; admin console stays signed in on a bad signal. | D5: Everywhere | E5: Live | F5: 499b04b; out/fix2/core-done.md
A6: 25 Oct | B6: Projects | C6: Fix round 2: 36 Projects bugs fixed (reports, briefings, price builder, templates, RAMS/COSHH builders, permits, check-in, snags, certificates, inductions, schedule). | D6: Projects pages | E6: Live | F6: 160eed7; out/fix2/projA-done.md
A7: 25 Oct | B7: Projects | C7: Fix round 2: materials, HAVS, LOLER, one-person messages, PPE PDF, deliveries; a job link with a made-up job id now goes home. | D7: Projects pages | E7: Live | F7: 7579042; out/fix2/projB-done.md
A8: 25 Oct | B8: Finance | C8: Fix round 2: lists load in pages, retention "still held" everywhere, records in Xero protected, number clashes retried, stuck inbox invoices recovered. | D8: Finance pages | E8: Live | F8: c473337; out/fix2/finance-done.md
A9: 25 Oct | B9: Database | C9: Integrity: duplicate numbers refused, file paths checked for safety (H1/H2), search path fixed (L3), contra column for subcontract payments. | D9: — | E9: Live (database) | F9: sec_round2_a_integrity
A10: 25 Oct | B10: Security | C10: Security batch 1: OneDrive tokens server-only (C1), price files (H4), check-ins (H5), manager-only approvals (H6), company settings admin-only (M2), profile guard (M3), sign as yourself (M4), prices (M5). | D10: — | E10: Live (database) | F10: /home/claude/sql/1 - OpHUB security batch (25 Oct).sql
A11: 25 Oct | B11: Security | C11: Batch 2: materials/PO lock, delivery dates, delivery problem, invoice query, new message types. | D11: — | E11: Live (database) | F11: /home/claude/sql/2 - OpHUB materials and orders (25 Oct).sql
A12: 25 Oct (confirmed 27 Oct) | B12: Security | C12: Batch 3: files readable only inside your company (H3, buckets still public), shared folders per company (M6), webapp storage closed (M9), yard cost edits (M11), function access (L1, L2), device id fix (L4), orphan deletes (L6), clients kept out of company lists (M1), Finance project checks (N2). | D12: — | E12: Live (database) | F12: /home/claude/sql/3 - OpHUB security batch 3 (25 Oct).sql; ea36726
A13: 25 Oct | B13: Server | C13: 15 server functions redeployed: email links and daily limits, OneDrive upload checks, password reset limit, website allow-list, finance inbox (key header, supplier check), Xero v10 (split bills per project and the contra line). | D13: — | E13: Live (server) | F13: claude/OpHUB edge function deploy - 25 Oct 2026 evening.md
A14: 25 Oct | B14: Finance › Applications | C14: Proof of works: the Schedule of Works report goes with the application PDF, Excel and email (whole schedule, or photos since the last application). | D14: Application › Download PDF / Excel / Email | E14: Live | F14: 6d0375b; 9219zo
A15: 25 Oct | B15: Calendars | C15: Application dates show on the site and all-projects calendars for PMs, admins, estimators and QSs. | D15: Job calendar; all-projects calendar | E15: Live | F15: 6d0375b; 9219zp
... A43: Decided | B43: Back button | C43: FB-21: the "up one level" Back is for managers only. | D43: Projects pages | E43: Live | F43: c473337 (9219v:264)

Sheet Bugs Now
A1: Bugs Now: the 137 bugs, status on 27 Oct
A2: Every v2 row carried forward. Status now is only "Fixed" where a fix report or commit backs it up. Open first, then worst first.
A4: ID | B4: Severity | C4: Part of app | D4: Area | E4: Title | F4: Status in v2 | G4: Status now | H4: What changed | I4: Fixed on | J4: Evidence (done report / commit / file:line) | K4: v2 evidence | L4: v2 note
A5: CORE-M7 | B5: Medium | C5: Core 000-260 | D5: Leave approval and limits only checked in the client | E5: status:'approved' (admin or sick), the allowance check and the "max off at once" check are all decided in the browser. hrDecide is a plain d | F5: Open | G5: Open | H5: Not changed. Holiday approvals and limits are still only checked in the app; needs a database rule. | J5: core-done: "Not done (server only)"; hr_leave is not in security batches 1-3 | K5: 186-hr.js:174 dbInsert with status from the browser; 196 plain dbUpdate of status/decided_by | L5: Server-side trigger/RLS is Needs check.
A6: CORE-M3 | B6: Medium | C6: Core 000-260 | D6: Device lock only checked in the client | E6: signIn() saves the session to storage before the device-lock check. The lock is only checked at sign-in and app open, and nothing else (chec | F6: Open | G6: Partly fixed | H6: The app now saves the sign-in only after the device check passes. The server still doesn't check the device when someone checks in. | I6: 25 Oct | J6: core-done: 070:37-56, 050:105, 140:144/158, 150:94-108 (499b04b). Server part not done. | K6: 070-auth.js:50-51 saves SESSION before the device-lock check at 140:142-151 | L6: Nothing on the server enforces it (no SQL in repo).
A7: FA-15 | B7: Medium | C7: Finance 900-9219h | D7: Finance › Team (permissions) | E7: "Give Finance" quietly promotes the person to PM, and switching Finance off doesn't undo it | F7: Partly fixed | G7: Partly fixed | H7: Switching Finance off puts the old role back, but only on the device that gave Finance. The database column for it now exists; the app doesn't use it yet. | I7: 25 Oct | J7: finance-done: 908:218, 900:502 (localStorage); profiles.finance_prev_role added 25 Oct but unused (900:496 comment) | K7: 908:216-235 asks first ("also makes them a manager") and puts the old role back if Finance doesn't switch on. This covers the silent RLS refusal too, because 900:435 returns without setting finance_enabled. | L7: Switching Finance off still doesn't restore the earlier role, and the role is still changed before Finance access is confirmed.
A8: CORE-L11 | B8: Low | C8: Core 000-260 | D8: Malformed % in the URL crashes the page | E8: decodeURIComponent on from / reset parameters isn't wrapped in try/catch. | F8: Open | G8: Partly fixed | H8: Fixed on the sign-in and Team pages. The Schedule of Works page can still crash on a cut-off link. | I8: 25 Oct | J8: core-done: 140:21-23, 260:941; still open at 480:854 | K8: 260:937 and 140-login.js:21 decodeURIComponent without try/catch
A9: PA-38 | B9: Low | C9: Projects 270-589 | D9: Main contractor tiles | E9: MC tile hiding and the induction count | F9: Open | G9: Partly fixed | H9: The induction count is right now. Hidden tiles can still be opened by a direct link. | I9: 25 Oct | J9: projA-done: 510:66; route gating in 890 not done (no mc_hidden_tiles check in 890) | K9: 510:55, 62 counts every completion row, including leavers and repeats
A10: CORE-C1 | B10: Critical | C10: Core 000-260 | D10: XSS / navigation | E10: The header back arrow is built as onclick="goBack('${opts.back}')" with no escaping. opts.back can come from (a) the ?from= query on #/team, | F10: Partly fixed | G10: Fixed | H10: Every back arrow, tab bar and sidebar link is now checked or escaped, and a job link with a made-up job id goes back home. Small gap left: in Finance-only companies the job's Finance link skips the new job check. | I10: 25 Oct | J10: core-done: 130:104-184, 125:81, 260:941, 200:~205 (499b04b); projB-done: 890:229-250 (7579042) | K10: 130-shell.js:141 now goBack('${jsAttr(opts.back)}'). 260:937 and 480:854 still decodeURIComponent(from) with no check. 130:180 go('${t.href}') and 125:81 go('${i.go}') are still unescaped. | L10: The no-tap ?from= XSS is closed. The tab bar is still open: the route site id is never checked against SITES (890:202–203), and pages such as renderVariations (800:142) pass it to tabbar(). So #/site/x'-alert(1)-'/snagging/variations should still run script when any bottom tab is tapped (Needs check in Safari/Chrome: ' is not percent-encoded in a fragment). Use jsAttr in tabbar and the desktop sidebar too.
A11: CORE-H1 | B11: High | C11: Core 000-260 | D11: Stored XSS | E11: Device Locks puts d.device_id raw into onclick="approvePendingDevice('…')" / unlockDevice('…'). The device id is chosen by the client: getDe | F11: Fixed | G11: Fixed | H11: Fixed before v2. | I11: 24 Oct | K11: 260:910, 911, 920 now use jsAttr(d.device_id) | L11: Client side only. Whether check_device_lock_v2 checks the id's format is still Needs check (no SQL in repo).
A12: CORE-H2 | B12: High | C12: Core 000-260 | D12: XSS / broken button (superadmin) | E12: onclick="resetPassword('${escapeHtml(p.email)}')" uses escapeHtml inside a JS string. The browser turns &#39; back into ' before running the | F12: Fixed | G12: Fixed | H12: Fixed before v2. | I12: 24 Oct | K12: admin.html:485 resetPassword('${jsAttr(p.email)}') | L12: admin.html's own jsAttr (line 221) still doesn't escape \n / \r like the app's _jsEsc (030:194). That's minor, because an email address can't contain a newline.
A13: FA-01 | B13: High | C13: Finance 900-9219h | D13: Settings / invoice numbering | E13: Saving Finance settings can wind the invoice counter back, giving duplicate invoice numbers | F13: Fixed | G13: Fixed | H13: Fixed before v2. | I13: 24 Oct | K13: 900:158-160, 173. The invoice and job counters are only sent when the box differs from its defaultValue (or when there is no settings row or job number yet). The 9219o:85-99 wrapper still calls the base save. | L13: Someone can still type a lower number on purpose. There is no server-side floor (RPC or conditional update) as the finding suggested.
A14: FA-03 | B14: High | C14: Finance 900-9219h | D14: Purchase invoice inbox (auto-filing) | E14: Two people (or a phone and a computer) opening Finance at once file the same emailed invoice twice | F14: Fixed | G14: Fixed | H14: Fixed before v2. | I14: 24 Oct | K14: 9219b:56, 66 and 92-93. Each write is conditional on the row still being new: dbUpdate('fin_inbox', id+'&status=eq.new', …). The {status:'filed'} claim happens before the insert, and the item goes back to new if the insert fails (9219b:97). | L14: This is client-side only. There is still no unique index on purchase_invoices (DB check), so a browser that dies between claim and insert leaves the item "filed" with no invoice. See NEW-04 for a misleading toast.
A15: FA-04 | B15: High | C15: Finance 900-9219h | D15: Reports › Cash flow forecast | E15: The cash flow forecast counts money in without VAT and money out with VAT | F15: Fixed | G15: Fixed | H15: Fixed before v2. | I15: 24 Oct | K15: 913:87 uses finInvOutstanding(i) (gross) for invoices. Applications are ×1.2 when standard-rated, suppliers use total. | L15: All columns now include VAT.
A16: FA-05 | B16: High | C16: Finance 900-9219h | D16: The job "book" and reports | E16: Large lists are probably cut off at 1,000 rows, which silently drops costs from jobs and reports | F16: Open | G16: Fixed | H16: Finance lists now load in pages of 1,000 with no cap. (Assumes the server's row cap is 1,000 or more.) | I16: 25 Oct | J16: finance-done: 900:38 finSelectAll; 911:14 and 15 other files | K16: 911:20-36 (limit=5000/10000/20000/50000), 9219b:111-115, 9219:97-101, 9219zi:19. dbSelect (060:88-122) never pages. There is no dbSelectAll anywhere. | L16: It doesn't bite yet: live data is 51 sign-ins and 10 purchase invoices in total. It still needs paging, or a server-side aggregate, before real volumes arrive.
A17: FA-06 | B17: High | C17: Finance 900-9219h | D17: Subcontract applications (CIS) | E17: CIS on subcontractor applications is worked out after contra charges are taken off | F17: Fixed | G17: Fixed | H17: Fixed before v2. | I17: 24 Oct | K17: 912:210-228: gross = net + contraNow, labour = gross − newMat, cis = labour × rate. 912:279-283 stores gross and labour before the contra on fin_sub_payments. | L17: The fix introduced a problem: NEW-01. The deployed Xero push_sub_payment now posts a bill that includes the contra, so Xero leaves the contra amount owing.
A18: FB-01 | B18: High | C18: Finance 9219i-922 | D18: Finance lists: automatic totals bar, Title Case and column filters | E18: Totals-bar observer re-triggers itself every 60 ms, forever | F18: Fixed | G18: Fixed | H18: Fixed before v2. | I18: 24 Oct | K18: 9219x:114-117: the observer ignores mutations inside .finautofoot/.finsfoot/.fcf-row/.navcrumbs and added nodes of those classes.
A19: FB-02 | B19: High | C19: Finance 9219i-922 | D19: Applications for payment: autosave | E19: Application autosave doesn't record what it saved, so the next redraw throws away unsaved changes (e.g. "Use site progress") | F19: Fixed | G19: Fixed | H19: Fixed before v2. | I19: 24 Oct | K19: 9219ze:36: after a successful PATCH, finApp.__loaded is set to the returned updated_at, so 902:494 keeps the in-memory copy. 9219ze:76-81 queues an autosave after "Use site progress". | L19: A tiny race remains: a render that lands while an autosave is still in flight can still reload.
A20: FB-03 | B20: High | C20: Finance 9219i-922 | D20: Variations register ↔ draft applications | E20: Draft application counts a site variation twice after it is imported into the register | F20: Fixed | G20: Fixed | H20: Fixed before v2. | I20: 24 Oct | K20: 9219s:269-273 links variation_id-only rows to their register copy (sets fin_variation_id) before deciding what to add.
A21: FB-04 | B21: High | C21: Finance 9219i-922 | D21: Application / Certificate summary after certification | E21: Certified applications show wrong "Certified" figures in the summary (£0 on older certificates; variations taken from the previous certificate) | F21: Fixed | G21: Fixed | H21: Fixed before v2. | I21: 24 Oct | K21: 9219p:941-969 (fix 16): when cert_net is set, the Certified column comes from cert_gross/cert_discount/cert_retention/cert_previous/cert_net. Line splits come from cert_lines when present, otherwise a dash. 9219p:971-979 reads the application's own cert_lines for vars and days.
A22: FB-05 | B22: High | C22: Finance 9219i-922 | D22: Whole app (statements reader) | E22: A regex lookbehind in the statements file can stop the whole app loading on older iPhones | F22: Fixed | G22: Fixed | H22: Fixed before v2. | I22: 24 Oct | K22: 9219l:39-40: the lookbehind is built with new RegExp inside try/catch, with a fallback. No other lookbehind literal is left in src/js (grep).
A23: PB-01 | B23: High | C23: Projects 590-890 | E23: H&S Policy sign-in gate re-appears on every app launch after the annual re-sign | F23: Fixed | G23: Fixed | H23: Fixed before v2. | I23: 24 Oct | K23: 640:143 sigs.filter(s=>s.user_id===ME.id).pop() (newest)
A24: CORE-M1 | B24: Medium | C24: Core 000-260 | D24: Token / secret handling | E24: Integrations loads onedrive_connections with select=* (no column list) just to check odConn.access_token. Any admin's browser therefore rece | F24: Fixed | G24: Fixed | H24: Fixed before v2. | I24: 24 Oct | K24: 260:112 select=org_id,account_email,folder_path,connected_at; 260:286 tests odConn only | L24: Column grants on the token columns are still Needs check (server). Devices that opened Integrations before the fix still have the full row cached (see NEW-2).
A25: CORE-M2 | B25: Medium | C25: Core 000-260 | D25: Remember-me password | E25: "Remember my email & password" stores the password in plain text in localStorage.ophub_remember. doSignOut never clears it, and the login fo | F25: Open | G25: Fixed | H25: "Remember me" now keeps the email only. Any old saved password is wiped when the app starts. | I25: 25 Oct | J25: core-done: 040:44-60, 140:76-135, 070:80 (499b04b) | K25: 140-login.js:133 stores {email, password}; 140:74 pre-fills the password; 070:66-80 doSignOut never removes ophub_remember
A26: CORE-M4 | B26: Medium | C26: Core 000-260 | D26: Wrong counts (roster includes people who can't sign) | E26: The RAMS "outstanding" roster is every site_assignments user (operatives plus clients, drivers, site managers, PMs). Clients are view-only a | F26: Open | G26: Fixed | H26: RAMS "outstanding" now lists operatives only. | I26: 25 Oct | J26: core-done: 190:113-115, 200:114, 230:62 | K26: 190:84 rosterBySite = every assignment (RAMS uses it at 190:113); 200:77-78; 230:39-40, 61 | L26: Only the COSHH roster (190:91-92) is limited to operatives.
A27: CORE-M5 | B27: Medium | C27: Core 000-260 | D27: Data cut off at 1000 rows | E27: These queries have no limit (or a limit above the server cap) and are sorted oldest first. If the project uses Supabase's default max_rows = | F27: Open | G27: Fixed | H27: Check-in, PPE and holiday lists load in pages of 1,000, so nothing is cut off. "On site now" uses the latest check-in. | I27: 25 Oct | J27: core-done: 060:187 dbSelectAll; 260:161/170; 186:100; 185:507. Assumes the server row cap is 1,000 (not confirmed). | K27: 260:159 (checkins, asc, no limit), 260:166, 185:505 (asc, no limit), 186:65 limit=2000 | L27: dbSelectNet (060:105) does no paging.
A28: CORE-M6 | B28: Medium | C28: Core 000-260 | D28: Signed out because storage is full | E28: On the web, every successful dbSelect response (up to 300 whole result sets), the signed-link map (up to 4000 URLs) and the boot snapshot al | F28: Open | G28: Fixed | H28: If the phone's storage is full, the app clears old saved copies so the sign-in still saves. | I28: 25 Oct | J28: core-done: 050:105 persistSession; 060:57-89 | K28: 050:76 await setJSON(K_SESSION…) result not checked; 040:39 sset returns false/null on failure; 060:21 cap is 300 entries, not bytes
A29: CORE-M8 | B29: Medium | C29: Core 000-260 | D29: Calendar export on the phone app | E29: deliverIcsFile calls window.open(publicUrl('site-photos', …), '_system'). Once site-photos is private, the 065 wrapper opens about:blank fir | F29: Open | G29: Fixed | H29: Calendar files open through a signed link and never leave a blank page. | I29: 25 Oct | J29: core-done: 060:605-608, 065:184-197 | K29: 060:505 window.open(publicUrl('site-photos', stored), '_system'); 065:181 falls back to location.href = u | L29: The 065 wrapper runs even while the bucket is public (065:17-18), so this can happen now whenever no signed link is cached.
A30: FA-08 | B30: Medium | C30: Finance 900-9219h | D30: Retention card, Sales › Retention, the retention ledger, forecast retHeld, and the home tile "Retention held by clients" | E30: "Retention held" never goes down after retention release invoices | F30: Partly fixed | G30: Fixed | H30: "Still held" retention is used everywhere: home tile, ledger and reports. | I30: 25 Oct | J30: finance-done: 911:170, 913:64, 914:91 | K30: New finRetentionReleased / finRetentionStillHeld at 903:151-156. Used by the project tile (9219n:210, 9219q:37), the Retention card (9219n:263), Sales › Retention (9219:140) and the Detailed Summary (9219v:39). | L30: Still gross held in three places: the home "Retention held by clients" (914:89-90), the Retention ledger report (913:64) and the forecast/overview retHeld (911:168, which feeds the 913 overview "Retention held" column).
A31: FA-09 | B31: Medium | C31: Finance 900-9219h | D31: Applications | E31: After an earlier certificate comes in lower, a later submitted application shows a different amount due on screen than in its stored figures and Excel, and "Email again" silently rewrites it | F31: Fixed | G31: Fixed | H31: Fixed before v2. | I31: 24 Oct | K31: 902:496-500: a locked application uses the stored a.previous, and only drafts recompute it. There is an orange note when the live figure differs. 902:822: "Email again" only saves drafts. The 9219p:74/388 saves need #finAppSave, which a locked application doesn't render (902:552). The 9219ze autosave is off when locked (9219ze:10).
A32: FA-10 | B32: Medium | C32: Finance 900-9219h | D32: Xero sync (sales invoices) | E32: Xero works out VAT line by line, OpHUB on the whole invoice, so totals can differ by a penny or two | F32: Fixed | G32: Fixed | H32: Fixed before v2. | I32: 24 Oct | K32: 901:30-33 rounds VAT per line (finRound(a*c.r/100)) before summing, as Xero does. | L32: Old issued invoices are recomputed on screen from their lines and may now show 1p different from their stored total. The deployed edge function's 2p warning threshold is unchanged.
A33: FA-11 | B33: Medium | C33: Finance 900-9219h | D33: Xero sync (bills, operative invoices) | E33: Records already in Xero can still be changed, cancelled or rejected in OpHUB, leaving Xero out of step | F33: Partly fixed | G33: Fixed | H33: Changing a record already in Xero is blocked unless you confirm you will change Xero too; with no signal it stops. | I33: 25 Oct | J33: finance-done: 904:314-332, 910:169, 9219g:211-220, 917:127-207 | K33: It warns rather than blocks. finXeroPostedConfirm (904:312-317) is used for Reject (904:319), line coding (9219g:189-190), and operative invoice Save and Cancel (9219g:203-222). | L33: Edit, Cancel and Reject are still possible on records already in Xero, and nothing is pushed to Xero. The Split / allocate pop-up (917 openFinSplit) still has no warning.
A34: FA-12 | B34: Medium | C34: Finance 900-9219h | D34: Invoices | E34: The Sales page deletes anyone's brand-new invoice draft while they are still typing it | F34: Fixed | G34: Fixed | H34: Fixed before v2. | I34: 24 Oct | K34: 9219:82-90 only deletes empty drafts that are yours and over 24 h old, or anyone's over 7 days. 901:211 and 232 toast "This draft no longer exists" when the update matches 0 rows. | L34: Side effect, see NEW-05: young empty drafts are hidden from the list but not deleted.
A35: FA-13 | B35: Medium | C35: Finance 900-9219h | D35: Labour / job costs | E35: Materials supplied by operatives are never charged to any job | F35: Fixed | G35: Fixed | H35: Fixed before v2. | I35: 24 Oct | K35: 911:75-86 adds a "Materials supplied by operative" cost line (cat materials), shared by labour value across the invoice's job lines. It feeds the costs ledger, forecast and reports. | L35: The Labour card (finJobLabour, 9219c) leaves it out on purpose.
A36: FA-14 | B36: Medium | C36: Finance 900-9219h | D36: Subcontract CIS | E36: Marking a subcontract application paid doesn't check that its CIS record was saved | F36: Fixed | G36: Fixed | H36: Fixed before v2. | I36: 24 Oct | K36: 912:268-296 checks for an existing CIS row with dbSelectChecked and inserts fin_sub_payments first. The application is only marked paid after that row saves. A paid application with no CIS row gets an "Add it to the CIS return" button (912:203-207). | L36: There is no unique index on fin_sub_payments(sub_app_id) (DB check). The once-guard covers double taps.
A37: FA-16 | B37: Medium | C37: Finance 900-9219h | D37: Numbering | E37: Application, variation and subcontract numbers are worked out in the browser as "last + 1", so two people can get the same number | F37: Partly fixed | G37: Fixed | H37: Numbers retry if someone takes the same one at the same moment, and the database now refuses duplicates. | I37: 25 Oct | J37: finance-done: 912:100, 911:393, 9219s:244; unique indexes applied 25 Oct | K37: Applications: 902:460-476 retries on 409, backed by DB unique fin_applications_site_id_number_key, so this part works. Variations: 9219s:326-345 renumbers after the insert if it finds a clash. Subcontracts / sub applications: 912:93-109 retry on 409. | L37: There are no unique indexes on fin_variations(site_id,seq), fin_subcontracts(site_id,seq) or fin_sub_apps(subcontract_id,number) (DB check), so the 912 retry never fires. The variation check-and-renumber can still race three ways. Day works (saveFinDaywork) are not covered.
A38: FA-17 | B38: Medium | C38: Finance 900-9219h | D38: Wage pushes / PM Price tile | E38: Wage pushes booked on a price are never removed from that price when withdrawn, and re-sending books them twice (dormant in trial) | F38: Fixed | G38: Fixed | H38: Fixed before v2. | I38: 24 Oct | K38: 9217:44-58 finWagePushWithdraw sets the push to withdrawn and amount 0, and zeroes its price entry (with a roll-up when there is no price sheet). It is used by 9217:36 and 9219c:236. 9217:105-113 locks the buttons while booking and re-reads the push (dbSelectNet, status must be pending). | L38: A re-book creates a new entry; the old one stays at £0, so nothing is double-counted.
A39: FA-18 | B39: Medium | C39: Finance 900-9219h | D39: Project summary / reports | E39: The forecast's "Expected final value" includes variations not yet agreed, but the label says agreed only | F39: Partly fixed | G39: Fixed | H39: Labels now say the forecast includes submitted variations, and show how much. | I39: 25 Oct | J39: finance-done: 911:223, 9219zm:43/88, 9219q, 9219zj:64 | K39: Only the 913 report column labels changed: "(incl. submitted variations)" at 913:28, 33 and 38. | L39: Still in place: 911:142 ffa = contract + vAgreed + vPending and 911:221 "Contract plus agreed variations". New instance: 9219zj:64 headline subline (NEW-02).
A40: FA-19 | B40: Medium | C40: Finance 900-9219h | D40: Retention | E40: Retention release invoices ignore later certificates that change the amount held | F40: Fixed | G40: Fixed | H40: Fixed before v2. | I40: 24 Oct | K40: 903:139-147 finRetHalfAmt: the second half is held minus the first-half invoice's net, and an invoiced half shows its invoice amount. Used in 903:204 (raise) and 9219n:264 (card). If nothing is left to release, raising says so (903:205).
A41: FA-20 | B41: Medium | C41: Finance 900-9219h | D41: Job finance page / plant | E41: The first job-cost card on the project page counts plant hire twice when its cost comes from the hire company's invoices | F41: Partly fixed | G41: Fixed | H41: Plant hire costed from the hire company's invoices is no longer counted twice. | I41: 25 Oct | J41: finance-done: 900:278, 917:90 | K41: 910:229-245 wraps finPlantCardHtml to leave invoice-costed hires out of "Plant to date". | L41: Still unfiltered: 900:229 (hires.reduce(...finPlantCost) in the first job-cost card) and 917:89 (FIN_SPLIT_TABLES.fin_plant_hires.net, the value in the split pop-up).
A42: FB-06 | B42: Medium | C42: Finance 9219i-922 | D42: 922 once-guard × Xero auto-post | E42: The once-guard silently drops Xero posts that overlap (bulk approve posts only the first bill) | F42: Fixed | G42: Fixed | H42: Fixed before v2. | I42: 24 Oct | K42: 922:19: the guard key for finXeroPush is name+kind+id. finXeroAuto (907:150) calls it by global name, so it gets the wrapped version.
A43: FB-07 | B43: Medium | C43: Finance 9219i-922 | D43: Bill of Quantities autosave | E43: BoQ autosave can duplicate the whole Bill of Quantities (a failed read, or overlapping with Save) | F43: Fixed | G43: Fixed | H43: Fixed before v2. | I43: 24 Oct | K43: 9219n:507-509 uses a checked read that throws if it fails. 9219n:531-539: manual Save waits for a running autosave and blocks autosave while it runs.
A44: FB-08 | B44: Medium | C44: Finance 9219i-922 | D44: Certify | E44: Certificate save wrapper writes or wipes cert_lines before validating, and loses them if the save is retried | F44: Fixed | G44: Fixed | H44: Fixed before v2. | I44: 24 Oct | K44: 9219n:876-880 only writes cert_lines when finCertLines is set, never null, and no longer clears it. A retry therefore keeps the lines. | L44: It is still a separate write made before the base save validates. Harmless: it is overwritten on a successful certify.
A45: FB-09 | B45: Medium | C45: Finance 9219i-922 | D45: Certify from client's Excel | E45: Uploading the client's certificate Excel ignores their variation and day-work figures | F45: Fixed | G45: Fixed | H45: Fixed before v2. | I45: 24 Oct | K45: 9219p:367-370: the base returns variation (var_index) and day-work (day_index) lines. The wrapper at 9219p:590-598 copies them into W.vars / W.days before finCertRecalc().
A46: FB-10 | B46: Medium | C46: Finance 9219i-922 | D46: Project Overview › Needs attention | E46: "Needs attention" buttons double-escape the client name, so names with &, ' or " break | F46: Fixed | G46: Fixed | H46: Fixed before v2. | I46: 24 Oct | K46: 9219n:234 builds js with _jsEsc (JS-only escaping). 9219n:237 escapes it once for HTML.
A47: FB-11 | B47: Medium | C47: Finance 9219i-922 | D47: Invoices: client default VAT | E47: Reopening a saved draft invoice silently changes its line VAT to the client's default | F47: Fixed | G47: Fixed | H47: Fixed before v2. | I47: 24 Oct | K47: 9219n:937-939: the client default replaces l.vat===dflt only when updated_at===created_at. DB: both columns default to now(), and saveFinInvoiceDraft sets updated_at (901:204).
A48: FB-12 | B48: Medium | C48: Finance 9219i-922 | D48: Finance list filters (CSS) | E48: Filter bars and search boxes are hidden on Purchases, Directory › Suppliers and Yard stock (nothing left to filter with on phones) | F48: Fixed | G48: Fixed | H48: Fixed before v2. | I48: 24 Oct | K48: 9219s:315-319 scopes the hiding rules to .finprojfilt (914:158). Other .finjobfilt bars show on phones. | L48: On desktop (≥701px), every non-project filter bar is still hidden in favour of the column filters. That includes the Purchases "Sort" drop-down and the search box that 9219k moves into the bar.
A49: FB-13 | B49: Medium | C49: Finance 9219i-922 | D49: Yard stock (Finance and Material Requests) | E49: Yard pop-ups can open behind the one you tapped from | F49: Fixed | G49: Fixed | H49: Fixed before v2. | I49: 24 Oct | K49: 9219m:108, 170 and 234: each yard overlay calls document.body.appendChild(ov) when it opens, so it ends up on top.
A50: FB-14 | B50: Medium | C50: Finance 9219i-922 | D50: Application Excel round trip | E50: Uploading the same application Excel twice adds the new lines twice | F50: Fixed | G50: Fixed | H50: Fixed before v2. | I50: 24 Oct | K50: finXlSameLine at 9219n:789 is used in the old layout (9219n:810) and the new one (9219p:333-336, items, variations and day works). | L50: A genuinely new line with the same description and value as an existing one is now skipped too. The toast does say how many lines were skipped.
A51: PA-01 | B51: Medium | C51: Projects 270-589 | D51: Site reports | E51: Report multi-select carries over between jobs | F51: Open | G51: Fixed | H51: Ticked reports are cleared when you open another job. | I51: 25 Oct | J51: projA-done: 430:66, 430:90 (160eed7) | K51: 430:6 global Set; 430:241-252 deletes every ticked id, whatever the site | L51: Same set is shared with PM Home's report list (185:267-321). Reports ticked there across several jobs show up as "Delete N Selected" on any job's Reports page. The activity log goes to the site on screen.
A52: PA-02 | B52: Medium | C52: Projects 270-589 | D52: Site reports / Daily briefings | E52: Reports list includes Daily Briefings, MC inspections and LOLER, and signed briefings can be edited from there | F52: Open | G52: Fixed | H52: Daily briefings are out of the Reports list, and a signed briefing opens read-only. (The database doesn't block edits yet.) | I52: 25 Oct | J52: projA-done: 430:77, 430:302 | K52: 430:62 report_submissions?site_id=eq.X with no template-flag filter; 430:61 template list unfiltered | L52: Fill lock still only on the briefing route.
A53: PA-03 | B53: Medium | C53: Projects 270-589 | D53: Daily briefings | E53: Emailed briefing PDF has no signatures | F53: Open | G53: Fixed | H53: The emailed briefing PDF now includes the signatures. | I53: 25 Oct | J53: projA-done: 430:1789 | K53: 430:1099 Email → emailReportPDF; 430:1766 buildReportPdf (no signatures); 430:1774 reuses built.storedPath | L53: Bulk email (700:227-262) does use buildBriefingPdfWithSignatures.
A54: PA-04 | B54: Medium | C54: Projects 270-589 | D54: Price builder → pricing elements | E54: Issued price-builder sheet can be invisible on multi-site jobs | F54: Open | G54: Fixed | H54: On a job with several addresses, issuing a price sheet asks which address it is for. | I54: 25 Oct | J54: projA-done: 400:736, 400:818 | K54: 400:742 sub_site_id: …multi_site ? (priceSubAddrSelected[siteId]||null) : null | L54: No check that an address is chosen.
A55: PA-05 | B55: Medium | C55: Projects 270-589 | D55: Report templates | E55: Deleting a template question leaves its follow-ups hidden for good | F55: Open | G55: Fixed | H55: Deleting a question with follow-ups now asks what to do with them. | I55: 25 Oct | J55: projA-done: 420:510, 420:375 | K55: 420:505-508 plain splice; 420:375-382 move has no parent check
A56: PA-06 | B56: Medium | C56: Projects 270-589 | D56: RAMS library / RAMS builder | E56: Renaming a RAMS library item silently removes it from every template | F56: Open | G56: Fixed | H56: Renaming a RAMS library item renames it in every template too. | I56: 25 Oct | J56: projA-done: 588:127, 586:149 | K56: 588:127 renames title only; 586:117 byTitle match
A57: PA-07 | B57: Medium | C57: Projects 270-589 | D57: COSHH builder | E57: COSHH data-sheet upload overwrites an existing product with the same name | F57: Open | G57: Fixed | H57: A data sheet only updates a product with the same name and maker, and only fills blank boxes. | I57: 25 Oct | J57: projA-done: 589-coshh-builder-ui:267 | K57: 589-coshh-builder-ui.js:283-284 replaces data wholesale on a title-only match
A58: PA-08 | B58: Medium | C58: Projects 270-589 | D58: Permits | E58: Permit can be closed with no sign-off by the people assigned | F58: Open | G58: Fixed | H58: A permit can't be closed without sign-offs unless a manager confirms; the override is logged. | I58: 25 Oct | J58: projA-done: 520:271 | K58: 520:165 canClose ignores sign-offs; 520:259-279 closePermit doesn't check them
A59: PA-09 | B59: Medium | C59: Projects 270-589 | D59: Check-in/out | E59: Check-in "full history" export may be cut short | F59: Open | G59: Fixed | H59: The check-in export loads in pages, so it is complete. | I59: 25 Oct | J59: projA-done: 450:314 | K59: 450:268-270 one dbSelect order=ts.asc, no paging
A60: PA-10 | B60: Medium | C60: Projects 270-589 | D60: Assign team / OneDrive | E60: Assign Team reads the OneDrive access token into the browser | F60: Fixed | G60: Fixed | H60: Fixed before v2. | I60: 24 Oct | K60: 380:12 select=org_id; 380:21 row-exists check | L60: See NEW-1 about "connected" now meaning "row exists".
A61: PA-12 | B61: Medium | C61: Projects 270-589 | D61: Certifications | E61: Cert bundle and preview detect the file type from the display name | F61: Open | G61: Fixed | H61: The certificate file type is read from the file itself, not its display name. | I61: 25 Oct | J61: projA-done: 320:186, 320:367-380 | K61: 320:363, 367 test c.name; 320:245 tests the display name | L61: certDisplayName (320:173) helps null names on screen only.
A62: PA-13 | B62: Medium | C62: Projects 270-589 | D62: Activity history | E62: Activity history person filter persists across jobs | F62: Open | G62: Fixed | H62: Activity history filters reset when you change job. | I62: 25 Oct | J62: projA-done: 385:17 | K62: 385:8 global; 385:35 select hidden when ≤1 person
A63: PA-15 | B63: Medium | C63: Projects 270-589 | D63: Assign team | E63: Removing an operative from a job leaves the subcontractor link, and silent delete failures look like success | F63: Open | G63: Fixed | H63: Removing someone checks it worked and also removes their subcontractor link for that job. | I63: 25 Oct | J63: projA-done: 380:367 | K63: 380:365 raw DELETE (no empty-result check); subcontractor_operatives untouched
A64: PA-16 | B64: Medium | C64: Projects 270-589 | D64: Snagging | E64: Snag draft carries over to other jobs | F64: Open | G64: Fixed | H64: Each job keeps its own half-written snag. | I64: 25 Oct | J64: projA-done: 500:12 | K64: 500:3-5 global draft; 500:147-157 saves it on whichever siteId
A65: PA-33 | B65: Medium | C65: Projects 270-589 | D65: Check-in/out, multi-site check-in | E65: Check-in double tap and closed addresses | F65: Open | G65: Fixed | H65: Check-in reads the latest record first: no double check-ins and none at closed addresses. | I65: 25 Oct | J65: projA-done: 450:161, 450:261 | K65: 450:158-262: no check for a closed address or an already-open check-in | L65: The double-tap part was wrong: both functions are in the 890:464 wrapper and set checkinBusy.
A66: PB-02 | B66: Medium | C66: Projects 590-890 | E66: Ticked Material Requests carry over to other jobs and get sent under the wrong job | F66: Open | G66: Fixed | H66: Ticks and supplier are cleared when you open another job, and only this job's items are sent. | I66: 25 Oct | J66: projB-done: 890:11-26, 890:251, 760:590-594 (7579042) | K66: 720:39 global; 720:146-160 no reset on site change; 760:590 uses the on-screen siteId | L66: 730:17, 700:12 and 650:21 are the same.
A67: PB-03 | B67: Medium | C67: Projects 590-890 | E67: HAVS day badge adds up all operatives' points, so "ELV EXCEEDED" is shown wrongly | F67: Open | G67: Fixed | H67: The HAVS day badge uses the highest single person and shows how many are over. | I67: 25 Oct | J67: projB-done: 660:473-479 | K67: 660:432 sums every operative's entries; 660:443-444 compares the sum with 400/100
A68: PB-04 | B68: Medium | C68: Projects 590-890 | E68: HAVS minutes typed in are lost unless the user closes the day or changes week | F68: Open | G68: Fixed | H68: HAVS minutes save when you leave the page, put the app away, or press the new Save Minutes. | I68: 25 Oct | J68: projB-done: 660:214-246, 890:72-74 | K68: 660:52 drafts in memory; flushed only at 660:78, 270, 1005; no flush in go()/router
A69: PB-05 | B69: Medium | C69: Projects 590-890 | E69: LOLER entries can't be opened by operatives even when the tile is shown to them | F69: Open | G69: Fixed | H69: Operatives can open LOLER entries (read-only) on their job. | I69: 25 Oct | J69: projB-done: 890:346-356, 750:55-120 | K69: 750:98 links to snagging/reports; 890:254 manager-only
A70: PB-06 | B70: Medium | C70: Projects 590-890 | E70: Signed RAMS/COSHH exports include last year's signatures after a re-sign | F70: Open | G70: Fixed | H70: Signed RAMS/COSHH PDFs include only this cycle's signatures, one per person. | I70: 25 Oct | J70: projB-done: 610:120-140, 620:358 | K70: 610:125 and 620:358 load every signature; no cycle filter
A71: PB-07 | B71: Medium | C71: Projects 590-890 | E71: Single-person messages never appear in any in-app Inbox | F71: Open | G71: Fixed | H71: Messages to one person now show in their Inbox and the job's Messages. (Unread badges don't count them yet.) | I71: 25 Oct | J71: projB-done: 830:61-76; badges at 185:465, 200:60, 340:2112 not changed | K71: 830:58 writes audience:'single'; reads only operatives/managers (830:90-94, 256-257; 185:465; 200:60)
A72: CORE-L1 | B72: Low | C72: Core 000-260 | D72: Wrong mode from quick search | E72: Report results check status==='draft' for fill vs view and the "Draft" label. Report statuses are in_progress / submitted (430:71, 154; 435: | F72: Open | G72: Fixed | H72: In-progress reports open as drafts again. | I72: 25 Oct | J72: core-done: 136:57 | K72: 136-quick-search.js:57 r.status==='draft'
A73: CORE-L10 | B73: Low | C73: Core 000-260 | D73: admin.html signs out on any refresh failure | E73: ensureFreshToken calls clearSession() on any non-OK response (including 429/5xx). A network error throws out of sbFetch with nothing catchin | F73: Open | G73: Fixed | H73: The admin console no longer signs you out when the server is busy or the signal drops. | I73: 25 Oct | J73: core-done: admin.html:233-258 | K73: admin.html:241-243 clearSession() on any non-OK response; no try/catch around fetch (232) | L73: admin.html has no unhandledrejection handler.
A74: CORE-L2 | B74: Low | C74: Core 000-260 | D74: Missing org_id filters (relies on RLS only) | E74: These queries have no org_id=eq.ME.org_id, unlike their neighbours (e.g. the permanent invite on 260:107 has one). | F74: Open | G74: Fixed | H74: Lists now show only your own company's invites, people, PPE, check-ins and incidents. Check-ins, incidents and drawings are filtered in the app (the database has no company column on them). | I74: 25 Oct | J74: core-done: 260:106/161-170, 100:490, 230:20-21, 185:93, 136:58 | K74: 260:106, 100:482, 230:20, 260:159/166, 185:93/505, 136:53: none has org_id | L74: 136:40 !p.org_id || still passes everyone, because 100:482 doesn't select org_id.
A75: CORE-L3 | B75: Low | C75: Core 000-260 | D75: HUB due-date filters | E75: Messages and SOW photos use their created time as dueDate. | F75: Open | G75: Fixed | H75: Messages and SOW photos no longer show as "due". | I75: 25 Oct | J75: core-done: 200:132-183 | K75: 200:132 dueDate:new Date(a.latest), 200:139 dueDate: new Date(m.created_at)
A76: CORE-L4 | B76: Low | C76: Core 000-260 | D76: Role dropdown shows an unsaved value | E76: Admin › Users calls setUserRole(id, value) without the sel argument, so on Cancel nothing re-renders. | F76: Open | G76: Fixed | H76: Cancelling a role change in Admin › Users now puts the box back. | I76: 25 Oct | J76: core-done: 100:452, 170:153 | K76: 100-state.js:444 setUserRole('${p.id}', this.value) (no sel); 170:145 only re-renders if(sel)
A77: CORE-L5 | B77: Low | C77: Core 000-260 | D77: Bank holidays run out | E77: HR_BANK_HOLS is hard-coded to 2026-2028. | F77: Open | G77: Fixed | H77: Bank holidays are worked out for any year, not just 2026-28. | I77: 25 Oct | J77: core-done: 186:24-83 | K77: 186-hr.js:24-28 2026–2028 only
A78: CORE-L6 | B78: Low | C78: Core 000-260 | D78: Unsaved typing lost when signal returns | E78: The online event calls render() whenever OFFLINE_CACHE_USED. Home/Projects set that flag whenever the phone is offline. | F78: Open | G78: Fixed | H78: When signal comes back, a "tap to refresh" pill shows instead of the page redrawing while you type. | I78: 25 Oct | J78: core-done: 060:213-238 | K78: 060:141-144 online → if(OFFLINE_CACHE_USED) render()
A79: CORE-L7 | B79: Low | C79: Core 000-260 | D79: Previous user's filters kept after sign-out | E79: resetPerUserState doesn't reset hubFilterPmId, outstandingPmId, siteFilterPmIds, hubFilterSiteId, HR/HR_BH_ENSURED, pmReportsTpl/By. | F79: Open | G79: Fixed | H79: Filters are reset when someone else signs in on the same device. | I79: 25 Oct | J79: core-done: 100:23-30 | K79: 100-state.js:16-23: none of hubFilterPmId / outstandingPmId / siteFilterPmIds / hubFilterSiteId / HR / pmReportsTpl reset
A80: CORE-L8 | B80: Low | C80: Core 000-260 | D80: Emailed file link for a private bucket | E80: hrEmailPolicy sends file_url: publicUrl('mc-documents', …), and mc-documents is on the private list (065:19). | F80: Open | G80: Fixed | H80: The policy email now sends the file's storage path, and send-document-email (redeployed 25 Oct) uses it. | I80: 25 Oct | J80: core-done: 186:456; send-document-email v11 → v12 | K80: 186-hr.js:421 file_url: publicUrl('mc-documents', stored) | L80: send-document-email isn't in the repo (Needs check).
A81: CORE-L9 | B81: Low | C81: Core 000-260 | D81: Service worker offline fallback | E81: Any same-origin page that fails to load (sign.html, admin.html, index.html) falls back to the cached app.html. | F81: Open | G81: Fixed | H81: Other pages show a plain "You're offline" page instead of the app. | I81: 25 Oct | J81: core-done: sw.js:14-55 | K81: sw.js:42 hit || caches.match(APP_PAGE) for any same-origin navigation
A82: FA-21 | B82: Low | C82: Finance 900-9219h | D82: Invoice totals | E82: The PDF and screen VAT rows can be a penny different from the VAT total on mixed-rate invoices | F82: Fixed | G82: Fixed | H82: Fixed before v2. | I82: 24 Oct | K82: 901:30-36: each rate's VAT row is the sum of rounded line VAT, so the rows add up to vat.
A83: FA-22 | B83: Low | C83: Finance 900-9219h | D83: Applications | E83: The application Excel upload (older one-sheet layout) loses the daywork register link, so the daywork is counted twice on the next application | F83: Fixed | G83: Fixed | H83: Fixed before v2. | I83: 24 Oct | K83: 902:809 Object.assign({}, d, {description, value}) keeps fin_daywork_id.
A84: FA-23 | B84: Low | C84: Finance 900-9219h | D84: Bill of Quantities | E84: Saving the Bill of Quantities while the connection is bad can duplicate every line | F84: Fixed | G84: Fixed | H84: Fixed before v2. | I84: 24 Oct | K84: 902:221-223 uses dbSelectChecked. If the read fails it aborts with a toast. | L84: A row with an id that is missing from existing (deleted elsewhere) is still inserted as new. That is acceptable.
A85: FA-24 | B85: Low | C85: Finance 900-9219h | D85: Reports | E85: The aged debtors report says "Including VAT" but shows figures without VAT | F85: Fixed | G85: Fixed | H85: Fixed before v2. | I85: 24 Oct | K85: 913:73 note now says "Excluding VAT (as everywhere in Finance)".
A86: FA-25 | B86: Low | C86: Finance 900-9219h | D86: Reports | E86: "Labour by person" shows 0 days for operative invoices | F86: Fixed | G86: Fixed | H86: Fixed before v2. | I86: 24 Oct | K86: 913:101-107 takes days from the operative invoice line when present. Otherwise the cell is blank (null) and a note explains why. | L86: Operative invoice lines are saved without days (9219c:186), so in practice the cell is always blank. That is what the fix intends.
A87: FA-26 | B87: Low | C87: Finance 900-9219h | D87: Pay run (finPayLinesFor) | E87: The pay run's sign-in window is in UTC, so in summer it misses an hour at the start and end of the week | F87: Fixed | G87: Fixed | H87: Fixed before v2. | I87: 24 Oct | K87: 9218:24: new Date(from+'T00:00:00').toISOString() gives local midnight, sent in UTC, and the window ends exclusively at the next day. | L87: This assumes the device is on UK time.
A88: FA-27 | B88: Low | C88: Finance 900-9219h | D88: Settings | E88: Saving settings gives no message if the company-record update is quietly refused | F88: Fixed | G88: Fixed | H88: Fixed before v2. | I88: 24 Oct | K88: 900:179: undefined (refused) and null (error) from the organizations update each get their own toast, then a re-render.
A89: FA-28 | B89: Low | C89: Finance 900-9219h | D89: Xero bills | E89: A supplier's whole bill is tracked to one project in Xero even when it is split across projects | F89: Partly fixed | G89: Fixed | H89: The Xero function v10 (deployed 25 Oct) sends a split bill as one line per project. | I89: 25 Oct | J89: edge deploy 25 Oct: xero v9 → v10 | K89: The repo index.ts:363-388 splits the bill into one line per project. The deployed function (xero v9, checked via the Supabase MCP) still sends a single line tracked to pi.site_id. | L89: Needs a deploy.
A90: FA-29 | B90: Low | C90: Finance 900-9219h | D90: Purchase invoice form | E90: The "Possible duplicate" warning stays dismissed after the invoice number is changed | F90: Fixed | G90: Fixed | H90: Fixed before v2. | I90: 24 Oct | K90: 904:228-235: dupOk holds a supplier | L90: number key, so changing either re-runs the check. The warning clears if the new number isn't a duplicate.
A91: FB-15 | B91: Low | C91: Finance 9219i-922 | E91: "Received To Date" tile includes VAT but is labelled "Excl. VAT" | F91: Fixed | G91: Fixed | H91: Fixed before v2. | I91: 24 Oct | K91: 9219q:39 counts the net share of paid, capped at the total.
A92: FB-16 | B92: Low | C92: Finance 9219i-922 | E92: Issuing from the preview panel turns every confirm dialog into an automatic "yes" | F92: Fixed | G92: Fixed | H92: Fixed before v2. | I92: 24 Oct | K92: 9219zf:72 calls issueFinInvoice(siteId, true). 901:228 skips only its own confirm, and customConfirm is no longer swapped.
A93: FB-17 | B93: Low | C93: Finance 9219i-922 | E93: A PO raised on another job can get this job's plot | F93: Fixed | G93: Fixed | H93: Fixed before v2. | I93: 24 Oct | K93: 9219zb:146-148: sub is only taken when poSite===n.siteId.
A94: FB-18 | B94: Low | C94: Finance 9219i-922 | E94: Phone CSS for the ⋯ column applies to every Finance table | F94: Fixed | G94: Fixed | H94: Fixed before v2. | I94: 24 Oct | K94: 9219t:78-79: rows without td.finrowdots get their right padding back. | L94: Older WebKit without :has() keeps the 44px.
A95: FB-19 | B95: Low | C95: Finance 9219i-922 | E95: "Send & export" menu can run off the right edge on a phone (Needs check) | F95: Fixed | G95: Fixed | H95: Fixed before v2. | I95: 24 Oct | K95: 9219t:196-210 wraps finAppMoreMenu and clamps left to the viewport with an 8px margin.
A96: FB-20 | B96: Low | C96: Finance 9219i-922 | E96: Esc closes the wrong pop-up, and fires app-wide | F96: Fixed | G96: Fixed | H96: Fixed before v2. | I96: 24 Oct | K96: 9219z:191-209: the confirm counts as top, otherwise the highest z-index (last one on a tie) wins. It ignores defaultPrevented and the client-suggestion Esc. modalClose clicks .geo-modal-cancel, so customConfirm resolves false.
A97: FB-21 | B97: Low | C97: Finance 9219i-922 | E97: Back-button override changes Back on every Projects page for every user (Needs check) | F97: Open | G97: Fixed | H97: Decided: the "up one level" Back is for managers only. Operatives and drivers get their own Back again. | I97: 25 Oct | J97: finance-done: 9219v:264 (c473337) | K97: 9219v:161-198: navUpTarget still sends any #/site/<id>/<page> to site home, and site home to #/sites, for every role. Only Finance gets "previous page". | L97: This is intentional per the code comment (Andy, 23 Oct). It is waiting on his decision for operatives and drivers.
A98: FB-22 | B98: Low | C98: Finance 9219i-922 | E98: Changing one statement line reloads everything | F98: Fixed | G98: Fixed | H98: Fixed before v2. | I98: 24 Oct | K98: 9219l:249-256 and 308: after a save, the page redraws with the statement, candidates and PDF URL it already has (finStmt.quick), with no refetch. | L98: It is still a full-page redraw, and the desktop PDF iframe reloads.
A99: FB-23 | B99: Low | C99: Finance 9219i-922 | E99: Excel "Prev Certified" can come from an application that was never certified | F99: Fixed | G99: Fixed | H99: Fixed before v2. | I99: 24 Oct | K99: 9219p:154-155: "Prev Certified" only comes from certified/invoiced applications.
A100: FB-24 | B100: Low | C100: Finance 9219i-922 | E100: Once-guard can let Apply run while a Save is still writing (Needs check) | F100: Fixed | G100: Fixed | H100: Fixed before v2. | I100: 24 Oct | K100: 922:21-24: the guard returns the in-flight promise. Apply (9219p:74) waits for it and stops on false.
A101: FB-25 | B101: Low | C101: Finance 9219i-922 | E101: Project Purchases "Total Spend" may include non-purchase costs (Needs check) | F101: Fixed | G101: Fixed | H101: Fixed before v2. | I101: 24 Oct | K101: 9219y:23-25 leaves labour/subcontract costs out of the tab. | L101: Prelims, overhead and other categories still count, which is intended.
...

Sheet Security Now
A1: Security Now: 30 items from 23 Oct + 3 found on 24 Oct
A2: Based on the database and server state confirmed on 27 Oct: integrity fixes, security batches 1–3 applied, and the 25–26 Oct server function deploys.
A3: Still manual for you: turn on leaked-password protection, and reconnect OneDrive / revoke the old Microsoft sessions.
A5: ID | B5: Severity | C5: Area | D5: Title | E5: Status in v2 | F5: Status now | G5: What changed | H5: Fixed on | I5: Evidence (batch / deploy / file) | J5: Left to do | K5: v2 evidence | L5: Found
A6: SEC-C1 | B6: Critical | C6: RLS / OAuth token handling | D6: OneDrive access/refresh tokens readable by every member of the company (and cached on phones) | E6: Partly fixed | F6: Partly fixed | G6: Only the server can read the tokens now (database batch 1), and the app no longer fetches them. Left for you: reconnect OneDrive and revoke the old Microsoft sessions. | H6: 25 Oct | I6: security batch 1: C1 column grants; core-done 060 cache purge | J6: You: reconnect OneDrive; revoke old sessions | K6: App: 380-assign-team…:12 now uses select=org_id, and odCompanyConnected = odConnRows.length>0 (:21). 260-admin-centre-layout.js:112 selects only org_id,account_email,folder_path,connected_at. DB unchanged: policy onedrive_connections."select own org" is still USING (org_id = (SELECT my_org_id())). authenticated still has full table grants (SELECT, INSERT, UPDATE, DELETE…), and the 1 live connection still holds an access token. Anyone in the company can still call GET /rest/v1/onedrive_connections?select=access_token. The old app's cached response is also still on devices (see N1). The token should be treated as already exposed until it is rotated. | L6: 23 Oct
A7: SEC-H3 | B7: High | C7: Storage | D7: Cross-company read of every file in the public buckets (signatures, incident photos, expense receipts, RAMS/COSHH, company policies, drawings) | E7: Open | F7: Partly fixed | G7: Listing and opening files is now limited to your own company. The buckets are still public, so anyone with a file's exact link can open it. | H7: 25 Oct (batch 3, confirmed 27 Oct) | I7: security batch 3: H3 | J7: Make the buckets private and use signed links (app + database) | K7: All 9 buckets are still public=true (signatures, incident-photos, site-photos, rams-docs, coshh-docs, coshh-library, mc-documents, drawings, operative-tools). The 9 "signed-in read <bucket>" policies still read USING (bucket_id = '<bucket>') with no org check. 1 profile with no org still exists. | L7: 23 Oct
A8: SEC-L10 | B8: Low | D8: Leaked-password protection off; password-reset endpoint not rate limited | E8: Open | F8: Partly fixed | G8: Password reset emails are limited to 3 per address per hour. Left for you: turn on leaked-password protection. | H8: 25 Oct | I8: edge deploy 25 Oct: send-password-reset v1 → v2 | J8: You: turn on leaked-password protection | K8: Advisor auth_leaked_password_protection is still WARN. send-password-reset is v1, unchanged. | L8: 23 Oct
A9: SEC-N3 | B9: Info | C9: Edge functions | D9: The xero edge function in the repo differs from the deployed one | E9: Open | F9: Partly fixed | G9: Xero v10 is live. The repo copy is older than what is live; copy the live version in. | H9: 25 Oct | I9: edge deploy 25 Oct; supabase/functions/xero/index.ts differs from the live source | J9: Copy the live xero (and finance-inbox) source into the repo | K9: The FA-28 change (one Xero line per project when a bill is split) isn't live. I found no security problem in the new code: the extra sites lookup is .eq('org_id', orgId). But the I1 conclusion ("deployed matches repo") no longer holds for this function. | L9: New
A10: SEC-I2 | B10: Info | D10: Needs check (not individually read) | E10: Info / needs check | F10: Info / needs check | G10: 11 email functions were reviewed and hardened on 25 Oct. The other send/notify functions were not re-checked. | I10: edge deploy 25 Oct | J10: Review the remaining send-*/notify-* functions | K10: Not re-read. Note: the repo supabase/functions/xero/index.ts changed on 24 Oct (FA-28, bill split per project), but the deployed function is still v9 (21 Oct). See N3. | L10: 23 Oct
A11: SEC-I1 | B11: Info | D11: Things checked and found OK | E11: Info / needs check | F11: Info | G11: Not re-checked. | K11: The "checked and OK" list still holds. The new client code follows the same pattern (section 4). | L11: 23 Oct
A12: SEC-H1 | B12: High | C12: Client XSS + RLS | D12: Stored XSS through organizations.logo_path (runs for the whole company and in the superadmin console) | E12: Fixed | F12: Fixed | G12: App side (v2) plus the database check on logo paths. | H12: 25 Oct | I12: path-safe check constraints (H1/H2) applied 25 Oct | K12: 100-state.js:302 URL-encodes each path segment. encodeURIComponent encodes ", <, > and spaces, and every orgLogoUrl() use is a double-quoted src="…" (125:112, 130:125, 140:85, 150:65, 170:59, 260:233, 640:156). admin.html:420 uses the same encoding. The other raw publicUrl('org-logos', ORG.logo_path) calls (320:803, 340:1570/1728, 400:1060, 430:1230, 500:561/835, 550:419, 660:868, 800:198, 587:30, 589:692) only fetch() bytes for PDFs and never reach HTML. Still not done: there is no organizations_logo_path_safe CHECK constraint, and "pm update own org branding" is unchanged (see M2). | L12: 23 Oct
A13: SEC-H2 | B13: High | C13: Client XSS | D13: Stored XSS through photo/file storage_path values in src= and onclick= (49 places) | E13: Open | F13: Fixed | G13: The app encodes every file path, and the database refuses unsafe paths. | H13: 25 Oct | I13: core-done: 060:380-383, 065:125; path-safe check constraints applied 25 Oct | K13: 060-offline-read-cache.js publicUrl() still does SUPABASE_URL+'/storage/v1/object/public/'+bucket+'/'+path with no encoding. 46 template sites still interpolate it into src="${publicUrl(…)}" / viewImage('${publicUrl(…)}'), e.g. 340-maintenance-repair-contract.js:913,921, 320-per-operative-certifications.js:502,657, 240-my-signature…:11. No *_paths_safe constraints exist (pg_constraint has none). schedule_photos."insert site access" is unchanged. | L13: 23 Oct
A14: SEC-H4 | B14: High | C14: Storage | D14: Any PM/admin of any company can read every company's price files | E14: Open | F14: Fixed | G14: Price files only for your own company's projects. | H14: 25 Oct | I14: security batch 1: H4 | K14: storage."select price files storage": the first branch is still EXISTS(profiles pr WHERE pr.id = auth.uid() AND pr.role IN ('pm','admin')) with no site or org check. | L14: 23 Oct
A15: SEC-H5 | B15: High | C15: RLS / finance integrity | D15: Check-ins can be forged for anyone, at any time, and they drive pay runs and labour costs | E15: Open | F15: Fixed | G15: You can only check yourself in, at the current time; only managers edit check-ins. | H15: 25 Oct | I15: security batch 1: H5 | K15: checkins."insert site access" WITH CHECK is still has_site_access(site_id), and "update site access" is still has_site_access(site_id) on both sides. There is no user_id/ts check. Pay run still reads these (9218-finance-payrun.js:26, now with a UK-midnight window, but forged rows still count). | L15: 23 Oct
A16: SEC-H6 | B16: High | C16: Client-only role checks | D16: Approval and status fields protected only in the UI (variations, permits, RAMS/COSHH docs, materials) | E16: Open | F16: Fixed | G16: Approval and decision fields on variations, permits, RAMS, COSHH and materials can only be changed by managers. Snags, schedule and site-layout tables still use the general job rule. | H16: 25 Oct | I16: security batch 1: H6 guard trigger (guard_manager_fields) | J16: Optional: same guard on snags, schedule and site layout | K16: variations, permits, rams_docs, coshh_docs and materials UPDATE policies are still has_site_access(site_id) on both sides. There is no guard trigger (none in pg_trigger on those tables). | L16: 23 Oct
A17: SEC-M1 | B17: Medium | C17: RLS | D17: Org-wide SELECT policies don't exclude the client (external customer) role | E17: Open | F17: Fixed | G17: Client logins can't read company-wide lists. A few stay open on purpose because client screens need them (names, H&S policy, tools, toolbox talks). | H17: 25 Oct (batch 3, confirmed 27 Oct) | I17: security batch 3: M1 | K17: report_submissions."org can read submissions" = org_id = my_org_id(), and profiles."select same org profiles" and suppliers."select own org" are unchanged. There are 0 client profiles today, so nobody can exploit this yet. | L17: 23 Oct
A18: SEC-M10 | B18: Medium | C18: Client XSS | D18: JS injection in the superadmin console through a user-editable profile email | E18: Fixed | F18: Fixed | G18: Fixed before v2 (the injection); batch 1 also stops managers changing other people's email. | H18: 24 Oct | I18: v2; security batch 1: M3 / M10 | K18: admin.html:485 is now onclick="resetPassword('${jsAttr(p.email)}')". Still not done: profiles.email is still editable by its owner ("user update own profile", and no trigger keeps it in step with auth.users). That doesn't matter for this sink any more. | L18: 23 Oct
A19: SEC-M11 | B19: Medium | C19: SECURITY DEFINER RPC | D19: yard_cost_edit lets non-finance PMs edit finance job costs and move them to any site | E19: Open | F19: Fixed | G19: Yard cost edits stay inside your company, and only Finance can change the money. | H19: 25 Oct (batch 3, confirmed 27 Oct) | I19: security batch 3: M11 | K19: The yard_cost_edit body is unchanged. It still has no check that p_site belongs to the caller's org (update fin_job_costs set … site_id = coalesce(p_site, site_id)), and PMs can still change net. has_function_privilege('anon', …) is still true. | L19: 23 Oct
A20: SEC-M2 | B20: Medium | C20: RLS | D20: Any PM/site manager can rewrite any column of the company record | E20: Open | F20: Fixed | G20: Only an admin changes the company name, billing, modules, job numbering or expenses email. | H20: 25 Oct | I20: security batch 1: M2 | K20: organizations."pm update own org branding" = is_pm() AND id = my_org_id() on all columns. The only triggers are trg_protect_plan_tier and trg_org_modules_from_tier. | L20: 23 Oct
A21: SEC-M3 | B21: Medium | C21: RLS | D21: PMs can edit other people's profiles, including signature images and roles | E21: Open | F21: Fixed | G21: A manager can't change someone else's signature or email, or make them an admin. | H21: 25 Oct | I21: security batch 1: M3 / M10 | K21: profiles."manager update pm/operative role within org" is unchanged. There is no protect_profile_by_manager trigger: the profiles triggers are estimator_sync, finance_on_insert, protect_profile_finance and protect_profile_role_org. New client code relies on this path: 908-finance-standalone.js:216-235 (finTeamToggle) promotes a user to pm when Finance is granted (it now asks first, :221). | L21: 23 Oct
A22: SEC-M4 | B22: Medium | C22: RLS / H&S records | D22: Signatures can be forged in another person's name | E22: Open | F22: Fixed | G22: You can only sign as yourself. | H22: 25 Oct | I22: security batch 1: M4 | K22: rams_signatures, coshh_signatures and site_layout_signatures "insert site access" WITH CHECK still has only has_site_access(...), with no user_id = auth.uid(). | L22: 23 Oct
A23: SEC-M5 | B23: Medium | C23: RLS | D23: Commercial values readable by operatives and subcontractors (hidden only in the UI) | E23: Open | F23: Fixed | G23: Prices only for managers, Finance and people given price access on that job. | H23: 25 Oct | I23: security batch 1: M5 | K23: pricing_elements."select site access" and price_weeks."select site access" are still just has_site_access(site_id). sites."select assigned or pm" is unchanged, and there is no column revoke. | L23: 23 Oct
A24: SEC-M6 | B24: Medium | C24: Storage | D24: storage_path_mine() shares folders across all companies and lets any member write or delete any site folder | E24: Open | F24: Fixed | G24: Shared folders are kept per company, and only the uploader or a manager of the same company can delete or replace a file. Old shared folders still take new files until phones are updated. | H24: 25 Oct (batch 3, confirmed 27 Oct) | I24: security batch 3: M6 (storage_path_mine, storage_can_change); app commit ea36726 | K24: storage_path_mine() body is unchanged: if s1 in ('general','exports','report-pdfs') then return true applies to any signed-in user with an org. It also returns true for s2 = org and for any site folder of the caller's org, whether or not they are assigned to it. | L24: 23 Oct
A25: SEC-M7 | B25: Medium | C25: Edge functions (email abuse) | D25: Signed-in users can send company-branded email to any address, with any link | E25: Open | F25: Fixed | G25: Email functions redeployed: links must be your own files, and every send is logged and limited per day. | H25: 25 Oct | I25: edge deploy 25 Oct (11 send-* functions); edge_email_log table | K25: send-document-email is still v11, last deployed 16 Oct. Nothing has been redeployed. | L25: 23 Oct
A26: SEC-M8 | B26: Medium | C26: Edge functions | D26: Any member can write or overwrite files anywhere in the company's OneDrive/SharePoint | E26: Open | F26: Fixed | G26: Operatives can only upload to OneDrive for jobs they are on. | H26: 25 Oct | I26: edge deploy 25 Oct: onedrive-upload v29 → v30 | K26: onedrive-upload is still v29, last deployed 14 Oct. | L26: 23 Oct
A27: SEC-M9 | B27: Medium | C27: Storage | D27: webapp bucket: public, and any PM of any company can upload or overwrite | E27: Open | F27: Fixed | G27: Nobody signed in can write to the old "webapp" storage any more. | H27: 25 Oct (batch 3, confirmed 27 Oct) | I27: security batch 3: M9 | K27: webapp is still public with 2 objects. "pm upload webapp" and "pm update webapp" are still bucket_id='webapp' AND is_pm(), with no org check. | L27: 23 Oct
A28: SEC-L1 | B28: Low | D28: SECURITY DEFINER functions executable by anon (39) and trigger functions exposed as RPCs | E28: Open | F28: Fixed | G28: Logged-out visitors can't call database functions (except the invite page), and trigger functions can't be called directly. | H28: 25 Oct (batch 3, confirmed 27 Oct) | I28: security batch 3: L1 | K28: Advisor: anon_security_definer_function_executable 39 and authenticated_security_definer_function_executable 55. The same functions are listed as on 23 Oct, trigger functions included. | L28: 23 Oct
A29: SEC-L2 | B29: Low | D29: check_and_lock_device (v1) still callable alongside v2 | E29: Open | F29: Fixed | G29: The old device check is switched off. | H29: 25 Oct (batch 3, confirmed 27 Oct) | I29: security batch 3: L2 | K29: check_and_lock_device(text): authenticated can still execute it (anon cannot). | L29: 23 Oct
A30: SEC-L3 | B30: Low | D30: Mutable search_path on fin_item_key(text), fin_qty_num(text) | E30: Open | F30: Fixed | G30: Applied. | H30: 25 Oct | I30: sec_round2_a_integrity (search_path) | K30: Advisor function_search_path_mutable: fin_item_key, fin_qty_num. proconfig is null. | L30: 23 Oct
A31: SEC-L4 | B31: Low | D31: Device lock is trivially bypassed | E31: Open | F31: Fixed | G31: An old-style phone id that belongs to someone else no longer lets you straight in. (The device lock is still a deterrent, not a hard lock.) | H31: 25 Oct (batch 3, confirmed 27 Oct) | I31: security batch 3: L4 | K31: The check_device_lock_v2 body still has the fp_ branch. | L31: 23 Oct
A32: SEC-L5 | B32: Low | D32: Finance inbox: key in the URL, and AI auto-filing is exposed to prompt injection | E32: Open | F32: Fixed | G32: The inbox key now goes in a header (the old link form still works), AI-filed invoices are never auto-approved, and a supplier that doesn't match the PO goes to Query. | H32: 25 Oct | I32: edge deploy 25 Oct: finance-inbox v2 → v3 (index.ts:9, 120-159) | J32: Optional: move the mail forwarder to the header, then stop accepting ?key= | K32: finance-inbox is still v2 (21 Oct), with no redeploy. On the client, filing now claims the row first (9219b-finance-purchases.js:96, 906-finance-inbox.js:188). That stops double filing, but the AI auto-filing trust issue is unchanged. | L32: 23 Oct
A33: SEC-L6 | B33: Low | D33: "Orphan row" clauses let any PM on the platform delete orphaned rows of other companies | E33: Open | F33: Fixed | G33: The "orphan row" delete escape hatch is removed. | H33: 25 Oct (batch 3, confirmed 27 Oct) | I33: security batch 3: L6 | K33: 29 policies still contain NOT (EXISTS (SELECT 1 FROM sites …)) orphan branches, e.g. checkins."pm delete", variations."pm delete", pricing_elements."pm delete", price_weeks."pm delete". | L33: 23 Oct
A34: SEC-L7 | B34: Low | D34: Session and offline cache (including finance data) stored in localStorage | E34: Open | F34: Fixed | G34: Finance, wages, OneDrive and Xero data are never saved on the phone. | H34: 25 Oct | I34: core-done: 060:49-53 cacheNeverStore | K34: 060-offline-read-cache.js:46 cacheRows() still caches every dbSelect response with no table exclusions. That now also includes client_pos.files and the new job_finance columns. | L34: 23 Oct
A35: SEC-L8 | B35: Low | D35: Edge function hygiene | E35: Open | F35: Fixed | G35: Functions redeployed with a website allow-list and the other tidy-ups. | H35: 25 Oct | I35: edge deploy 25 Oct | K35: No edge function has been redeployed since 21 Oct, so CORS *, raw error echoes and the Math.random() password in admin-reset-password (v18, 3 Oct) are unchanged. | L35: 23 Oct
A36: SEC-L9 | B36: Low | D36: onedrive-oauth-callback reflects the error parameter into HTML unescaped | E36: Open | F36: Fixed | G36: The OneDrive sign-in page escapes the error text. | H36: 25 Oct | I36: edge deploy 25 Oct: onedrive-oauth-callback v27 → v28 | K36: onedrive-oauth-callback is v27, unchanged since 20 Sep. | L36: 23 Oct
A37: SEC-N1 | B37: Low | C37: Client offline cache / C1 follow-up | D37: OneDrive token responses from the old app are still cached on devices | E37: Open | F37: Fixed | G37: Phones wipe old copies, and the database no longer hands out the tokens. Reconnect OneDrive (under SEC-C1). | H37: 25 Oct | I37: core-done 060:91-111; security batch 1 (C1) | K37: The C1 client fix stops new fetches of the token. Nothing removes the responses the old build already wrote to localStorage. They stay until sign-out or until 300 newer reads push them out. The refresh_token from the admin screen's select=* lasts much longer than an hour. | L37: New
A38: SEC-N2 | B38: Low | C38: RLS, Finance tables used by the new Overview, BoQ and variations screens | D38: Several finance tables don't check that site_id belongs to your company on write (integrity only); contract_value_source is free text | E38: Open | F38: Fixed | G38: Finance rows can only point at your own company's projects. | H38: 25 Oct (batch 3, confirmed 27 Oct) | I38: security batch 3: N2 (site_in_my_org) | K38: A Finance user can save one of their own company's rows against another company's site_id. The other company can't see the row (it's filtered by org), so nothing leaks across companies. But it's inconsistent with the stricter tables, and it lets bad data in (e.g. a pasted wrong UUID). contract_value_source accepts any text. | L38: New

Sheet New Issues
A1: New Issues (found 24 Oct evening): status on 27 Oct
A2: ID prefixes: CP- = Core/Projects re-check, FIN- = Finance re-check, SEC-N = security re-check, NS- = review of the new screens, FX- = review of the fixes.
A4: ID | B4: Source | C4: Severity | D4: Area | E4: Title | F4: Status in v2 | G4: Status now | H4: What changed | I4: Fixed on | J4: Evidence | K4: What was wrong (v2) | L4: Where (file:line, v2) | M4: Same as
A5: CP-NEW-1 | B5: Core/Projects re-check | C5: Low | D5: Admin Centre › Integrations; Assign Team | E5: OneDrive shows "Connected" when any connection row exists (Needs check) | F5: Needs check | G5: Open | H5: Not changed. Integrations shows "Connected" whenever a connection record exists (the app can no longer read the token to check). | J5: core-done: "Not done (needs DB)"; 260:112 and 380:12 now select org_id only | K5: The 24 Oct fix stopped loading access_token, so "connected" now means "a row exists for this org". Before, it meant "a row with a token exists". If the OAuth flow creates the row before the token is stored, or the refresh job blanks the token when Microsoft revokes it, the page now says "Connected — syncing to …". | L5: 260-admin-centre-layout.js:112, 286; 380-assign-team-per-site-pm-allocates-operat.js:12, 21
A6: SEC-N3 | B6: Security re-check | C6: Info | D6: Edge functions | E6: The xero edge function in the repo differs from the deployed one | F6: Open | G6: Partly fixed | H6: The live Xero function is now v10. The copy in the code (repo) is older than what is live, so a redeploy from the repo would undo the contra line. Copy the live version in. | I6: 25 Oct | J6: edge deploy 25 Oct (xero v9 → v10 from /home/claude/edge/xero/new); supabase/functions/xero/index.ts differs | K6: The FA-28 change (one Xero line per project when a bill is split) isn't live. I found no security problem in the new code: the extra sites lookup is .eq('org_id', orgId). But the I1 conclusion ("deployed matches repo") no longer holds for this function. | L6: supabase/functions/xero/index.ts:363-390 (24 Oct, FA-28 split lines). Deployed xero is v9, updated_at 21 Oct. | M6: FX-P10
A7: NS-H1 | B7: New screens review | C7: High | D7: Bill of Quantities on the phone (9219zk) together with the autosave (9219n) | E7: Phone BoQ editor: a new line (or edits) typed while an autosave is running is never saved | F7: Fixed (waiting for Push origin) | G7: Fixed | H7: Fixed on 24 Oct night (tested); live since you pressed Push origin. | I7: 24 Oct (night) | J7: commit 698ae60 | K7: • finBqAddAt (every "+ Add …" on the phone) inserts an empty row and calls finContractAutoSave() immediately, then opens the edit sheet. • The autosave skips the empty row, because it has no description. • When the autosave finishes, though, it takes the "saved" snapshot from the current finContractRows. That snapshot already includes whatever the user has typed into the sheet in the meantime. • When the user taps Done, finBqClose checks finContractIsDirty(), gets false, and does not save. • The same happens to any edit made in the sheet that is reopened after Up/Down (finBqMove → finContractMove → autosave → finBqEdit). • The autosave PATCHes every line one after another, so on a real BoQ it runs for several seconds on mobile. That makes this window easy to hit. | L7: • 9219n-finance-newjob.js:504-523: rows is filtered and captured at the start; then finContractSnap = finContractSnapOf(finContractRows) runs at the end. • 9219zk-finance-boq-phone.js:53-60 (finBqAddAt) and :75-80 (finBqClose).
A8: NS-H2 | B8: New screens review | C8: High | D8: Bill of Quantities on the phone (9219zk) | E8: Phone BoQ "Remove" does nothing: the confirm dialog opens behind the edit sheet | F8: Fixed (waiting for Push origin) | G8: Fixed | H8: Fixed on 24 Oct night (tested); live since you pressed Push origin. | I8: 24 Oct (night) | J8: commit 698ae60 | K8: • The sheet and the confirm overlay have the same z-index, so DOM order decides which is on top. • #confirmModalOverlay is created the first time any confirm is used in the session. #finBqOv is created the first time the BoQ sheet opens. • If any confirm has been shown earlier in the session (very common), the confirm sits earlier in the DOM and is painted under the sheet. | L8: • 9219zk-finance-boq-phone.js:120-125 (finBqDelete asks customConfirm while the sheet is still open). • 9219zk-finance-boq-phone.js:158 (.bq-ov{z-index:10050}). • 9219m-yard-stock.js:280 (#confirmModalOverlay{z-index:10050 !important}). • 110-routing.js:191-197 (the confirm overlay is created once and appended to body).
A9: FIN-NEW-01 | B9: Finance re-check | C9: Medium | D9: Subcontracts / CIS / Xero (side effect of the FA-06 fix) | E9: Subcontractor bills posted to Xero now include the contra charge, so Xero shows the contra as still owed | F9: Andy to decide | G9: Fixed | H9: The CIS record stores the contra, and Xero v10 adds it as a minus line on the bill. | I9: 25 Oct | J9: finance-done: 912:297; xero v10 deployed 25 Oct | K9: Since the FA-06 fix, fin_sub_payments stores labour and gross before the contra charge. This is correct for CIS. But the Xero bill is built from labour + materials, so it now includes the contra. The payment actually made (net_pay) is after the contra, and nothing posts the contra to Xero as a credit or negative line. | L9: 912-finance-subcontracts.js:279-283 (gross = net_due + contraNow, labour = gross − materials stored on fin_sub_payments). Deployed xero function v9, push_sub_payment (the bill = labour line + materials line, NoTax). | M9: FX-P2
A10: FX-P1 | B10: Fix check review | C10: Medium | D10: Purchases › Inbox (FA-03) | E10: An inbox item can be left "filed" with no purchase invoice, and drop out of sight | F10: Open | G10: Fixed | H10: Stuck "filed" inbox invoices show again and can be filed; only one person can claim one at a time. (One server step would be stronger.) | I10: 25 Oct | J10: finance-done: 906:26, 9219b:120, 914, 9219l | K10: The claim sets status:'filed' before the purchase invoice is inserted. If the insert doesn't complete, the only recovery is a second dbUpdate(...{status:'new'}). That second call fails too when the cause was a dropped connection: dbInsert catches the network error and returns null, then the revert PATCH also fails. It also fails if the app is closed or backgrounded between the two calls. The row is then status='filed', purchase_invoice_id=null. The Purchases inbox only loads status=eq.new, and no screen lists filed items with no invoice. A failed claim (offline) also shows "This one has just been filed by someone else", which is wrong, alongside the generic "Update failed" toast. | L10: src/js/9219b-finance-purchases.js:96-103 (and 906-finance-inbox.js:188-193); list query at 9219b-finance-purchases.js:119 | M10: FIN-NEW-04 (toast part)
A11: FX-P2 | B11: Fix check review | C11: Medium | D11: Subcontracts / CIS → Xero (FA-06) | E11: Subcontract bill in Xero is now overstated by the contra charge | F11: Andy to decide | G11: Fixed | H11: Same as FIN-NEW-01: the contra goes to Xero as a minus line. | I11: 25 Oct | J11: finance-done: 912:297; xero v10 deployed 25 Oct | K11: The CIS figures are now right per CISR15030: gross before contra, and cis_deduction on that. But the same fin_sub_payments row feeds Xero, which posts a bill of labour + materials = net due + this time's contra. The subcontractor is actually paid pay_amount = net due − CIS. Nothing posts the contra to Xero, so Xero shows them owed the contra amount on top. Fix-C flags this, but it is still unfixed and the bill posts automatically like any other. | L11: src/js/912-finance-subcontracts.js:283-286 (CIS record labour/gross now before contra); supabase/functions/xero/index.ts:417-418 (push_sub_payment posts labour + materials) | M11: FIN-NEW-01
A12: NS-M1 | B12: New screens review | C12: Medium | D12: Contract value: typed vs BoQ (9219zi), used by all three BoQ save paths | E12: A failed read in finCvPatch overwrites a typed (manual) contract value with the BoQ total | F12: Fixed (waiting for Push origin) | G12: Fixed | H12: Fixed on 24 Oct night (tested); live since you pressed Push origin. | I12: 24 Oct (night) | J12: commit 698ae60 | K12: • finCvPatch reads job_finance.contract_value_source with dbSelect(...).catch(()=>[]). • dbSelect does not throw on failure: it returns [] (or a cached copy) on a network or server error (060-offline-read-cache.js:111-117). • An empty answer is treated as "not manual", so the patch includes contract_value: <BoQ total>, and the upsert that follows (in a separate request) overwrites the typed value. | L12: • 9219zi-finance-setup.js:12-15. • Called from 902-finance-applications.js:243 (Save button), 9219n-finance-newjob.js:522 (autosave) and 9219n-finance-newjob.js:739 (finAppAddLineCore). | M12: FIN-NEW-03
A13: NS-M2 | B13: New screens review | C13: Medium | D13: Project Overview (9219zj block, 9219q finVdRowHtml) | E13: The overview's "Variations & Day Works" row is cached for the whole session and never refreshes | F13: Fixed (waiting for Push origin) | G13: Fixed | H13: Fixed on 24 Oct night (tested); live since you pressed Push origin. | I13: 24 Oct (night) | J13: commit 698ae60 | K13: The totals are fetched the first time the row is drawn for a project. After that, every re-render reuses the cached lists. | L13: 9219q-finance-summary-cards.js:267-290. FIN_VD_DATA[siteId] is loaded once and never cleared; finVdLoad only runs when it is missing. | M13: Map L85
A14: NS-M3 | B14: New screens review | C14: Medium | D14: Retention dates (9219zh, 9219 sales retention table) | E14: A typed "Final Retention Release" date overrides everything else from then on, and the Finance home ignores it | F14: Fixed (waiting for Push origin) | G14: Fixed | H14: Fixed on 24 Oct night (tested); live since you pressed Push origin. | I14: 24 Oct (night) | J14: commit 698ae60 | K14: • Once final_release_date is set from Sales › Retention, the wrapper returns it whatever the PC date or defects period say. • Project Admin still offers "Practical completion" + "Defects (months)" + "Save dates", but saving them no longer changes the final date that is shown or used. • The defects months that finRetSetDate back-fills are rounded to whole months, so the two disagree. For example, PC 1 Jan 2026 with final 15 Mar 2027 gives 14 months, which works out to 1 Mar 2027. • The Finance home builds its "Retention to claim back" reminders from a select that has no final_release_date. It therefore uses PC + defects instead, and if only the final date was typed (no PC date) there is no reminder at all. | L14: • 9219zh-finance-sales-tidy.js:8-24 (the finRetentionDates wrapper and finRetSetDate). • 903-finance-certs-retention.js:188-193 (saveFinRetentionDates never touches final_release_date). • 914-finance-sections.js:67 (the home's job_finance select has no final_release_date) and :90 (home retention reminders). | M14: Map L83
A15: NS-M4 | B15: New screens review | C15: Medium | D15: Project Admin and contract value (900, 902, 9219zi) | E15: A typed contract value on an applications project with a BoQ cannot be corrected, and the Save toast quotes the wrong figure | F15: Fixed (waiting for Push origin) | G15: Fixed | H15: Fixed on 24 Oct night (tested); live since you pressed Push origin. | I15: 24 Oct (night) | J15: commit 698ae60 | K15: • 24 Oct made the typed value "win" (contract_value_source='manual'), but Project Admin still locks the box as soon as the project has BoQ lines. • The only way to change a typed figure (e.g. a typo, or a revised contract sum) is "Use BoQ", which throws it away. • The Save toast reports the BoQ total as the contract value even though it was deliberately not applied. | L15: • 900-finance.js:265: the Contract value input is disabled when bt==='application' && items.length. • 900-finance.js:275: the hint says "The contract value comes from the Bill of Quantities". • 902-finance-applications.js:259: the toast 'Schedule saved — contract value '+finMoney(total). | M15: Map L82
A16: NS-M5 | B16: New screens review | C16: Medium | D16: Bill of Quantities on the phone (9219zk) | E16: The phone BoQ edit sheet stays on top after leaving the page | F16: Fixed (waiting for Push origin) | G16: Fixed | H16: Fixed on 24 Oct night (tested); live since you pressed Push origin. | I16: 24 Oct (night) | J16: commit 698ae60 | K16: • A phone back gesture, Android back, or a go() from elsewhere (a notification, tapping a tab under the sheet's edge) re-renders #app but leaves #finBqOv showing (display:flex, z-index 10050) over the next page. • Its inputs still write into finContractRows[i]. If a different project's BoQ has been opened since, that array belongs to the other project, and Done then autosaves it. | L16: 9219zk-finance-boq-phone.js:70-74. The overlay is appended to <body>, not #app, and nothing closes it on a route change.
A17: NS-M6 | B17: New screens review | C17: Medium | D17: Client PO, multiple files (900) | E17: Client PO save: a failed read of the existing files drops the earlier attachments from the PO | F17: Fixed (waiting for Push origin) | G17: Fixed | H17: Fixed on 24 Oct night (tested); live since you pressed Push origin. | I17: 24 Oct (night) | J17: commit 698ae60 | K17: • dbSelect returns [] on a network or server error, so old becomes empty. • row.files is then written as only the newly added files, and file_path/file_name are replaced as well. • The earlier copies stay in storage, but nothing in the app points to them any more. | L17: 900-finance.js:376, const old = poId ? finPoFilesOf((await dbSelect(...))[0]||{}) : [].
A18: CP-NEW-2 | B18: Core/Projects re-check | C18: Low | D18: Offline read cache / security follow-up to CORE-M1 | E18: Old offline cache still holds the OneDrive tokens on devices that opened Integrations before the fix | F18: Open | G18: Fixed | H18: Old saved OneDrive copies are wiped from phones when the app starts. | I18: 25 Oct | J18: core-done: 060:91-111 cachePurgeSensitive | K18: Every dbSelect result is saved to localStorage under table?querystring. The old select=* row, with the access and refresh tokens, is still on any admin's browser that opened Integrations before 24 Oct. The new query has a different key, so nothing overwrites it. It goes only on sign-out or when 300 newer entries push it out. | L18: 060-offline-read-cache.js:46-51 (cacheRows), 21 (300-entry LRU); old query key onedrive_connections?org_id=eq.<org> | M18: SEC-N1
A19: FIN-NEW-02 | B19: Finance re-check | C19: Low | D19: Project Overview (new file 9219zj) | E19: The Overview headline says "Contract + agreed variations" under a figure that also includes unagreed ones | F19: Open | G19: Fixed | H19: The headline now says it includes submitted variations, and how much. | I19: 25 Oct | J19: finance-done: FA-18 / FIN-NEW-02 | K19: The headline shows fc.ffa (contract + agreed + priced/submitted variations). The line under it reads "Contract £X + £Y agreed variations", which only adds up when nothing is pending. This is FA-18 again, in the new Overview block. | L19: 9219zj-finance-overview-cards.js:56 and 64. The source figure is 911-finance-qs.js:142.
A20: FIN-NEW-03 | B20: Finance re-check | C20: Low | D20: Bill of Quantities / contract value (new in 9219zi) | E20: A failed read can overwrite a typed contract value with the BoQ total | F20: Fixed (waiting for Push origin) | G20: Fixed | H20: Fixed on 24 Oct night (tested); live since you pressed Push origin. | I20: 24 Oct (night) | J20: commit 698ae60 | K20: finCvPatch reads contract_value_source with dbSelect. On an error that returns [], and the .catch never runs. With jf undefined, the function returns {contract_value: total}. On a flaky read, a project whose value was set by hand ("manual") therefore gets the BoQ total written over it. | L20: 9219zi-finance-setup.js:12-15 (finCvPatch). Called from 902:243 (Save) and 9219n:522 (autosave). | M20: NS-M1
A21: FIN-NEW-04 | B21: Finance re-check | C21: Low | D21: Purchases inbox (from the FA-03 fix) | E21: Filing an inbox invoice by hand on a bad signal says "filed by someone else" | F21: Fixed (waiting for Push origin) | G21: Fixed | H21: Fixed on 24 Oct night (tested); live since you pressed Push origin. | I21: 24 Oct (night) | J21: commit 698ae60 | K21: dbUpdate returns null on a network or HTTP error (it has already shown "Update failed…") and undefined when 0 rows matched. The claim treats both as "already filed". | L21: 9219b-finance-purchases.js:92-93 | M21: FX-P1 (toast part)
A22: FIN-NEW-05 | B22: Finance re-check | C22: Low | D22: Sales invoices (side effect of the FA-12 fix) | E22: Recently created empty drafts vanish from Sales but still count as "Drafts not sent yet" | F22: Open | G22: Fixed | H22: New empty drafts stay in the Sales list so they can be finished or deleted. | I22: 25 Oct | J22: finance-done: 9219:94 | K22: Empty drafts younger than the clean-up age are no longer deleted (correct), but they are also left out of the Sales list. The project page still counts them in "Drafts not sent yet" and links to Sales › Invoices. | L22: 9219-finance-sales-tables.js:87 (an empty draft that isn't "old" goes into neither keep nor gone), and 9219n-finance-newjob.js:225-226 (the project "Needs attention" count).
A23: FX-P3 | B23: Fix check review | C23: Low | D23: Invoices (FA-10/21) | E23: Per-line VAT can still be 1p different from Xero on 5% and negative lines | F23: Open | G23: Fixed | H23: VAT per line now rounds the same way as Xero. | I23: 25 Oct | J23: finance-done: 901:35 | K23: Math.round(x*100)/100 on a float. 20.10 × 5 / 100 = 1.00499999… rounds to 1.00, where Xero gives 1.01. Negative half-pennies round toward zero (−0.005 → 0), where Xero rounds away from zero (−0.01). At 20% a half-penny can't happen with 2dp amounts. At 5% it can. No issued invoice is affected today (0 of 13). | L23: src/js/901-finance-invoices.js:33 (finRound(a*c.r/100), with finRound at 901:9)
A24: FX-P4 | B24: Fix check review | C24: Low | D24: Finance › Settings (FA-27) | E24: Every Finance-settings save by a non-admin says the project number settings can't be changed | F24: Fixed (waiting for Push origin) | G24: Fixed | H24: Fixed on 24 Oct night (tested); live since you pressed Push origin. | I24: 24 Oct (night) | J24: commit 698ae60 | K24: orgPatch always includes auto_job_numbers and job_number_prefix, even when they weren't touched. For a non-admin (RLS refuses), dbUpdate returns undefined on every save, so the "can only be changed by an admin" toast shows every time. FA-15 promotes Finance users to pm, not admin, so this is the normal case. | L24: src/js/900-finance.js:158-160, 179
A25: FX-P5 | B25: Fix check review | C25: Low | D25: Retention (FA-08 / FA-19) | E25: "Still held" may double-deduct when the client's later certificate already shows reduced retention (Needs check) | F25: Andy to decide | G25: Fixed | H25: Retention already dropped on a later certificate is no longer taken off twice. | I25: 25 Oct | J25: finance-done: 903:154-167 | K25: Still held = latest certificate's cumulative retention − release invoices issued. Under JCT-style certificates, the certificate issued after practical completion usually already holds only half the retention. If the user enters that certificate and has raised the first-half release invoice, the half is taken off twice: still held drops to about 0, and "Raise invoice" for the second half says "Nothing left to release". It is consistent as long as cert_retention keeps the full held figure until both releases are invoiced. Separately, 911:168 (Reports "Retention held"), 913:64 (retention ledger) and 914:89 (home tile) still show gross, so different screens show different retention figures (known partial). | L25: src/js/903-finance-certs-retention.js:131-134 (finRetentionHeld = latest cert_retention), 150-156, 141-147
A26: FX-P6 | B26: Fix check review | C26: Low | D26: Applications (FA-16) | E26: Two "New application" taps on two devices now quietly make two drafts | F26: Open | G26: Fixed | H26: A second "New application" opens the other person's new draft instead of making two. | I26: 25 Oct | J26: finance-done: 902:485 | K26: Before, the second insert failed on the unique (site, number) key. Now it silently becomes N+1. Its % complete lines are copied from N−1 (the last read before the clash), not from N. Nothing tells the user that application N already exists. | L26: src/js/902-finance-applications.js:458-475
A27: FX-P7 | B27: Fix check review | C27: Low | D27: Subcontracts / applications numbering (FA-16) | E27: Any 409 is treated as "number already taken" | F27: Open | G27: Fixed | H27: Only a real "number taken" clash is retried; other errors show the real message. | I27: 25 Oct | J27: finance-done: 900:66 | K27: PostgREST also returns 409 for foreign-key violations (23503). finScInsertNumbered retries 4 times and then says "someone else was saving at the same moment". That is misleading. It is dormant for subcontracts until the proposed unique indexes exist. | L27: src/js/912-finance-subcontracts.js:105; 902-finance-applications.js:470
A28: FX-P8 | B28: Fix check review | C28: Low | D28: BoQ (FB-07) | E28: Edits made while "Save Bill of Quantities" is running are dropped | F28: Open | G28: Fixed | H28: Edits made while Save runs are kept and saved straight after. | I28: 25 Oct | J28: finance-done: 902:222, 9219n:540 | K28: The Save wrapper's finally sets finCtAuto.again=false. An autosave requested during Save (e.g. a line added or moved) is thrown away. The base Save then sets finContractRows=null and re-renders from the database, so the edit is lost from the screen too. | L28: src/js/9219n-finance-newjob.js:535-539; base 902-finance-applications.js:213-275
A29: FX-P9 | B29: Fix check review | C29: Low | D29: Certificate from client's Excel (FB-09) | E29: Uncapped client variation value in the plain certificate path (Needs check) | F29: Needs check | G29: Fixed | H29: The client's variation value is capped at 100% of ours, as line by line. | I29: 25 Oct | J29: finance-done: 9219p:370 | K29: The variation gross uses the client's £ without a cap, and that goes into finCertGross. The 100% cap only happens later, in line-by-line mode, through finPct in finCertTotals (9219p:514). In line-by-line mode, the "Read from the client's Excel: certified to date £X" note shows the uncapped figure while the box underneath shows the capped one. If plain mode (not finCertMode()) is reachable, the saved cert_gross and cert_lines are uncapped. | L29: src/js/9219p-finance-app-export.js:369-379
A30: FX-X1 | B30: Fix check review (outside scope) | C30: Low | D30: Raise invoice (Andy's 24 Oct change) | E30: Phone: "Approve & Issue Invoice" issues the invoice with no confirm | F30: Open | G30: Fixed | H30: Phones now ask before issuing the invoice. | I30: 25 Oct | J30: finance-done: 9219zf:72 | K30: the "✓ Approve & Issue Invoice" box now shows on phones too and calls issueFinInvoice(siteId, true), which skips the confirm. The old Issue button, which had the confirm, is hidden by html.finidpage. On a phone, one tap now issues an invoice and takes the next invoice number, with no confirmation. | L30: 9219zf-finance-raise-invoice.js:38-45, 72
A31: NS-L1 | B31: New screens review | C31: Low | D31: Getting Started (9219zi) | E31: Getting Started is ticked even when Project Admin's save failed, and the tick can arrive after the redraw | F31: Open | G31: Fixed | H31: Getting Started is ticked only when the save worked. | I31: 25 Oct | J31: finance-done: 900:390 | K31: • The wrapper always upserts setup_checked_at after saveSiteFinance returns. The base returns undefined both on success and on every early return: a bad email or retention %, a job-number clash, or the QS save failing in 9219u. • The base has already called render() (not awaited) before this POST, so the redraw may read job_finance before setup_checked_at is written. This race part is "Needs check". | L31: 9219zi-finance-setup.js:105-113. | M31: Map L84
A32: NS-L2 | B32: New screens review | C32: Low | D32: Contract value pop-up (9219zi) | E32: "Keep the typed value" is forgotten by the Save pop-up | F32: Fixed (waiting for Push origin) | G32: Fixed | H32: Fixed on 24 Oct night (tested); live since you pressed Push origin. | I32: 24 Oct (night) | J32: commit 698ae60 | K32: The saveFinContract wrapper shows finCvPrompt whenever the values differ. It never checks the finCvAck key that "Keep typed" stores (only the bar does). | L32: 9219zi-finance-setup.js:54-59. | M32: Map L82
A33: NS-L3 | B33: New screens review | C33: Low | D33: Bill of Quantities layout (9219zk) | E33: Laptop windows narrower than 1100 px, touch laptops and tablets get the phone BoQ list plus the desktop add buttons | F33: Fixed (waiting for Push origin) | G33: Fixed | H33: Fixed on 24 Oct night (tested); live since you pressed Push origin. | I33: 24 Oct (night) | J33: commit 698ae60 | K33: • Between 701 and 1099 px (or on any iPad or touch screen), the page draws the phone list but keeps three sets of add buttons: "+ Section / + Sub-section / + Item" at the top and at the bottom, plus "＋ Add to Bill of Quantities". • The "Apply to ticked" cost tool also stays, but the phone list has no tick boxes. • This contradicts the file's "Computers keep the full grid". | L33: • 9219zk-finance-boq-phone.js:11: finBqPhone() is !isDeskMode(), where desk mode means at least 1100 px wide with a fine pointer. • 9219zk-finance-boq-phone.js:135-137: the CSS hides the old buttons only at max-width:700px.
A34: NS-L4 | B34: New screens review | C34: Low | D34: Sales tiles (9219) | E34: Sales "Applied Value" date fallback never works | F34: Fixed (waiting for Push origin) | G34: Fixed | H34: Fixed on 24 Oct night (tested); live since you pressed Push origin. | I34: 24 Oct (night) | J34: commit 698ae60 | K34: The 24 Oct fallback is dead code. | L34: 9219-finance-sales-tables.js:155-157 uses a.submitted_at||a.created_at, but the select at :102 does not include submitted_at or created_at.
A35: NS-L5 | B35: New screens review | C35: Low | D35: Sales › Applications search (9219) | E35: Applications search promises "client" but can't find by client | F35: Open | G35: Fixed | H35: Applications search finds the client. | I35: 25 Oct | J35: finance-done: 9219:44 | K35: Applications search promises "client" but can't find by client | L35: 9219-finance-sales-tables.js:125 (placeholder "Search application no., project or client") and :49 (data-lf = job tag + "application certificate" + number only).
A36: NS-L6 | B36: New screens review | C36: Low | D36: Finance › Projects list (9219zg) | E36: Finance › Projects: hidden filters keep filtering at other widths, the "n match" count is wrong, and the desktop Sort loses its label | F36: Open | G36: Fixed | H36: Phone filters show a chip, the count is right, and the computer shows its normal Sort. | I36: 25 Oct | J36: finance-done: 9219zg:25 | K36: • A client filter set at a wider width (or before rotating a phone or tablet) still hides rows on the phone, with no visible box and no Clear. • The search box is hidden above 700 px, but finJobQ keeps filtering there. • On a computer, the footer Sort now shows only "Sort ▾" instead of the current choice ("Sort: Newest project no."). | L36: • 9219zg-finance-projects-phone.js:65 hides .finprojfilt (Client box and its Clear) under 700 px. • :9-21: the count ignores rows hidden by the client filter class. • :36-41: the Sort wrap is not limited to phones; .fjq-sort select{opacity:0} is global.
A37: NS-L7 | B37: New screens review | C37: Low | D37: Payment Procedure / contract value source (918, 908, 9219zi) | E37: Switching a project to applications says the BoQ will set the value, but manual projects keep theirs, and values typed in Project Admin are not protected | F37: Fixed (waiting for Push origin) | G37: Fixed | H37: Fixed on 24 Oct night (tested); live since you pressed Push origin. | I37: 24 Oct (night) | J37: commit 698ae60 | K37: • Only a value typed on the new project form is protected ('manual'). A value typed later in Project Admin on an invoice project keeps source=null, so after "Change to applications" the first BoQ autosave silently replaces it. • In the opposite case (new-project value), the confirm promises the BoQ will set it, which it won't. | L37: • 918-finance-billing-type.js:43-45: the confirm text "The contract value will come from the Bill of Quantities". • 900-finance.js:323: saveSiteFinance never sets contract_value_source. | M37: Map L82
A38: NS-L8 | B38: New screens review | C38: Low | D38: New project form (908) | E38: New project: a failed PO insert is silent | F38: Fixed (waiting for Push origin) | G38: Fixed | H38: Fixed on 24 Oct night (tested); live since you pressed Push origin. | I38: 24 Oct (night) | J38: commit 698ae60 | K38: If the insert is refused (RLS, a column problem, or the network), the files are already uploaded and the toast says "Project … created". | L38: 908-finance-standalone.js:140. The dbInsert('client_pos', …) result is not checked. | M38: Map L81
A39: SEC-N1 | B39: Security re-check | C39: Low | D39: Client offline cache / C1 follow-up | E39: OneDrive token responses from the old app are still cached on devices | F39: Open | G39: Fixed | H39: Phones wipe old copies (app) and the database no longer hands out the tokens (C1). Reconnecting OneDrive replaces the old tokens (your task, under SEC-C1). | I39: 25 Oct | J39: core-done: 060:91-111; security batch 1 (C1) | K39: The C1 client fix stops new fetches of the token. Nothing removes the responses the old build already wrote to localStorage. They stay until sign-out or until 300 newer reads push them out. The refresh_token from the admin screen's select=* lasts much longer than an hour. | L39: 060-offline-read-cache.js:46-51 (cacheRows, LRU of 300 entries, CACHE_MAX_ENTRIES at :21); old cache keys onedrive_connections?org_id=eq.<org>&select=access_token (old 380:12) and onedrive_connections?org_id=eq.<org> (old 260:112, select=*, which included the refresh_token). | M39: CP-NEW-2
A40: SEC-N2 | B40: Security re-check | C40: Low | D40: RLS, Finance tables used by the new Overview, BoQ and variations screens | E40: Several finance tables don't check that site_id belongs to your company on write (integrity only); contract_value_source is free text | F40: Open | G40: Fixed | H40: Finance rows can only point at your own company's projects (database). | I40: 25 Oct (batch 3, confirmed 27 Oct) | J40: security batch 3: N2 (site_in_my_org) | K40: A Finance user can save one of their own company's rows against another company's site_id. The other company can't see the row (it's filtered by org), so nothing leaks across companies. But it's inconsistent with the stricter tables, and it lets bad data in (e.g. a pasted wrong UUID). contract_value_source accepts any text. | L40: policies fin_variations_finance, fin_dayworks_finance, fin_job_budgets_finance, fin_job_costs_finance, fin_quotes_finance, fin_quote_items_finance, fin_subcontracts_finance, fin_sub_apps_finance, fin_sub_values_finance and "finance update purchase_orders". Their WITH CHECK is only org_id = my_org_id() AND is_finance(), unlike job_finance, client_pos and fin_contract_items, which also check the site. Client reads at 9219q-finance-summary-cards.js:286-287 and 9219s-finance-boq-tabs.js:264-265.
A41: FX-P10 | B41: Fix check review | C41: Info | D41: Xero edge function (FA-28) | E41: Deploying the repo xero function also ships v10's "don't sync this supplier" check (Needs check) | F41: Needs check | G41: Fixed | H41: Deployed on purpose with Xero v10: suppliers marked "don't sync" are skipped. | I41: 25 Oct | J41: edge deploy 25 Oct (xero v10) | K41: It isn't wrong; the deploy just does more than FA-28. The deployed xero function is version 9 and has neither the no_sync supplier block nor FA-28. The repo copy is the v10 source (project doc "xero function v10 source") plus FA-28, so the deploy switches on both. The columns fin_suppliers.no_sync, supplier_id and name exist. Two other points: if a supplier has more than one fin_suppliers row, maybeSingle errors and the block is skipped. All split lines go to the single purchase account, as unsplit bills do. | L41: supabase/functions/xero/index.ts:337-347 (fin_suppliers.no_sync block) and 349-391 | M41: SEC-N3

Sheet Still to do
A1: Still to do: one list, most important first
A2: Everything still open or partly fixed from the Bugs, Security and New Issues tabs, the left-overs from the fix reports, and your manual tasks. Database changes still need your go-ahead.
A4: Priority | B4: What | C4: Why it matters | D4: Who | E4: Refs | F4: Status
A5: 1 — now | B5: Turn on leaked-password protection | C5: Stops people using passwords that are known to have leaked. Supabase › Authentication › Attack Protection (or Passwords). | D5: You (Andy) | E5: SEC-L10 | F5: Your task
A6: 1 — now | B6: Reconnect OneDrive, and revoke the old Microsoft sessions | C6: The old tokens could have been read before 25 Oct. Admin Centre › Integrations: disconnect and reconnect. Then Microsoft Entra › the OneDrive user › Revoke sessions. | D6: You (Andy) | E6: SEC-C1, SEC-N1 | F6: Your task
A7: 1 — now | B7: Press Push origin for the 26–27 Oct changes (if not done) | C7: Send pop-up, invoice jobs, purchase invoices table, driver time off and the polish are on the laptop; they go live when pushed. | D7: You (Andy) | E7: Changes since v2 | F7: Your task
A8: 2 — soon | B8: Make the storage buckets private and use signed links | C8: Files are now limited to your company inside the app, but anyone with a file's exact web link can still open it. | D8: Claude (database — needs your go-ahead) | E8: SEC-H3 | F8: Partly fixed
A9: 2 — soon | B9: Copy the live Xero and finance-inbox functions into the code | C9: The live versions are newer than the copies in the code. A redeploy from the code would undo the contra line and the inbox checks. | D9: Claude (server function) | E9: SEC-N3 | F9: Partly fixed
A10: 2 — soon | B10: Check a driver can mark a collection as received | C10: If the database doesn't let a driver's login write the "received" mark, it fails quietly. Safer: do it on the server when the delivery task is completed. | D10: Claude (database — needs your go-ahead) | E10: Map L41; materials-done item 4 | F10: Needs check
A11: 2 — soon | B11: Give site variations a value (they reach Finance at £0) | C11: The only Broken money link that reaches the client: site variations arrive in the register and on applications at £0. | D11: Claude (app) | E11: Map L22; P06 | F11: Open
A12: 2 — soon | B12: Holiday approvals checked by the database | C12: Approvals and the limits are only checked in the app, so someone could approve their own holiday through the API. | D12: Claude (database — needs your go-ahead) | E12: CORE-M7 | F12: Open
A13: 2 — soon | B13: Device lock checked by the server at check-in | C13: The app checks the device, but the server accepts a check-in from any device. | D13: Claude (database — needs your go-ahead) | E13: CORE-M3 | F13: Partly fixed
A14: 2 — soon | B14: Finance switch-off restores the old role on every device | C14: The old role is only remembered on the device that gave Finance. The database column now exists; the app needs to use it. | D14: Claude (app) | E14: FA-15 | F14: Partly fixed
A15: 2 — soon | B15: Go-live switches: trial stubs and POs for every PM order | C15: Needed before Finance leaves the trial: fixes Broken links L51, L52, L59 and the PM "To book" badge; PMs without Finance don't raise POs yet. | D15: Claude (app) | E15: P01, P02; Map L28, L51, L52, L59, L73 | F15: Open
... A36: 4 — waiting for you | B36: Repair jobs in Finance | C36: When you ask. | D36: You (Andy) | E36: Map L13–L15; P25 | F36: Later

Sheet Finance-Projects Map v3
A1: How Finance and Projects talk to each other (v3)
A2: Same content as the "Projects ⇄ Finance" map page (data.json, 27 Oct). Status: Working / Partial / Broken / Missing / Needs check / Not needed. Statuses changed only where the 25–26 Oct work or the 24 Oct night fixes (now live) back it up.
A4: ID | B4: Stage | C4: From | D4: To | E4: Trigger (what the user does) | F4: What data moves | G4: Direction | H4: Code location (v2) | I4: Status in v2 | J4: Status now | K4: Notes / gaps (now) | L4: What changed since v2
A5: L01 | B5: 1. Set up the job | C5: Admin Centre › Users / Account settings | D5: Finance access | E5: Admin taps the Finance switch on a user; the user ticks "Show Finance" | F5: profiles.finance_enabled, profiles.finance_hidden | G5: one-way, manual | H5: 900-finance.js:toggleFinanceAccess; 220:setMyFinanceShown; 908:finTeamToggle | I5: Working | J5: Working | K5: finHasAccess() / isFinanceUser() gate every Finance page and tile. Giving Finance to a non-manager from Finance › Team now asks first ("also makes them a manager") and puts the old role back if Finance doesn't switch on (FA-15).
A6: L02 | B6: 1. Set up the job | C6: PM home, site home, Admin Centre, router | D6: Finance pages | E6: Tap the Finance tile or entry | F6: route #/finance, #/site/<id>/finance/... | G6: one-way, manual | H6: 185-pm-home.js:172; 330-site-home.js:228; 260:19; 890-router-render.js:195,453 | I6: Working | J6: Working | K6: Tiles show only when isFinanceUser().
A7: L03 | B7: 11. Reports, Xero & search | C7: Finance book | D7: Site home money strip | E7: A finance user opens a project home (also repair contracts) | F7: finLoadBook → costs to date, invoiced, margin | G7: one-way, automatic | H7: 921-finance-home-strip.js:finHomeStripHtml/finHomeStripFill; called at 330:148, 340:214 | I7: Working | J7: Working | K7: Still the full book (about 17 queries, up to 50,000 check-ins) after paint on every project home. 921:50 redraws #finFcSlot through finForecastCardHtml, which 9219zj now makes return '' (harmless on site home, where there is no slot).
A8: L04 | B8: 1. Set up the job | C8: Finance-only company | D8: Projects router | E8: Any navigation when organizations.has_pm=false | F8: route allow-list | G8: one-way, automatic | H8: 890:60; 908-finance-standalone.js:finOnlyRoute | I8: Working | J8: Working
A9: L05 | B9: 1. Set up the job | C9: Finance › Project Admin | D9: Projects site record | E9: Save project details | F9: sites.name, client_name, address, postcode, start_date, responsible_pm_id, status, job_number | G9: two-way (same row), manual | H9: 900:saveSiteFinance (295); 908:finJobEditPatch; wrapped by 9219n:179, 9219u:68, 9219zi:107 | I9: Working | J9: Working | K9: Finance edits the Projects record directly. The new 9219zi wrapper also stamps job_finance.setup_checked_at after every save (see L84).
A10: L06 | B10: 1. Set up the job | C10: Finance settings › Project numbers | D10: Projects › New site | E10: Create a site while auto numbering is on | F10: organizations.auto_job_numbers, job_number_prefix, next_job_number → sites.job_number | G10: one-way, automatic | H10: 900:saveFinanceSettings, finNextJobNumberLabel; 180-sites-list.js:305,392,415 | I10: Working | J10: Working | K10: next_job_number (and next_invoice_number) are now only written back when the box was actually changed, so a form left open no longer winds the counter back (FA-01). A non-admin is now told the project-number part didn't save (FA-27). Only Finance users can reach this setting.
A11: L07 | B11: 1. Set up the job | C11: Finance › New job | D11: Projects sites | E11: Finance user creates a job | F11: sites row (name, number, status, PM, single/multi/repair, client, address, start) + job_finance row (+ client_pos, see L81) | G11: one-way, manual | H11: 908:openFinNewJob (66), saveFinNewJob (103); 9219e:30-31 | I11: Partial | J11: Partial | K11: Still blocked by the trial wrapper except in Finance-only and Sandbox orgs, so normal companies must create jobs in Projects. The form now asks for "Payment Procedure", always shows the contract value (kept as contract_value_source='manual' for both types) and takes a client PO number and files. The job_finance upsert result is still not checked.
A12: L08 | B12: 1. Set up the job | C12: Projects site client_name / client_email | D12: job_finance billing, sales invoices | E12: Open project Finance, raise an invoice | F12: client_name → fin_clients (matched by name) → job_finance.billing_name/address/email → fin_invoices.bill_* | G12: one-way, automatic | H12: 901-finance-invoices.js:66-67; 9219n:finBillingSync, finBillingSummaryHtml; 9219n:234 "Client not in the Directory"; 9219i:finClientsHtml | I12: Partial | J12: Partial | K12: Still matched by name only (no client_id key). "Pull from Xero" no longer adds the same name twice in one run (FB-28), and the "Client not in the Directory" button now works for names with an apostrophe or ampersand (_jsEsc, then escapeHtml at 9219n:238). A spelling difference on the Projects form still means a duplicate or "not in the Directory".
A13: L09 | B13: 10. Getting paid | C13: Projects site address | D13: Invoice and application PDFs / Excel | E13: Issue an invoice, export an application | F13: sites.address/postcode, job_number, name | G13: one-way, automatic | H13: 901:395; 9219p-finance-app-export.js:231,407 | I13: Working | J13: Working
A14: L10 | B14: 5. Materials & orders | C14: Projects site job_number / postcode / address | D14: Purchase invoice inbox job matching | E14: An invoice is emailed in or uploaded | F14: text matched to sites.job_number, postcode, address line 1, name | G14: one-way, automatic | H14: 9219b-finance-purchases.js:finInboxMatchJob, finInboxAutoProcess; supabase/functions/finance-inbox:matchJob | I14: Partial | J14: Partial | K14: Plots (site_sub_addresses) and repair_jobs addresses are still never checked, so a plot address lands in Unallocated with no sub_job_id. Filing is now "claimed" first (status=eq.new), so two devices can't file the same email twice (FA-03).
A15: L11 | B15: 1. Set up the job | C15: Projects site status | D15: Finance lists and pickers | E15: Close or reopen a job on either side | F15: sites.status (finSiteStatus) | G15: two-way, automatic | H15: 900:finSiteStatus; 9219u:finDeleteJob (763-789) | I15: Working | J15: Working | K15: Closed jobs drop out of the operative-invoice, yard and inbox pickers. Finance's delete now offers "Close it instead" when finance records exist and writes sites.status=closed, closed_at, closed_by (see L88).
A16: L12 | B16: 1. Set up the job | C16: Projects › Delete site | D16: Finance records | E16: PM deletes an empty-looking site | F16: site_is_empty RPC decides | G16: one-way, automatic | H16: 180-sites-list.js:490-529 (deleteSite); 9219u:finDeleteJob | I16: Needs check | J16: Needs check | K16: Projects side unchanged: a PM's delete depends on site_is_empty (not in the repo) and an admin's delete skips the check altogether and hard-deletes the site, finance rows or not. Finance's own delete is now fail-closed and checks 20 finance tables (L88).
A17: L13 | B17: 2. Plan the work | C17: Projects plots/addresses and repair jobs | D17: Finance sub-jobs (costs by plot or repair job) | E17: Open any Finance cost form or report | F17: site_sub_addresses, repair_jobs → FIN_SUBJOBS (sub_job_id) | G17: one-way read, automatic | H17: 917-finance-subjobs.js:finSubJobsLoad; 9219zk:finBqEdit (plot picker) | I17: Working | J17: Working | K17: The new phone BoQ editor (9219zk) also offers the plot / repair-job picker per line (finContractRows[i].sub → fin_contract_items.sub_job_id).
A18: L14 | B18: 2. Plan the work | C18: Repair job variation_cost | D18: Finance sub-job value | E18: Open Costs by repair job | F18: repair_jobs.variation_cost → value | G18: one-way read, automatic | H18: 917:25; 918-finance-billing-type.js:finSubValues | I18: Working | J18: Working
A19: L15 | B19: 10. Getting paid | C19: Repair job "Mark as Invoiced" | D19: Finance sales invoices | E19: PM ticks Invoiced; Finance raises an invoice | F19: repair_jobs.invoiced vs fin_invoices | G19: none | H19: 340-maintenance-repair-contract.js:setRepairJobInvoiced; 901 | I19: Missing | J19: Missing | K19: Still never linked.
A20: L16 | B20: 1. Set up the job | C20: Projects profiles (PM / admin / finance) | D20: Finance QS and PM fields | E20: Project Admin save | F20: job_finance.qs_id, sites.responsible_pm_id | G20: one-way, manual | H20: 9219u-finance-project-admin.js:finQsOptions, saveSiteFinance wrap (68); 908:finJobEditPatch | I20: Working | J20: Working
A21: L17 | B21: 2. Plan the work | C21: Finance Bill of Quantities | D21: Operatives' Schedule of Works | E21: "Send to the operatives' schedule" | F21: fin_contract_items (section/subsection/item, plot) → schedule_sections / schedule_tasks with contract_item_id (no prices) | G21: one-way, manual | H21: 918:finSendToSow (123) | I21: Partial | J21: Partial | K21: Unchanged: deleted BoQ lines leave orphan tasks, qty/unit not carried, repair contracts excluded, a line moved to another plot is only updated.
A22: L18 | B22: 2. Plan the work | C22: Operatives' Schedule of Works | D22: Finance Bill of Quantities | E22: "Copy in N tasks from the site schedule" | F22: schedule_sections/tasks → fin_contract_items, then contract_item_id written back | G22: two-way link, manual | H22: 918:finContractFromSow; 902-finance-applications.js:230-231 | I22: Working | J22: Working | K22: Saving the BoQ now stops if the read of saved lines fails (FA-23/FB-07), so a copy-in can't be doubled by a bad signal.
A23: L19 | B23: 3. Progress on site | C23: SoW task status / percent_complete | D23: Application line % | E23: Open an application; tap "Use site progress" or the "Site 40% Use" tag | F23: schedule_tasks.status, percent_complete averaged per contract_item_id | G23: one-way, suggested | H23: 918:finSiteProgress; 902:467,504; 9219w:finAppUseSiteProgress, finSpUseLine; 9219ze:1950-1955 | I23: Working | J23: Working | K23: The result of "Use site progress" is now autosaved (9219ze wraps both buttons). Still a plain average, not weighted by value; "In progress" with no % counts as 0.
A24: L20 | B24: 3. Progress on site | C24: SoW section progress | D24: Variation % on an application | E24: Open an application | F24: schedule_tasks by section → fin_variations.schedule_section_id / variations.schedule_section_id | G24: one-way, suggested | H24: 9219w:finSiteVarProgress, renderFinApplication wrapper | I24: Working | J24: Working
A25: L21 | B25: 4. Variations & day works | C25: Projects › Variations (raised on site) | D25: Finance variations register | E25: Someone opens BoQ › Variations (or the old register) | F25: variations → fin_variations (variation_id, title, status, quoted, agreed_value) | G25: one-way, automatic on view | H25: 9219s-finance-boq-tabs.js:finCtVariationsFill (92-108); 911-finance-qs.js:finVarFromSite | I25: Partial | J25: Partial | K25: Still imported only when a Finance user opens that tab, and a PM's on-site approval still becomes 'agreed' (client-approved). Later on-site changes are not re-synced. New: a site variation already on a draft application is now linked to its register copy instead of being added twice (FB-03, 9219s:261-279).
A26: L22 | B26: 4. Variations & day works | C26: Site variation cost_impact | D26: Application value / register quoted value | E26: New application, register import | F26: variations.cost_impact → fin_variations.quoted/agreed_value, application variation value | G26: one-way, automatic | H26: 902:448; 911:385; 9219s:103; 9219n:586 | I26: Broken | J26: Broken | K26: 800-variations.js is unchanged and still never writes cost_impact, so site variations still arrive at £0, and an "agreed" one goes onto the application at £0. They now also show at £0 in the Overview's Variations row (L85).
A27: L23 | B27: 4. Variations & day works | C27: Finance variation | D27: Operatives' Schedule of Works | E27: "+ Schedule of Works" on a variation | F27: new schedule_section; fin_variations.schedule_section_id and variations.schedule_section_id | G27: two-way link, manual | H27: 9219n:591-599 (finVarToSow); 9219s:117 | I27: Working | J27: Working
A28: L24 | B28: 4. Variations & day works | C28: Projects "Add variation to schedule" | D28: Finance register "On the schedule" | E28: PM adds an approved site variation to the SoW | F28: variations.schedule_section_id | G28: one-way read | H28: 480-schedule-of-works-from-library-site-side.js:929-933; 9219s:inSow | I28: Working | J28: Working | K28: Site variations auto-closed on site (480:1208) are still not seen by Finance.
A29: L25 | B29: 4. Variations & day works | C29: Finance variation status | D29: Projects variation | E29: Finance marks a variation rejected or agreed | F29: fin_variations.status → variations.approval_status | G29: none | H29: 9219s:finVarSetGroup | I29: Missing | J29: Missing | K29: Still one-way only.
A30: L26 | B30: 4. Variations & day works | C30: Price tile "Variations to Price" | D30: Finance variations / costs | E30: Operative claims extra; PM approves | F30: additional_works_requests (amount, note, photo) | G30: none | H30: 390-pricing-elements.js:211-290 | I30: Missing | J30: Missing
A31: L27 | B31: 4. Variations & day works | C31: Site day work | D31: Finance day works register → applications | E31: Finance types a day work | F31: fin_dayworks (approved) → application dayworks | G31: Finance only, manual | H31: 9219s:176-250; 902:432 | I31: Missing | J31: Missing | K31: Still no day-work sheet on site. Finance-side only: the older Excel upload keeps fin_daywork_id (FA-22) and certificates now carry day-work lines (FB-09).
A32: L28 | B32: 5. Materials & orders | C32: Material Requests › Send order | D32: Finance purchase orders | E32: PM sends a material order (single or grouped) | F32: materials ids, supplier, branch, fulfilment, required date → fin_raise_po → purchase_orders; PO id goes on the order email | G32: one-way, automatic | H32: 760-price-builder-rate-card-admin-centre-wip.js:confirmSendMaterial (501), confirmSendGroupedMaterial (601); 904-finance-purchasing.js:finRaisePoForOrder (12-13) | I32: Partial | J32: Partial | K32: The isFinanceUser() gate is still at 904:13, so PMs without Finance never raise POs, despite the settings text. During the trial fin_raise_po also needs po_enabled.
A33: L29 | B33: 5. Materials & orders | C33: Material Requests › Send again | D33: Finance purchase orders | E33: Re-send an order that was already sent | F33: fin_raise_po called again for the same material ids | G33: one-way, automatic | H33: 760:530 sendMaterialAgain → confirmSend… → 904:finRaisePoForOrder | I33: Needs check | J33: Working | K33: A request on a sent PO is locked in Projects (in the app and in the database), so "Send again" can't raise a second PO. Changes are made on the PO in Finance. | L33: Fixed 25 Oct — sent orders are locked in Projects
A34: L30 | B34: 5. Materials & orders | C34: Material request cancelled / deleted | D34: Finance PO / committed cost | E34: PM cancels or deletes a request after it was ordered | F34: materials.status=cancelled or row deleted; PO unchanged | G34: none | H34: 760:cancelMaterial (264), deleteSelectedMaterials (557); 904:renderFinPo ("Removed" pill) | I34: Missing | J34: Working | K34: Requests on a sent PO are locked in Projects. Cancelling the PO in Finance, or taking lines off it ("Remove lines…"), cancels the matching requests and updates the PO value. Left: reopening a cancelled PO doesn't un-cancel the requests. | L34: Built 25 Oct — Finance changes the PO and the site requests follow
A35: L31 | B35: 5. Materials & orders | C35: Project quotes / shopping list | D35: Material request line and PO price | E35: Pick "From a project quote" when requesting | F35: fin_shop_items id → materials.shop_item_id → PO rate source 'list' | G35: one-way, manual | H35: 915-finance-pricing.js:openShopPicker, pickShopItem, finShopPickFor; 760:282-284; 720:348 | I35: Partial | J35: Partial | K35: Picker still Finance-users-only (720:348).
A36: L32 | B36: 5. Materials & orders | C36: Material request plot / repair job | D36: PO sub_job_id → purchase invoice | E36: Request for Plot 3 is ordered | F36: materials.sub_site_id / repair_job_id → purchase_orders.sub_job_id | G36: one-way, automatic | H36: 917 header; inside fin_raise_po | I36: Needs check | J36: Needs check | K36: Client still passes no sub-job.
A37: L33 | B37: 5. Materials & orders | C37: Goods received note (GRN) on a delivery | D37: PO page, purchase invoice checks | E37: Operative or PM saves a GRN | F37: materials.grn {ok, notes, photos} → PO item "Received / problem", PI query flags, Checks column | G37: one-way, automatic read | H37: 726-suppliers-branches-grn.js:saveGrn; 904:102,125,241-243; 9219g:44-52; 9219b:finInboxFileCore (73-104) | I37: Partial | J37: Partial | K37: A delivery saved with a problem now puts the PO's supplier invoices on query and tells Finance (L34). A driver's collection now counts as received (L41). Still: inbox filing itself doesn't check "not received", and POs raised in Finance have no request lines to receive against. | L37: Notes updated
A38: L34 | B38: 5. Materials & orders | C38: GRN with a problem | D38: Finance team | E38: GRN saved with ok=false | F38: message to site thread only | G38: none to Finance | H38: 726:128-129 | I38: Missing | J38: Working | K38: Saving a delivery with a problem tells Finance (Inbox: "Delivery problem") and puts that PO's supplier invoices on query. Operatives see "the office has been told", with no PO or invoice wording. Tapping the message takes a Finance user to the PO. | L38: Built 25 Oct — delivery problems go to Finance
A39: L35 | B39: 5. Materials & orders | C39: Finance › New PO | D39: Projects Materials, Delivery Schedule, site calendar | E39: Finance raises a PO (909 / 9219zb) | F39: purchase_orders only (fin_new_po) | G39: none to Projects | H39: 909-finance-po.js:108; 9219zb-finance-po-builder.js:142 | I39: Missing | J39: Working | K39: Managers see an "Ordered By The Office" card on the job's Materials (PO number, supplier, delivery or collection date, each line received / problem / not received; no prices). Delivery and collection dates show on the job calendar for everyone and on the all-projects calendar for managers. Operatives never see PO numbers. | L39: Built 25 Oct — office orders and delivery dates show on the job
A40: L36 | B40: 5. Materials & orders | C40: Site team (site_assignments) | D40: Finance PO site contact | E40: Build a PO | F40: site_assignments → contact picker (PM, operatives, admins) | G40: one-way read, manual | H40: 9219zb:65 | I40: Working | J40: Working
A41: L37 | B41: 5. Materials & orders | C41: Projects suppliers list | D41: Finance POs, purchase invoices, inbox | E41: Raise a PO, add a PI, inbox reading | F41: suppliers (id, name, email) | G41: one-way read | H41: 909; 9219zb; 904:174 (datalist); 9219b:44 | I41: Working | J41: Working
A42: L38 | B42: 5. Materials & orders | C42: Projects suppliers ↔ Finance Directory suppliers | D42: Spend, VAT defaults, Xero no-sync | E42: Link in Directory; auto on Xero pull or new PO supplier by exact name | F42: fin_suppliers.supplier_id → suppliers.id | G42: two-way join, manual plus auto-by-name | H42: 9219zc-supplier-link.js; 9219j-finance-directory.js:167-168 | I42: Partial | J42: Partial | K42: Purchase invoices off a PO still keep only supplier_name text; the duplicate check (904:233) now re-runs when supplier or number changes (FA-29) but still matches by name.
A43: L39 | B43: 5. Materials & orders | C43: Directory supplier default VAT | D43: PO lines | E43: Pick the supplier on a Finance PO | F43: fin_suppliers.purchase_vat → line VAT | G43: one-way, automatic | H43: 9219j:271-283; 9219o:finVatKeysWith | I43: Partial | J43: Partial | K43: Still Finance-built POs only; Materials-tile POs use fin_settings.po_vat_default on the server. Drop-downs now show a switched-off rate the record still uses instead of looking like 20% (FB-27).
A44: L40 | B44: 5. Materials & orders | C44: Supplier branches | D44: PO | E44: Order sent to a branch | F44: branch name → purchase_orders.supplier_branch | G44: one-way, automatic | H44: 726; 904:19 | I44: Working | J44: Working
A45: L41 | B45: 5. Materials & orders | C45: Delivery Schedule collection | D45: PO / GRN | E45: Driver completes an order collection | F45: delivery_tasks (no po_id / material ids) | G45: none | H45: 760:bookOrderCollection; 840-delivery-driver.js | I45: Missing | J45: Partial | K45: Booking a collection links the driver's task to the PO and its items. When the driver completes it, each item not yet received is marked received ("Collected by <driver>", with the photos). Needs check: whether the database lets a driver's login write the "received" mark — if not, it fails quietly. Safer: do it on the server when the task is completed. | L45: Built 25 Oct — a driver's collection counts as goods received
A46: L42 | B46: 5. Materials & orders | C46: Projects › Material PO's folders | D46: Finance purchase orders | E46: OneDrive sync or upload of PO PDFs | F46: material_order_files / folders (+ calendar) | G46: none | H46: 770-material-po-s-pm-admin-managed-folders-o.js | I46: Missing | J46: Working | K46: Finance PO PDFs (from "PO PDF" and "Email to supplier") are saved into the job's Material PO's › Finance POs folder, updated in place (no duplicates). Managers only. | L46: Built 25 Oct — Finance PO PDFs appear in Material PO's
A47: L43 | B47: 6. Yard stock | C47: SoW waste / leftover flags | D47: Yard stock / job cost | E47: Operative ticks "Leftover material" or "Waste to clear" | F47: schedule_section_flags → delivery_requests (trigger) → Delivery Schedule | G47: none to Finance | H47: 480:314-405; 870-delivery-schedule-pm-admin-side.js:247-288 | I47: Missing | J47: Not needed | L47: Not wanted (Andy, 25 Oct): SoW waste and leftovers stay separate from the yard.
A48: L44 | B48: 6. Yard stock | C48: Material Requests "Fill from yard stock" | D48: Yard stock + job costs | E48: PM fills a request from the yard | F48: yard_moves (issue, material_id) → yard_stock qty; trigger yard_move_apply → fin_job_costs (qty × rate); materials closed "Yard stock" | G48: one-way, automatic | H48: 720:239,276; 9219m-yard-stock.js:yardMoveOpen, yardMoveSave (190-195) | I48: Needs check | J48: Needs check | K48: Cost still depends on the yard_move_apply trigger; an item without a rate still puts no cost on the job and PMs can't see that. The yard pop-ups are now appended to <body>, so they show on top from any screen.
A49: L45 | B49: 6. Yard stock | C49: Material Requests "📦 Yard stock" chip | D49: Yard stock + job costs | E49: PM quick-issues or returns from the overlay | F49: yard_moves issue/return (site_id) → fin_job_costs | G49: one-way, automatic | H49: 9219m:206-251 (matTopTabsHtml wrap, yardQuickIssue) | I49: Working | J49: Working | K49: Not tied to a material request, so the same need can also be ordered.
A50: L46 | B50: 6. Yard stock | C50: Finance › Purchases "+ Yard Stock" and yard cost edit | D50: Yard and job cost | E50: Finance issues or edits a yard cost | F50: yard_moves, yard_cost_edit RPC, fin_job_costs | G50: two-way, manual | H50: 9219z-finance-purchase-quotes.js:209; 9219zd-price-list-edit.js:113-160 | I50: Working | J50: Working
A51: L47 | B51: 6. Yard stock | C51: Yard "Book stock in" | D51: PO / purchase invoice | E51: Stock is bought for the yard | F51: yard_moves kind=in, rate typed by hand | G51: none | H51: 9219m:yardMoveSave | I51: Missing | J51: Partial | K51: Book stock in from Projects › Materials (PMs), the driver's home screen and Finance › Yard stock. It records item, quantity, supplier, the PO or delivery note number and a photo. Finance users can pick the PO itself, which links the booking to it; PMs and drivers type the number. Not linked to the supplier invoice; rates stay with the office. | L51: Built 25 Oct — book stock in from Projects › Materials (PMs), the driver home screen and Finance; can link to a PO and a delivery note photo
A52: L48 | B52: 7. Labour | C52: Check-ins | D52: PAYE labour cost on the job | E52: Operative checks in | F52: checkins (type=in, site_id, sub_site_id, ts) × fin_labour_rates.day_rate for pay_type paye | G52: one-way, automatic | H52: 9219c-finance-operatives.js:finJobLabour (298-313); 911:69-90; 905:finLabourDaysFrom | I52: Partial | J52: Partial | K52: Unchanged: one full day per person per site per date (two jobs = two day rates), hours ignored, no repair-job allocation.
A53: L49 | B53: 7. Labour | C53: Check-ins | D53: CIS operative invoices | E53: Operative invoice entered | F53: (none) | G53: none | H53: 9219c:saveFinOpInvoice; 9218-finance-payrun.js:finPayLinesFor (unused) | I53: Missing | J53: Missing | K53: finPayLinesFor got the UK-midnight fix (FA-26) but is still never called.
A54: L50 | B54: 7. Labour | C54: Finance operative invoice | D54: Job labour cost | E54: Save an operative invoice | F54: fin_sub_payments.lines[{site_id, amount}] → cost lines; fin_sub_payments.materials → materials cost lines | G54: one-way, automatic | H54: 9219c:saveFinOpInvoice; 911:72-86; 9219g:199-221 (Xero guard) | I54: Working | J54: Working | K54: Materials the operative supplied now reach the job costs as a "Materials supplied by operative" line, shared by each job line's labour value (FA-13). Editing or cancelling one already in Xero now asks first (FA-11).
A55: L51 | B55: 7. Labour | C55: Finance operative invoice | D55: PM Price tile "Wages to book" → price wages | E55: Save or cancel an operative invoice; PM books it | F55: wage_pushes → price_week_operative_entries (+ price_weeks roll-up) | G55: two-way, suggested | H55: 9219c:finOpPushToPm (217); 9217-wage-pushes.js:pmWagePushesHtml (75), pmWagePushBook; 390:965; stubs 9219e:37-38 | I55: Broken | J55: Broken | K55: Still dead: the 9219e stubs replace finOpPushToPm and pmWagePushesHtml. The 24 Oct fixes (withdrawn push zeroes the booked price line, double-tap guard, FA-17) are dormant behind them. Site home still counts pending wage_pushes (330:69).
A56: L52 | B56: 7. Labour | C56: Finance timesheets | D56: wage_pushes | E56: (was: save a timesheet) | F56: fin_labour_manual → wage_pushes | G56: none | H56: 9217:finWagePush (11) | I56: Broken | J56: Broken | K56: Still never called; its withdraw step now uses finWagePushWithdraw. fin_labour_manual rows are still costed.
A57: L53 | B57: 7. Labour | C57: Price tile labour wages / booked in | D57: Finance labour cost and budget | E57: PM types weekly wages per operative, books in price weeks | F57: price_week_operative_entries, price_weeks, pricing_elements.price_total | G57: none | H57: 390:468-630,1595-1761 | I57: Missing | J57: Missing
A58: L54 | B58: 7. Labour | C58: Price tile › Labour Invoices (files) | D58: Finance operative invoices | E58: PM uploads an operative's invoice PDF or Excel | F58: labour_invoices (bucket labour-invoices) | G58: none | H58: 410-labour-invoices.js:uploadLabourInvoices | I58: Missing | J58: Missing
A59: L55 | B59: 7. Labour | C59: Projects operatives (profiles) | D59: Finance People & rates | E59: Open People & rates or Directory › Labour | F59: profiles (operative, site_manager) ↔ fin_labour_rates.user_id | G59: two-way join, manual | H59: 9219d-finance-people.js:16-19; 9219j:296-299; 9216-finance-xero-workers.js:finXwMatch | I59: Working | J59: Working
A60: L56 | B60: 7. Labour | C60: Subcontractor sign-up form | D60: Finance Directory › Labour (CIS) | E60: Finance taps "Add" on a submitted form | F60: subcontractor_applications.data (UTR, CIS status, VAT, company no., address) → fin_labour_rates | G60: one-way, manual | H60: 866/867; 9219j:finDirFromAppDo (333-340) | I60: Working | J60: Working | K60: Insurance expiry dates still not carried over.
A61: L57 | B61: 8. Subcontractors | C61: Projects subcontractor companies | D61: Finance subcontract orders / workers | E61: Subbie set up on site, then ordered in Finance | F61: subcontractor_companies / subcontractor_operatives vs fin_subcontracts.name / fin_labour_rates | G61: none | H61: 380, 550, 570; 912-finance-subcontracts.js:openFinSubcontract | I61: Missing | J61: Missing
A62: L58 | B62: 8. Subcontractors | C62: PM issues a price sheet | D62: Finance subcontract order | E62: Price sheet issued or re-issued | F62: price_builder_sheets → fin_subcontracts (source=price_sheet, order_value follows) via DB trigger fin_sheet_to_order | G62: one-way, automatic | H62: 912 (comment); 9219c:60; 400 | I62: Needs check | J62: Needs check | K62: Trigger still not in the repo.
A63: L59 | B63: 8. Subcontractors | C63: Finance subcontract order | D63: PM Price file (pricing element + issued sheet) | E63: Save a new subcontractor PO with "Add to the project's Price file" ticked | F63: pricing_elements, price_builder_sheets, price_builder_sheet_items, fin_subcontracts.price_sheet_id | G63: one-way, automatic | H63: 912:finScSyncSheet (366), called at 88; checkbox 912:342; stub 9219e:39 | I63: Broken | J63: Broken | K63: Still replaced by the empty stub; the checkbox is still ticked by default on a new order and silently does nothing.
A64: L60 | B64: 8. Subcontractors | C64: Finance subcontract page | D64: PM price sheet | E64: Open a subcontract | F64: price_builder_sheets (title, status, total) | G64: one-way read | H64: 912:113,289-292 | I64: Working | J64: Working
A65: L61 | B65: 8. Subcontractors | C65: Snags on subcontractor work | D65: Subcontract contra charges | E65: Snag raised and assigned | F65: snags vs fin_sub_apps.contra (typed) | G65: none | H65: 500-snagging.js; 912 | I65: Missing | J65: Missing | K65: Contra now counts as paid for CIS (FA-06), but still typed by hand.
A66: L62 | B66: 7. Labour | C66: Delivery driver hours | D66: Labour / transport cost | E66: Driver checks in and out | F66: driver_checkins, driver_breaks | G66: none | H66: 840; 870:driverWeekHoursHtml | I66: Missing | J66: Missing
A67: L63 | B67: 9. Plant & expenses | C67: Plant register | D67: Job plant cost | E67: Plant item transferred to or checked out on a site | F67: plant_items.current_site_id, plant_transfers, plant_checkouts | G67: none | H67: 740-plant-company-wide-plant-tool-register-c.js:transferPlantItemHere, signPlantCheckout | I67: Missing | J67: Missing
A68: L64 | B68: 9. Plant & expenses | C68: External plant hire | D68: Job plant cost | E68: Finance adds a hire | F68: fin_plant_hires (rate × days or "from invoices") → cost lines | G68: Finance only, manual | H68: 905-finance-labour-plant.js:openFinPlantForm, finPlantCost; 911:87-90; 910:589-606 | I68: Partial | J68: Partial | K68: Inside Finance the plant card no longer double-counts hires costed from invoices (FA-20). Site still has no view of what is on hire and no off-hire request.
A69: L65 | B69: 10. Getting paid | C69: Projects handover / practical completion | D69: Retention release dates | E69: Handover O&M issued, job completed | F69: job_finance.pc_date typed in Finance | G69: none | H69: 903-finance-certs-retention.js:182-195; 9219zh:finRetSetDate; 857-handover-om-manual.js | I69: Missing | J69: Missing | K69: Still nothing from Projects. The dates can now also be typed in Sales › Retention (L83), but that is still Finance typing them.
A70: L66 | B70: 3. Progress on site | C70: Finance application and payment dates | D70: Site calendar / PM home | E70: Application day set | F70: job_finance.app_reminder_day, app_dates; fin_applications.final_date | G70: none | H70: 918:finAppDatesHtml; 780-site-calendar | I70: Missing | J70: Working | K70: Each month's application date shows on the job calendar and the all-projects calendar ("💷 Application due", or "sent" once it has gone) for PMs, admins, estimators, QSs and Finance users. Tap one to open the project's Finance. Payment due dates are not shown. | L70: Built 25 Oct — application dates now show on the site and all-projects calendars for PMs, admins, estimators and QSs
A71: L67 | B71: 3. Progress on site | C71: SoW photos | D71: Application evidence | E71: Value an application | F71: schedule_photos | G71: none | H71: 481/480; 9219p | I71: Missing | J71: Working | K71: Application PDF, Excel and email can include the Schedule of Works report as proof of works: the whole schedule, or only the photos taken since the last application. | L71: Built 25 Oct — application exports and emails can include the Schedule of Works report as proof of works
A72: L68 | B72: 9. Plant & expenses | C72: Expenses (inside Materials) | D72: Finance receipts / job costs | E72: Operative photographs a receipt and saves | F72: expenses rows (no amount) → send-expenses-email | G72: none | H72: 590-expenses-sub-tile-inside-materials.js:151-183 | I72: Missing | J72: Missing
A73: L69 | B73: 11. Reports, Xero & search | C73: Finance sales invoices, bills, operative payments | D73: Xero (project tracking) | E73: Approve, issue, post | F73: fin_invoices, purchase_invoices, fin_sub_payments + sites.job_number/name as tracking option | G73: one-way, automatic or manual | H73: 907-finance-xero.js; supabase/functions/xero/index.ts:push_bill (350-400), push_sub_payment (402+); 904:finXeroPostedConfirm | I73: Partial | J73: Partial | K73: Xero v10 is live (25 Oct): a bill split across projects goes as one line per project, each tracked to its job (FA-28), and a subcontract bill has a minus line for the contra charge. Changing a record already in Xero is blocked unless you confirm (FA-11). Still one account (310), no cost-code coding, and operative payments carry no project tracking. Still blocked outside Sandbox during the trial. | L73: Fixed 25 Oct — per-project bill lines and the contra line are live
A74: L70 | B74: 11. Reports, Xero & search | C74: Xero contacts and payroll | D74: Finance people, clients, suppliers | E74: "Bring in from Xero", "Pull from Xero" | F74: Xero contacts/employees → fin_labour_rates (matched to profiles), fin_clients, fin_suppliers (auto-linked to suppliers by name) | G74: one-way, manual | H74: 9216:finXwMatch; 9219i:51-66; 9219j:154-168 | I74: Working | J74: Working | K74: The same contact twice in one pull now updates instead of duplicating (FB-28).
A75: L71 | B75: 11. Reports, Xero & search | C75: Projects data (check-ins, sites, plots) | D75: Finance reports, monthly report, detailed summary | E75: Open a report | F75: finLoadBook (checkins, sub-jobs, etc.) | G75: one-way read | H75: 913-finance-reports.js:finRepBookLoad; 920-finance-monthly.js; 9219v-finance-detail-summary.js | I75: Working | J75: Working | K75: "Labour by person" now takes days from the operative invoice line and leaves unknown days blank (FA-25); cash flow counts VAT on cash in (FA-04); stat periods cover the whole month/quarter/year. The org-wide book still pulls up to 50,000 check-ins with no date filter (911:24).
A76: L72 | B76: 3. Progress on site | C76: Projects site reports / daily briefings | D76: Finance | E76: Site report submitted | F76: report_submissions (headcount, weather, delays) | G76: none | H76: 430, 700 | I76: Missing | J76: Missing
A77: L73 | B77: 5. Materials & orders | C77: Finance inbox | D77: PM "To book" screen | E77: Finance sends an unallocated invoice to a PM; PM books or replies | F77: fin_inbox.stage=with_pm, assigned_pm → fin_inbox_pm_book / fin_inbox_pm_reply → purchase_invoices | G77: two-way, manual | H77: 9219b:finInboxSendPm (291), pmToBookCounts (324), renderPmToBook (335); 890:82; 185:124; stub 9219e:36 | I77: Partial | J77: Partial | K77: Unchanged: sending is blocked outside Sandbox (9219e:27-28) and the PM home badge is always 0 because of the pmToBookCounts stub.
A78: L74 | B78: 5. Materials & orders | C78: Purchase invoice query | D78: Responsible PM | E78: Finance marks an invoice Query | F78: purchase_invoices.status=query, query_note | G78: none | H78: 904:queryPurchaseInvoice, savePurchaseInvoiceQuery | I78: Missing | J78: Working | K78: Marking a supplier invoice Query messages the job's responsible PM. The PM answers in a pop-up (no Finance access needed); the conversation shows on the invoice in Finance, and Finance can reply. | L78: Built 25 Oct — invoice queries go to the PM
A79: L75 | B79: 2. Plan the work | C79: Drawings | D79: Finance (BoQ, variations) | E79: — | F79: drawing_files | G79: none | H79: 810 | I79: Missing | J79: Missing
A80: L76 | B80: 2. Plan the work | C80: Rate card / price sheets | D80: Bill of Quantities cost prices | E80: Price a BoQ line | F80: price_rate_items/options, price_builder_sheet_items vs fin_contract_items.cost | G80: none | H80: 760:12-228; 400; 902 / 9219zk (BoQ editors) | I80: Missing | J80: Missing | K80: The new phone BoQ editor still takes cost rate/total typed by hand.
A81: L77 | B81: 2. Plan the work | C81: SoW library templates | D81: Bill of Quantities | E81: Start a BoQ | F81: sow_library_templates/sections/tasks | G81: none | H81: 290; 480:60-71 | I81: Missing | J81: Missing
A82: L78 | B82: 5. Materials & orders | C82: Finance price book / project quotes | D82: Materials-tile PO pricing | E82: Order sent | F82: fin_price_book, fin_shop_prices → PO rate (estimate) | G82: one-way, automatic | H82: 915 header; fin_raise_po | I82: Needs check | J82: Needs check
A83: L79 | B83: 11. Reports, Xero & search | C83: Projects app search | D83: Finance records | E83: Search box | F83: materials, snags, todos (270); projects, people, reports, documents (136 quick search) | G83: none | H83: 270-app-search-home-screen.js; 136-quick-search.js | I83: Missing | J83: Missing | K83: Still no PO, invoice or application numbers. Finance's own Sales list search now matches application / certificate numbers, and Finance › Projects has a phone search (L87), but neither is the app search.
A84: L80 | B84: 5. Materials & orders | C84: Material request message | D84: Finance | E84: Request added or sent | F84: postSystemMessage to the site thread | G84: none to Finance | H84: 760:287 | I84: Missing | J84: Partial | K84: The note typed when sending an order (branch and message) now goes on the PO, so Finance sees it. Other request messages still go only to the job's message thread. | L84: Built 25 Oct — the order note goes on the PO
A85: L81 | B85: 1. Set up the job | C85: Finance › New project form (and Project Admin › Client PO) | D85: Project's client PO → invoices, applications, certificates, Finance Projects list "Client PO" column, Getting Started | E85: Create a project with a client PO number and files; add or edit a PO later | F85: client_pos {po_number, is_primary:true, files:[{path,name}], file_path/file_name = first file}; files to finance-docs/<org>/<site>/client-po/ | G85: one-way, manual | H85: 908:saveFinNewJob (109-112, 132-142); 900:saveClientPo (370-395), finPoFilesOf, openClientPoFile (405-425) | I85: Partial | J85: Partial | K85: Works, and a PO now holds any number of files (picker when more than one). Gaps: the form is only reachable in Finance-only and Sandbox orgs (trial wrapper, L07), so normal companies add the PO afterwards in Project Admin; the client_pos insert result is not checked, so "Project created" still shows if it fails (dbInsert's own toast is quickly replaced); the Projects-side new-site form (180) has no PO field. | L85: Gap fixed 25 Oct — the PO now always saves or says it didn't (now live)
A86: L82 | B86: 1. Set up the job | C86: Typed contract value (new project / Project Admin) ↔ Bill of Quantities total | D86: job_finance.contract_value | E86: Save the BoQ (button or autosave), add a BoQ line from an application, open the BoQ page | F86: job_finance.contract_value_source ('manual' / 'boq' / null), contract_value, contract_value_manual vs sum of fin_contract_items values | G86: two-way check, manual choice | H86: 9219zi:finCvPatch (12-15), finCvCheck, finCvUse, finCvPrompt, saveFinContract and renderFinContract wraps; used at 902:243, 9219n:522, 9219n:739 | I86: Partial | J86: Partial | K86: A typed value is no longer overwritten by BoQ saves, and a pop-up (after Save) or a bar (on the BoQ page) offers "Use BoQ" or "Keep typed". Gaps: finCvPatch treats a failed read as "not manual" and overwrites the typed value; "Keep typed" is remembered in localStorage only, so other devices keep showing the bar; Project Admin edits of the contract value never set contract_value_source, so on a project created without a value the next BoQ save silently replaces it; 9219n:740 still sets finAppCtx.jf.contract_value to the BoQ total in memory, so the retention cap on that application screen uses the wrong figure until reload; contract_value_manual is written but never read. | L86: Gap fixed 25 Oct — a typed value is never overwritten on a bad signal (now live)
A87: L83 | B87: 10. Getting paid | C87: Finance › Sales › Retention list | D87: Project retention dates (job_finance) → project Retention card, Finance home reminders, retention report | E87: Type a "1st Retention Release" or "Final Retention Release" date in the list | F87: pc_date; final_release_date (+ defects_months recomputed from the gap) | G87: one-way, manual | H87: 9219:146 (date boxes); 9219zh:finRetSetDate (16-24), finRetentionDates override (8-15) | I87: Partial | J87: Working | K87: Saves to the project. Since the 24 Oct night fix (now live), Project Admin and the typed final release date agree, and Finance home reminders use the final date. Invoice jobs have no retention dates (26 Oct). Only projects with retention still held are listed. | L87: Gap fixed 25 Oct — Project Admin and Finance home now agree on the final date
A88: L84 | B88: 1. Set up the job | C88: Project set-up state (job_finance, client_pos, BoQ lines, invoices, applications) | D88: Getting Started card on the project Overview | E88: Open the project; tap "✓ Done"; save Project Admin | F88: job_finance.setup_checked_at; counts of BoQ items, client POs, invoices, applications | G88: one-way read (plus manual tick) | H88: 9219zi:finStartCardHtml (87-104), finSetupDone (82-86), saveSiteFinance wrap (106-112); 9219n:217 | I88: Partial | J88: Working | K88: Finished steps drop off and the card goes once any invoice or application exists. Since 25 Oct the "Check retention, VAT and application dates" step is only ticked when the Project Admin save worked (NS-L1). | L88: Gap fixed 25 Oct — only ticked when the save worked
A89: L85 | B89: 4. Variations & day works | C89: Finance variations and day works registers (incl. site variations once imported, L21) | D89: Project Overview "Variations & Day Works" row | E89: Open the project Overview; ⋯ picks Approved / Unapproved / All; tap opens BoQ › Variations or Day Works | F89: fin_variations (status, quoted, agreed_value), fin_dayworks (status, value) | G89: one-way read | H89: 9219q:finVdRowHtml, finVdTotals, finVdLoad (265-303); 9219zj:finOvBlockHtml | I89: Partial | J89: Partial | K89: Totals load once per project and are cached in FIN_VD_DATA for the whole session, so a new or approved variation doesn't show until the app is reloaded. It reads fin_variations only, so site variations count only after someone has opened BoQ › Variations, and then at £0 (L22) and as Approved (L21). Unpriced variations show £0 here but at their cost_estimate in the register. | L89: Gap fixed 25 Oct — now the Variations tile on the Overview, refreshed each time (now live)
A90: L86 | B90: 11. Reports, Xero & search | C90: Projects-derived job book (check-in labour, plots, POs, purchase invoices) + job_finance | D90: Project Overview block (headline Final Account / Contract Value, margin pill, progress bar, 8 boxes) | E90: Open a project's Finance Overview | F90: finLoadBook → finJobForecast (window.__finFcLast) → finOvBlockHtml; box choices in localStorage | G90: one-way read | H90: 9219zj (whole file); 9219q:finTopVal; 900:290 | I90: Working | J90: Working | K90: Replaces the coloured tiles and the Project Summary card; finForecastCardHtml still runs for its side effects and now returns ''. Retention box uses "still held".
A91: L87 | B91: 1. Set up the job | C91: Projects site fields (job no., name, client, PM, postcode) + client POs | D91: Finance › Projects list search on a phone | E91: Type in "Search projects" | F91: data-lf text of each row (sites + client_pos) | G91: one-way read | H91: 9219zg:finJobPhoneTidy, finJobSearchApply; 9219f:finJobGridHtml (58) | I91: Working | J91: Working | K91: Phone only; replaces the Client box. Computers keep the column filters.
A92: L88 | B92: 1. Set up the job | C92: Finance › Delete project | D92: Projects site (close or delete) | E92: Delete from Finance project admin | F92: checks 20 finance tables incl. operative-invoice lines; if any rows → sites.status=closed, closed_at, closed_by; else → Projects deleteSite | G92: one-way, manual | H92: 9219u:finDeleteJob (763-789); 180:deleteSite (490) | I92: Working | J92: Working | K92: Fail-closed: any failed lookup stops the delete. fin_statements has no project link, so it can't be checked. When nothing financial is booked, a PM's delete still depends on site_is_empty (L12).

Sheet Proposals
A1: Proposals: more interlinking between Projects and Finance
A2: Copied from v2 unchanged (Done? is as of 24 Oct). Since then P05, P20 (application dates), P27 and P29 have been built, and P03 partly: see Finance-Projects Map v3.
A4: # | B4: Proposal | C4: What it does | D4: Tables / screens | E4: Benefit | F4: Effort (S/M/L) | G4: Done? | H4: Suggested phase | I4: Note
A5: P01 | B5: Make the trial stubs conditional | C5: Change the four plain async function stubs in 9219e to if(FIN_TRIAL && !finIsSandbox()) window.x = … style overrides, so operative-invoice → PM wages, the To-book badge and subcontract → price sheet work in Sandbox and turn on at go-live just by setting FIN_TRIAL=false. Hide the "Add to Price file" tick while it's off. | D5: 9219e; 9219c finOpPushToPm; 9217; 912 finScSyncSheet; 9219b pmToBookCounts | E5: Fixes 3 Broken links (L51, L59, L73) and makes Sandbox testing true to live | F5: S | G5: No | H5: 1 — next | I5: the four stubs are still plain declarations at 9219e:36-39. The FA-17 wage-push fixes and the 9219g operative-invoice guard call finOpPushToPm, which is still the empty stub.
A6: P02 | B6: POs for every PM's order | C6: Drop the client isFinanceUser() gate in finRaisePoForOrder and let fin_raise_po check po_enabled. Correct the settings wording. | D6: 904; 900 settings; fin_raise_po | E6: Every material order gets a PO and committed cost, not just Finance users' (L28) | F6: S | G6: No | H6: 1 — next
A7: P03 | B7: Keep POs in step with requests | C7: Cancelling, deleting or re-sending a material request cancels or reduces the PO line (or asks first), and stops duplicate POs on re-send. | D7: materials, purchase_orders; 760 cancelMaterial, deleteSelectedMaterials, sendMaterialAgain | E7: Committed cost stays right; no duplicate POs (L29, L30) | F7: S | G7: No | H7: 1 — next
A8: P04 | B8: GRN for every PO | C8: A "Receive" action per PO line (a po_receipts table, or materials rows made for Finance POs) shown on the project Materials tile as "Ordered by the office". Port the GRN checks into finInboxFileCore. | D8: purchase_orders, materials.grn / po_receipts; 9219b finInboxFileCore; 720/726 | E8: Three-way match (PO, GRN, invoice) works for all invoices, including inbox ones (L33, L35) | F8: M | G8: No | H8: 2 — soon
A9: P05 | B9: Driver collection = GRN | C9: Store po_id/material_ids on delivery_tasks made by bookOrderCollection. When the driver completes it, write the GRN with the driver's photos. | D9: delivery_tasks, materials.grn; 760, 840 | E9: No separate GRN step for collections (L41) | F9: M | G9: No | H9: 2 — soon
A10: P06 | B10: Give site variations a value and sync both ways | C10: Add "Our price / client price" to Projects › Variations (fills cost_impact). Import site approvals as 'issued', not 'agreed'. Push Finance agreed/rejected back to variations.approval_status. Import when the variation is created (trigger), not when the tab is opened. | D10: variations, fin_variations; 800, 9219s finCtVariationsFill, 902 newFinApplication | E10: Variations reach applications at the right value and only once the client has agreed (L21, L22, L25) | F10: M | G10: No | H10: 1 — next
A11: P07 | B11: Extra-work claims → client variation | C11: When a PM approves an additional_works_request, offer "Also raise a client variation", creating fin_variations with cost_estimate = amount and photo attached. | D11: additional_works_requests, fin_variations; 390 | E11: Recovers extra work that is paid to operatives but never billed (L26) | F11: S | G11: No | H11: 2 — soon
A12: P08 | B12: Site day-work sheets | C12: A day-work form on site (labour from that day's check-ins, plant, materials, client signature) that creates an 'issued' fin_dayworks row with the signed PDF. | D12: new site screen; fin_dayworks; checkins | E12: Day works are captured on the day with evidence, not reconstructed later (L27) | F12: M | G12: No | H12: 2 — soon
A13: P09 | B13: Fair PAYE day costing | C13: Split a person's day across the jobs they signed into, by check-in/check-out time (or evenly), and allow hourly rates. Add repair_job_id to check-ins on repair contracts. | D13: checkins, fin_labour_rates; 9219c finJobLabour, 911 cost lines, 440/450 | E13: Stops double day-rates; labour by repair job (L48) | F13: S/M | G13: No | H13: 2 — soon
A14: P10 | B14: Sign-in vs invoice check | C14: On an operative invoice, show the days signed in per job for that week next to each line and flag invoiced jobs with no sign-ins. | D14: checkins, fin_sub_payments; 9219c finOpPaint | E14: Catches over-claiming and wrong-job allocations (L49) | F14: S | G14: No | H14: 1 — next
A15: P11 | B15: One place for labour invoices | C15: Uploading a labour invoice in the Price tile creates a draft operative invoice for Finance (file shared). Finance's operative invoice shows in that pricing element's Labour Invoices list. | D15: labour_invoices, fin_sub_payments; 410, 9219c | E15: Ends double upload and double typing (L54) | F15: M | G15: No | H15: 2 — soon
A16: P12 | B16: Price tile → Finance labour budget and accrual | C16: Use pricing_elements.price_total as the labour budget suggestion and price_week_operative_entries / booked-in as labour accrued, before the operative invoice arrives. | D16: pricing_elements, price_weeks, price_week_operative_entries, fin_job_budgets; 911 finJobForecast | E16: Labour forecast without retyping; early warning when price work runs over (L53) | F16: M | G16: No | H16: 2 — soon
A17: P13 | B17: Internal plant hire charges | C17: Add a Finance-only internal rate per plant item (like yard_stock_rates). Transfers and check-outs to a site create or close fin_plant_hires (cost_from rate) automatically. | D17: plant_items, plant_transfers, plant_checkouts, fin_plant_hires; 740, 905 | E17: Owned plant carries a cost to the job (L63) | F17: M | G17: No | H17: 3 — later
... A22: P18 | B22: Rate card and SoW library feed the BoQ | C22: When building a BoQ, pick lines from the SoW library and suggest cost prices from the rate card or a price sheet (fin_contract_items.cost). | D22: sow_library_*, price_rate_items, fin_contract_items; 290, 760, 902 | E22: Quicker BoQs with a real cost budget (L76, L77) | F22: M/L | G22: No | H22: 3 — later
A23: P19 | B23: Practical completion date from Projects | C23: Issuing the handover O&M (or closing the site) suggests job_finance.pc_date, so retention release dates and reminders start. | D23: handover_om_manuals, sites, job_finance; 857, 903 | E23: Retention isn't forgotten (L65) | F23: S | G23: No | H23: 1 — next | I23: the PC date and the final release date can now be typed in Sales › Retention (L83), but nothing comes from Projects handover or site close.
A24: P20 | B24: Money dates on calendars | C24: Put the application date, final date for payment and PO required-by dates on the site calendar and PM home (managers only). | D24: site_calendar_events, job_finance, fin_applications, purchase_orders; 780, 790 | E24: PMs see when valuations and deliveries fall due (L66) | F24: S | G24: No | H24: 3 — later
A25: P21 | B25: Finance ↔ PM notifications | C25: Message the responsible PM when a purchase invoice is queried, a GRN problem affects an invoice, plant has been on hire over 4 weeks or a PO has no value. Message Finance when a GRN has a problem. | D25: messages (postSystemMessageToUser); 904, 726, 905 | E25: Problems are sorted out on site straight away (L34, L74, L80) | F25: S | G25: No | H25: 1 — next
A26: P22 | B26: Inbox matching knows plots and repair jobs | C26: Match inbox invoices against site_sub_addresses and repair_jobs addresses and postcodes, set sub_job_id, and include the PO's sub-job. | D26: 9219b finInboxMatchJob; finance-inbox matchJob | E26: Fewer Unallocated invoices; costs by plot are right (L10) | F26: S | G26: No | H26: 1 — next
A27: P23 | B27: Xero bills by cost code and project split | C27: Post bill lines per cost code (fin_cost_codes.code as AccountCode) and per project share, each with its own tracking option. Track operative payments per job line. | D27: xero function push_bill, push_sub_payment; 9219g splits | E27: Xero P&L by project matches OpHUB (L69) | F27: M | G27: Partly | H27: 3 — later | I27: the repo copy of the xero function (push_bill, index.ts:363-388) now sends a bill split across projects as one line per project, each with its own tracking option (FA-28). It is not deployed yet according to fix-B. Bills still post to one account (xero_purchase_account or 310), not per cost code, and push_sub_payment still sends no project tracking.
A28: P24 | B28: Real client link | C28: Add sites.client_id → fin_clients. The Projects new-site form picks from the client list (names only for PMs). Stop name matching. | D28: sites, fin_clients, job_finance; 180, 9219n, 9219i | E28: No duplicate clients; billing details always right (L08) | F28: M | G28: No | H28: 1 — next | I28: FB-28 only stops duplicates within one Xero pull; matching is still by name.
A29: P25 | B29: Repair job invoiced from Finance | C29: Raising a fin_invoice with sub_job_id = a repair job ticks repair_jobs.invoiced. "Closed — Subject to Invoice" jobs show in Finance as "To invoice" with their variation_cost. | D29: repair_jobs, fin_invoices; 340, 901, 917 | E29: Nothing signed off is left un-invoiced (L15) | F29: S | G29: No | H29: 2 — soon
A30: P26 | B30: Yard stock in from purchases, leftovers back | C30: Allow a PO or GRN "to the yard" that books stock in at the invoice price (weighted average rate). A leftover-material flag on site offers a yard return (credit to the job). | D30: yard_moves, yard_stock_rates, purchase_orders, schedule_section_flags; 9219m, 480 | E30: Yard value and job credits are right (L43, L47) | F30: M | G30: No | H30: 3 — later
A31: P27 | B31: Finance POs on the project | C31: Show Finance-raised POs on the project's Materials tile, put the required-by date on the site calendar, and offer the same delivery/collection booking as Materials orders. Put PO PDFs in the Material PO's folder. | D31: purchase_orders, material_order_files, delivery_tasks, site_calendar_events; 720, 770, 870, 909 | E31: The site knows what is coming (L35, L42) | F31: M | G31: No | H31: 2 — soon
A32: P28 | B32: Tidy BoQ → SoW sync | C32: Flag or remove tasks whose BoQ line was deleted, carry qty/unit to the task, and show which BoQ line a task belongs to (managers only). | D32: schedule_tasks.contract_item_id; 918 finSendToSow | E32: Site progress maps cleanly to applications (L17) | F32: S | G32: No | H32: 2 — soon
A33: P29 | B33: Progress photos in applications | C33: Attach the latest SoW photos per BoQ line to the application export or email pack. | D33: schedule_photos, fin_applications; 9219p | E33: Faster certification by the client's QS (L67) | F33: M | G33: No | H33: 3 — later
A34: P30 | B34: Search Finance records | C34: App search for Finance users finds PO, invoice, application and subcontract numbers and opens them. | D34: 270 app search; purchase_orders, fin_invoices, fin_applications | E34: Quick lookup from anywhere (L79) | F34: S | G34: No | H34: 1 — next | I34: the new searches are inside Finance lists (Sales applications, Finance › Projects on a phone), not the app search.
A35: P31 | B35: Site diary feeds commercial | C35: Daily briefing / site report headcount and delay entries show on the Finance project page (labour sanity check, delay log for extension-of-time claims). | D35: report_submissions, 9219v detailed summary | E35: Commercial evidence without retyping (L72) | F35: L | G35: No | H35: 3 — later
A36: P32 | B36: Lighter home money strip | C36: Cache the project book (or use a small summary RPC) for the site-home strip instead of the full 17-query load on every visit. | D36: 921, 911 finLoadBook | E36: Faster project home on phones (L03) | F36: S | G36: No | H36: 1 — next

Sheet Competitors
A1: Top 10 construction & trade apps — deep dive
A2: Researched 23–24 Oct 2026. [V] = checked on a current page; [K] = from background knowledge, not re-checked; estimates are labelled.
A3: This research is from 23–24 Oct 2026 and was not redone for v3.
A5: Product | B5: Type | C5: Best for | D5: UK fit | E5: Price (UK where known) | F5: Finance depth (job ↔ money) | G5: Who / UK presence / pricing detail | H5: Modules & features | I5: How their finance links to jobs | J5: Ideas for OpHUB | K5: Weaknesses / complaints | L5: Sources
A6: Simpro | B6: Field service + project ERP | C6: M&E, fire/security, service + project contractors, 10–500 staff | D6: Strong (UK office; owns Leeds-based BigChange since Oct 2024) | E6: Quote only, per user [V] | F6: High: progress claims, retention, stock, catalogues, WIP | G6: • What: End-to-end job and project management for trade contractors, from quote to invoice. Simpro Group also owns BigChange (UK, bought 25 Oct 2024), AroFlo (AU) and ClockShark (US time tracking). The group reports 22,000+ businesses, 400,000+ users and 600+ staff [V, Business Wire 2024]. • Who: Electrical, plumbing, HVAC, fire and security, solar, and M&E project and service contractors, typically 10–500 staff. • UK: UK office and UK web pages (simprogroup.com/uk) [V]. With BigChange's Leeds base it is now one of the largest field-service vendors in the UK. • Pricing: Quote only, per user per month. Capterra lists three bundles with no prices: *Premium*; *Premium & Digital Forms* (drag-and-drop form builder); *Premium & Data Feeds* (automatic extraction from PDF/CSV/Excel attachments with rule-based triggers). No free trial [V, Capterra, Oct 2026]. Toolradar (Sep 2026) also lists "request pricing". Typical quotes are usually reported at several hundred pounds a month for small teams, with onboarding fees [K – confirm]. | H6: | Area | Detail | |---|---| | Quoting / estimating | Multi-section quotes by cost centre; pre-builds (kits of materials + labour); catalogue pricing synced from suppliers; quote → job conversion; options/variations on quotes [V/K] | | Job / project management | Project overview comparing actual vs estimated material and labour, with original, revised and current budgets; milestones; linked invoices, POs and work orders [V, Simpro blog] | | Scheduling / dispatch | Drag-and-drop scheduler; RAIN (8 Jul 2026): AI scheduler assigning technicians by location, skills, certifications and availability [V] | | Timesheets / labour | Clock on/off by job and cost centre from mobile; labour at cost rate for costing and separate charge-out rates for billing [K] | | Materials & purchasing | Supplier catalogues synced automatically; request prices from several suppliers at once and compare side by side; POs restock and receipting updates stock; Price Discrepancies report comparing catalogue/PO cost with invoice cost [V] | | Stock | Multiple storage locations including vans; warehouse → van transfers; pre-allocate stock to a job; RAIN adds phone stock-takes and van-to-van transfers [V] | | Plant / assets | Asset register with test and maintenance history (e.g. fire extinguishers, PAT) [K] | | Subcontractors | Contractor work orders against jobs; contractor invoices to job cost [K]; UK CIS handled via accounts package [K – confirm] | | Variations | Variations on projects updating revised budget [K] | | Applications / retention | Deposits, Requests for Claim (client approves a claim before it becomes an invoice and before anything posts to accounts), progress claims, retention set to match the head contract (flat or sliding) with alerts when retention is due [V, Simpro blog 2019 – may be dated] | | Invoicing | Approval stages (Pending → Approved), per-user approval value limits, blocking unapproved invoices from being emailed [V] | | Accounting | Xero, MYOB, QuickBooks; Sage via connectors in UK [V/K] | | Job costing / WIP | Job cost vs estimate; Job WIP report [K]; BI reporting | | H&S / forms | Digital forms builder (paid bundle); RAIN adds photo-based smart safety forms (in AroFlo) [V] | | Customer portal | Customer portal to view quotes, jobs and invoices [K] | | Mobile | Simpro Mobile: job details, photos, signatures, materials used on site [V] | | AI | "Cooper" AI layer across Simpro, AroFlo and BigChange; RAIN (Jul 2026) brought the AI scheduler, live re-optimisation, native CRM/sales pipeline, AI-checked photo capture (BigChange), smart safety forms (AroFlo) and field inventory control [V] | | I6: • Quote → job → invoice. The cost centres in the quote become the job's budget lines. Labour, materials and contractor costs post to those cost centres. Progress claims are raised per cost centre or for the whole job. • Stock → job. Stock allocated or used from a van posts to the job at cost. • PO → supplier invoice. Receipting a PO updates stock and cost. The Price Discrepancies report flags invoice prices that differ from the PO or catalogue. • Budget revisions. Original, revised and current budgets are kept separately, so margin fade is visible. • Claims and retention. Each progress claim deducts retention and keeps a running retention balance. An alert tells you when to raise the retention claim. | J6: 1. Three budget columns (Original / Revised / Current) on Finance › Budget, with a log of every budget change and who approved it. 2. Approval value limits per user on POs and purchase invoices (e.g. PMs up to £2,500, above that goes to Andy). 3. Client "request for claim" draft. Send the client QS a draft application to agree before the formal application or invoice is raised and pushed to Xero. 4. Skills-aware scheduling. Only show operatives holding valid cards (CSCS, IPAF, PASMA, working at height, asbestos awareness) when allocating to a site whose RAMS needs them. 5. Field stock-take from a phone for yard stock and vans (count → adjustment move). | K6: Capterra UK 3.9/5 (151 reviews) [V]. Common themes: steep learning curve and many clicks; mobile app lag and sync problems after updates; slow support; occasional bugs and outages; it can need a full-time person to keep data up to date; POs and work orders must be handled carefully or job financials go wrong; contracts hard to change, and price rises [V]. --- | L6: • Capterra UK reviews (rating, pros/cons): https://www.capterra.co.uk/reviews/10529/simpro-enterprise • Capterra pricing (plans, no prices): https://capterra.com/p/10529/Simpro-Enterprise/pricing/ • Toolradar pricing (Sep 2026): https://toolradar.com/tools/simpro/pricing • Project invoicing, Requests for Claim, retention (blog, 2019): https://www.simprogroup.com/blog/a-snapshot-of-project-invoicing-and-payments-in-simpro • UK inventory features: https://www.simprogroup.com/uk/features/inventory-management-software • RAIN AI release (8 Jul 2026): https://cfotech.news/story/simpro-launches-rain-with-ai-tools-for-field-service • RAIN press release (could not be fetched): https://www.simprogroup.com/company/press/simpro-group-announces-rain • BigChange acquisition (Oct 2024): https://www.businesswire.com/news/home/20241025262794/en/Simpro-Group-Acquires-BigChange
A7: Tradify | B7: Small-trade job management | C7: 1–20 person trades | D7: Good (UK pricing, Xero/Sage/QBO) | E7: £34 / £37 / £44 per user/month (Lite/Pro/Plus) [V, Oct 2026] | F7: Low–medium: job costing, POs, bills to PO | G7: • What: Simple job management for small trade businesses (quotes, jobs, scheduling, timesheets, invoices). NZ-founded; markets in the UK, AU, NZ, US and ZA. • Who: 1–20 person trades (electricians, plumbers, builders, roofers). • UK: UK pricing, with Xero, Sage and QuickBooks Online sync [V]. • Pricing (per user per month, checked 22 Oct 2026) [V]: Lite £34 (jobs, scheduling, quotes, invoices, payments, accounting sync); Pro £37 (adds branding, enquiry forms, photos, recurring jobs, job costing, timesheets, compliance certificates); Plus £44 (adds service reminders, purchase orders, bulk invoicing, kit bundles, service reports); Custom on request. 14-day trial, monthly, no contract. SMS 10p each. VAT treatment not stated. | H7: | Area | Detail | |---|---| | Quoting | Quotes from price list items and kits; online acceptance [V/K] | | Jobs / scheduling | Job board by status/category; drag-and-drop schedule; recurring jobs (Pro) [V] | | Timesheets | Staff and subcontractors log time against jobs on their own devices [V] | | Materials / POs | POs linked to quotes, jobs, invoices and customers; move quote/job items straight into a PO; match supplier invoices to POs; import supplier price lists by CSV [V] | | Stock | Minimal; reviewers call inventory weak [V] | | Variations / progress | Partial invoicing; no UK application-for-payment workflow [K] | | Compliance | Compliance certificates (Pro) [V]; no RAMS builder [K] | | Accounting | Creates bills, payments, suppliers and customers in Xero; contact changes sync [V] | | Job costing | Snapshot of profit and cost per job [V] | | Portal | No customer portal [K] | | AI | Nothing significant found [V – search found none] | | I7: Quote items → job → PO (copy items) → supplier bill matched to PO → job cost → invoice → Xero. Timesheet hours cost to the job. Price lists feed quotes, POs and bills. There is no CVR or retention. | J7: • "Copy to PO" from any priced list (BoQ lines, SoW items, a won quote), not only from material requests. • Kit bundles (see Top 25 #5). • Service reminders / recurring jobs for maintenance contracts (gutter clears, annual roof inspections) feeding the Repair/Maintenance tile. | K7: Capterra UK 4.7/5 (152) [V]. Seen as pricey per user; weak reporting, scheduling and inventory; slow pages; no offline mode; no Google Calendar; "sent from Tradify" on emailed invoices [V]. --- | L7: • UK pricing (checked 22 Oct 2026): https://www.kaeltripton.com/tradify-pricing-uk/ • Features: https://www.tradifyhq.com/features • Purchase orders: https://tradifyhq.com/features/purchase-order-software • Capterra UK reviews: https://www.capterra.co.uk/reviews/152413/tradify
A8: Fergus | B8: Trade job management | C8: Plumbing/electrical/building SMEs | D8: Good (UK pricing, UK support) | E8: £39 Essentials / £45 Pro per user/month list (90% off promo to Dec 2026); timesheet users £12, contractors £2/day [V] | F8: Medium: supplier invoice import to jobs/phases, job phases, AI assistant | G8: • What: Job management for trades. NZ-founded; 26,000+ tradespeople in AU, NZ and the UK [V, Sep 2026]. UK and Ireland localisation (tax, compliance, invoicing) [V]. • Pricing UK (fergus.com/uk/pricing, Oct 2026) [V]: Essentials £39 and Pro £45 per user/month list (on promo at £3.90 / £4.50 until December); Enterprise (10+ staff) custom. Timesheet-only users £12/month, contractor users £2 per user per day, SMS £8 per 100, card fees 1.6% + 20p. Pro adds automatic supplier integrations, job phases, POs, forms, checklists, hazards/SWMS and advanced reporting. 14-day trial, no lock-in. | H8: | Area | Detail | |---|---| | Quoting | Labour, materials and markup; e-acceptance; branded templates (Aug 2025); takeoff via Groundplan integration [V] | | Jobs | Status board; job phases (Pro) so large jobs are quoted, costed and invoiced in stages [V]; PDF work order → job by AI (Aug 2025) [V] | | Scheduling | Visual schedule board [V] | | Time / labour | Time and materials against each job; timesheet-only users [V] | | Materials / suppliers | 100+ supplier integrations: supplier invoices flow in line by line and are assigned to a job in one click, can be split across jobs and phases; supplier price books uploaded or auto-synced; POs to suppliers for pricing, collection or delivery [V] | | H&S | Hazards and SWMS (Pro) – AU-style; reviewers call H&S clunky [V] | | Accounting | Xero, QuickBooks, MYOB [V] | | Job costing | Financial summary and profit per job [V] | | Payments | Fergus Pay [V] | | AI | Fergus Assistant (web: set up jobs, build quotes, schedule, prepare invoices, draft messages, answer "why is this job losing money?" and build reports on request); Assistant on Fergus Go (voice/text on site, logging time and notes); Fergus AI (Sep 2026) for end-to-end admin. Uses existing permissions and asks for confirmation before anything is created, changed or sent [V] | | I8: Supplier invoice line items arrive electronically and are dropped onto job/phase cost. Time and materials flow onto the invoice pre-filled. Phases give stage budgets and stage invoices. | J8: • AI Assistant with a confirmation step (Top 25 #1). • Voice notes from site that become structured records (Top 25 #8). • Cheaper "timesheet-only" and "day-rate contractor" user types. A useful pattern if OpHUB is ever sold to other contractors. • PDF work order → repair job. Housing association and managing agent work orders become a Repair/Maintenance job automatically. | K8: GetApp UK 4.6/5 (155; sampled reviews 2018–21) [V]. Published quotes cannot be edited; price book and favourites search weak; H&S tools clunky; overtime entered by hand; costly for part-time staff [V]. --- | L8: • UK pricing: https://www.fergus.com/uk/pricing/ • Product facts page: https://fergus.com/llm-info/ • Supplier integrations: https://fergus.com/integrations/suppliers/ • AI-first launch (13 Sep 2026): https://completeaitraining.com/news/fergus-launches-ai-first-job-management-for-tradespeople/ • PDF work order import and templates (Aug 2025): https://electricalcontractingnews.com/news/products/software-and-apps/fergus-introduces-new-tools-for-job-management/ • GetApp UK reviews: https://www.getapp.co.uk/reviews/105833/fergus • Toolradar pricing (Oct 2026): https://toolradar.com/tools/fergus/pricing
A9: ServiceM8 | B9: Service job app (iPhone-first) | C9: Small service trades, high job counts | D9: Medium (UK pricing; iOS-first) | E9: £0–£269/month by jobs per month, unlimited users [V, Oct 2026] | F9: Low: add-ons for costing, progress invoicing, POs | G9: • What: Job management for small service businesses, iPhone-first (full app on iOS, "lite" Android) [V, review]. • UK pricing (checked 22 Oct 2026) [V]: priced by jobs per month, unlimited users on paid plans: Free £0 (30 jobs, 1 user); Starter £25 (50); Growing £59 (150); Premium £119 (500); Premium Plus £269 (1,500+). 14-day trial. VAT not stated. | H9: | Area | Detail | |---|---| | Quotes / jobs | Job cards, quotes, online booking, text reminders [V] | | Scheduling | Dispatch board, staff GPS [K] | | Add-ons | Job Costing, Markup Billing (cost and markup per item), Partial/Progress Invoicing, Bundles, MyPO (POs), Forms, Automated Timesheet Sync (clock-on/off → Xero/QBO/MYOB timesheets), Deputy rostering [V] | | Accounting | Two-way customer and item sync with Xero; invoices to Xero in two taps; payments sync both ways [V] | | Portal | Self-serve online booking; no full client portal [V] | | AI | Nothing specific found [V] | | I9: Fairly loose: costing is an add-on, and POs are a third-party add-on. The strong part is clock-on/off → payroll timesheets in Xero. | J9: • Push approved check-in hours into Xero Payroll as timesheets. OpHUB already does "wage pushes"; check that hours, not only amounts, are pushed where staff are hourly. • Pricing by usage, not seats, if OpHUB is ever sold to others. | K9: Capterra UK 4.5/5 (311) [V]. Paid add-ons pile up; iOS-only full app; card payment fees; support complaints and a price change during migration; staff cannot set their own availability; forms cannot be job tasks [V]. --- | L9: • UK pricing (checked 22 Oct 2026): https://www.kaeltripton.com/servicem8-uk/ • Add-ons: https://www.servicem8.com/addons • Xero integration (UK): https://servicem8.com/uk/xero-integration • Capterra UK reviews: https://www.capterra.co.uk/reviews/110711/servicem8
A10: Procore | B10: Enterprise construction platform | C10: Main contractors, large subcontractors | D10: Present (UK site and UK support docs) but US-centric finance | E10: Annual fee by construction volume; est. $15–30k/yr for small GCs (third-party) [V-estimate] | F10: Very high: budget, commitments, change events, invoicing, forecasting | G10: • What: Enterprise construction management covering project management, quality and safety, financials, preconstruction, Procore Pay, analytics and AI (Helix / Assist / Agents). • Who: Main contractors, large specialist subcontractors, owners/developers. • UK: UK website and UK-English support docs (v2.support.procore.com/en-gb) [V]; used by UK tier 1–3 contractors [K]. Finance is US-shaped (AIA billing, retainage), though "retention" is supported [V]. • Pricing: No public rate card. Annual fee by product and Annual Construction Volume (ACV), unlimited users. Third-party estimate: ~$15k–30k/yr at $10–50m ACV, $30k–80k at $50–200m, plus first-year implementation that can be large [V-estimate, OneCrew Jul 2026, a competitor]. Capterra reviewers: "too expensive for a small contractor" [V]. | H10: | Area | Detail | |---|---| | Estimating / precon | Estimating, takeoff, bid management; awarded bid → subcontract [V/K] | | Project management | Drawings (with automatic register and revision handling, much praised), RFIs, submittals, daily log, meetings, schedule, photos [V] | | Quality & safety | Inspections, observations, incidents, permits/forms, action plans [K] | | Timesheets / T&M | Timesheets and crews; T&M tickets signed in the field [K] | | Commitments | Subcontracts and purchase orders with schedule of values (SoV), default retention %, payment settings [V] | | Change management | Change events → potential change orders → commitment and prime change orders, with configurable tiers [V/K] | | Invoicing | Owner invoices (payment applications) from the prime contract SoV; subcontractor invoices submitted by invoice contacts against their commitment; retention controls (Feb 2025): each pay app type is *Work, Materials & Retention*, *Work & Materials* (retention blocked) or *Retention Release* (only retention) [V] | | Budget / forecasting | Budget by cost code with original, approved changes, revised, pending, committed, direct costs, job-to-date, projected cost, estimated cost at completion, projected over/under; budget views; forecasting tool [K] | | Payments | "Payments Issued" updates budget automatically [V]; Procore Pay (mainly US) [K] | | Accounting | ERP integrations (Sage Intacct, Viewpoint, etc.); in the UK typically via connectors [K] | | AI | Helix intelligence layer; Procore Assist (photo intelligence summarising progress and safety from site photos; multilingual incl. Polish; mobile voice); Agent Builder (custom agents from natural-language prompts); pre-built RFI Creation Agent and Daily Log Agent (Groundbreak Oct 2025) [V]. Groundbreak 2026: Procore AI Go voice-first mobile app (open beta), NVIDIA digital twin (closed beta) [V] | | I10: Cost code is the spine. Budget lines, commitment SoV lines, change order lines, direct costs and timesheets all carry a cost code (and cost type), so the budget view rolls up *original → revised → committed → actual → projected* per code. Change events start as "pending budget changes" before they are approved, so exposure shows early. A subcontractor invoice is billed against its commitment SoV (% complete per line, retention by line), which gives the "% complete from the schedule" pattern. Owner pay apps come from the prime contract SoV. | J10: • Change events / early warnings (Top 25 #6): record a likely cost or revenue change before it is a priced variation, so CVR shows risk and opportunity. • Subcontractor self-billing portal against their subcontract SoV (Top 25 #10). OpHUB has subcontractor applications; take it further so the sub enters % per SoV line and OpHUB applies retention per line. • Retention release as its own application type (Procore's three pay app types) so retention cannot be claimed early by mistake. • AI daily log agent (Top 25 #7) and photo intelligence (progress and safety summary from SoW photos). • Polish/Romanian language for operatives' screens and AI answers. Procore added Polish; very relevant to UK roofing labour. | K10: Capterra UK 4.5/5 (2,680) [V]. Expensive for small firms; renewals inflexible; long learning curve; too much for smaller firms; hard for subcontractors and works best when the whole team adopts it; slow navigation [V]. Not built around UK CIS, VAT reverse charge or Construction Act notices [K]. --- | L10: • Pricing analysis (Jul 2026, third party/competitor): https://www.getonecrew.com/post/procore-pricing • Retention controls (14 Feb 2025): https://www.procore.com/en-au/whats-new/commitment-invoice-retainage-controls • Commitments guide (UK English): https://v2.support.procore.com/en-gb/process-guides/general-contractor-financial-management-user-guide/commitments-tool • AI at Groundbreak 2025 (and 2026 sidebar): https://www.businesswire.com/news/home/20251015796723/en/Procore-Advances-the-Future-of-Construction-with-New-AI-Innovations-at-Groundbreak-2025 • Capterra UK reviews: https://www.capterra.co.uk/reviews/56250/procore
A11: Buildertrend | B11: Residential builder platform | C11: US home builders and remodellers | D11: Weak (UK reviewers say VAT is manual) | E11: Quote only; est. ~$339–$1,099/month (third-party) [V-estimate] | F11: Medium–high: budgets, POs, bills, change orders, AIA-style progress billing (Sep 2026) | G11: • What: All-in-one platform for residential builders and remodellers (owns CoConstruct). US-centric. • UK: Weak. A UK reviewer complains that VAT has to be added by hand to quotes and invoices [V]. Few integrations. • Pricing: Not published; based on annual construction volume. Third-party estimates (Aug 2026) [V-estimate]: Essential ~$339–499/month; Advanced ~$499–799; Complete ~$829–1,099; unlimited users. | H11: | Area | Detail | |---|---| | Estimating / proposals | Estimates → proposals → budget; takeoff [V/K] | | Scheduling | Gantt and calendar, crew notifications [V] | | Daily logs | With photos and automatic weather [V] | | Client portal | Strong: homeowner sees schedule, photos, selections, change orders, invoices; customer-facing daily reports and automatic emails [V] | | Selections | Client picks finishes with allowances (Complete) [V] | | Change orders | Client approves and e-signs; flows to budget and invoice [V/K] | | POs / bills | POs to subs/suppliers, bills and lien waivers (US) [K]; AI Bill Capture (Sep 2026) [V] | | Progress billing | AIA-style progress invoicing with SoV, retainage, cover sheets (Sep 2026) [V] | | Accounting | QuickBooks, Xero, Sage Intacct two-way (Sep 2026) [V] | | Warranty | Warranty and service requests (Complete) [V] | | Time | Mobile time clock with GPS [V] | | AI | AI Submittals, AI Bill Capture, AI Client Updates (drafts client progress messages; vendor claims 97% time saving), AI Plans (organises plan sets); acquired BizJet AI for agentic AI [V] | | I11: Estimate → budget (by cost code) → POs/bills against budget lines → change orders adjust budget and contract → invoices (deposit, progress/SoV, cost-plus). Time-clock hours cost to the job. | J11: • Weekly AI client update (Top 25 #9) built from SoW progress, photos and check-ins, reviewed by the PM before sending. • Client / main-contractor portal (Top 25 #4). • Weather stamped on every daily briefing and site diary entry (Top 25 #12). Useful for roofing delay claims. • Warranty / defects requests after handover, logged against the O&M manual's job. | K11: Capterra UK 4.5/5 (2,489) [V]. Overwhelming to set up; financial tools behind accounting packages; manual VAT; few integrations; scheduling too simple for commercial work; weak reporting; poor for corporate clients with several contacts; no published price or free trial [V]. --- | L11: • Pricing breakdown (Aug 2026, third party): https://www.getonecrew.com/post/buildertrend-pricing • AI and financial tools (29 Sep 2026): https://www.newsfilecorp.com/release/316422 • Capterra UK reviews: https://www.capterra.co.uk/reviews/70092/buildertrend
A12: Fieldwire | B12: Field task and drawings app | C12: Site teams, subcontractors | D12: Good (UK GBP pricing) | E12: Free / £33 / £50 / £67 per user/month annual (Capterra UK) [V] | F12: Low: basic budget tool on top tiers | G12: • What: Site task management built on drawings: plans, pins, punch lists, forms, inspections and RFIs. Owned by Hilti since 2021. • UK pricing (Capterra UK) [V]: Basic free; Pro £33, Business £50, Business Plus £67 per user/month billed annually. US list Feb 2026: Pro $39 (annual) / $49 (monthly), Business $54 [V]. | H12: | Area | Detail | |---|---| | Drawings | Fast plan viewer, versioning, hyperlinking, markups, tasks pinned on the drawing [V/K] | | Tasks / punch | Tasks with status, priority, assignee, photos; punch lists; custom statuses (Pro) [V] | | Forms | Daily reports, inspections, checklists; unlimited forms (Business); DocuSign signing of forms; role-based form permissions (Oct 2025) [V] | | Scheduling | Gantt-lite; Microsoft Project import (Oct 2025) [V] | | BIM | 3D model viewing and section cuts (Business) [V] | | Budget | Basic budget tool (Business Plus) with activity tab, analytics bar and projected over/under (Oct 2025) [V] | | Integrations | Procore, BIM 360, Smartsheet, Teams, Outlook, Google Drive; Hilti ON!Track tool tracking (Business) [V] | | AI | AI photo tagging by discipline (Oct 2025) [V] | | I12: Weak by design. The budget tool sits on top of tasks. Churned users cite the need for financial management (43%) [V, competitor survey – treat with caution]. | J12: • Snags and tasks pinned on drawings (Top 25 #15). OpHUB has plan markup (498) and snagging (500); join them so each snag is a pin on the roof plan, with a filterable plan view per block or plot. • AI photo tagging of SoW, snag and delivery photos by trade or element (ridge, valley, flashing, gutter, scaffold) for search and O&M. • Tool/plant tracking with tags in the style of Hilti ON!Track, using QR stickers on the plant register (OpHUB has PUWER/LOLER; add scan-to-check-out to a site). | K12: Capterra UK 4.6/5 (99) [V]. Limited customisation; key features on dearer tiers; slow with large drawing sets or poor signal; mobile less capable than desktop; limited links to job management systems; no estimating or invoicing [V]. --- | L12: • Capterra UK (GBP pricing, reviews): https://www.capterra.co.uk/reviews/142801/fieldwire • 2026 pricing review (third party/competitor): https://constructionbids.ai/blog/fieldwire-review-pricing-contractors-2026 • Product updates (Oct 2025): https://www.fieldwire.com/blog/product-updates-2025-ai-photo-tagging/ • Pricing breakdown (Projul): https://projul.com/blog/fieldwire-pricing-breakdown/
