Workbook

Sheet General Summary
B2: Company Name | C2: RTB Roofing Ltd
B3: Client Name | C3: Bellway Homes
B4: Project Name | C4: Studley Rd
B5: Project ID | C5: J101
B6: Valuation Date | C6: 25 Oct 2026
B7: Application No. | C7: 2
B8: Client PO
B10: General Summary
B11: Section | C11: Total | D11: Applied Total | E11: Applied % | F11: Certified Total | G11: Certified %
B12: Main Roof | C12: =IFERROR(SUMIF('Main Roof'!P3:P204,1,'Main Roof'!G3:G204), 0) -> 48000 | D12: =IFERROR(SUMIF('Main Roof'!P3:P204,1,'Main Roof'!K3:K204), 0) -> 18000 | E12: =IFERROR(IF(OR(C12=0,ISBLANK(C12)),0,D12/C12), 0) -> 0.375 | F12: =IFERROR(SUMIF('Main Roof'!P3:P204,1,'Main Roof'!M3:M204), 0) -> 18000 | G12: =IFERROR(IF(OR(C12=0,ISBLANK(C12)),0,F12/C12), 0) -> 0.375
B13: Variations | C13: =IFERROR(SUMIF('Variations'!P3:P203,1,'Variations'!G3:G203), 0) -> 1000 | D13: =IFERROR(SUMIF('Variations'!P3:P203,1,'Variations'!K3:K203), 0) -> 1000 | E13: =IFERROR(IF(OR(C13=0,ISBLANK(C13)),0,D13/C13), 0) -> 1 | F13: =IFERROR(SUMIF('Variations'!P3:P203,1,'Variations'!M3:M203), 0) -> 1000 | G13: =IFERROR(IF(OR(C13=0,ISBLANK(C13)),0,F13/C13), 0) -> 1
B14: Dayworks | C14: =IFERROR(SUMIF('Dayworks'!P3:P203,1,'Dayworks'!G3:G203), 0) -> 640 | D14: =IFERROR(SUMIF('Dayworks'!P3:P203,1,'Dayworks'!K3:K203), 0) -> 640 | E14: =IFERROR(IF(OR(C14=0,ISBLANK(C14)),0,D14/C14), 0) -> 1 | F14: =IFERROR(SUMIF('Dayworks'!P3:P203,1,'Dayworks'!M3:M203), 0) -> 640 | G14: =IFERROR(IF(OR(C14=0,ISBLANK(C14)),0,F14/C14), 0) -> 1
B16: SubTotal | C16: =IFERROR(SUM(C12:C14), 0) -> 49640 | D16: =IFERROR(SUM(D12:D14), 0) -> 19640 | F16: =IFERROR(SUM(F12:F14), 0) -> 19640
B17: Less Discount at 0% | D17: =IFERROR(ROUND(D16*0,2), 0) -> 0 | F17: =IFERROR(ROUND(F16*0,2), 0) -> 0
B18: Retention at 5% | D18: =IFERROR(ROUND((D16-D17)*0.05,2), 0) -> 982 | F18: =IFERROR(ROUND((F16-F17)*0.05,2), 0) -> 982
B19: Net After Retention | D19: =IFERROR(D16-D17-D18, 0) -> 18658 | F19: =IFERROR(F16-F17-F18, 0) -> 18658
B20: Previously Certified (excl VAT) | D20: 0 | F20: 0
B21: Gross Payment Due | D21: =IFERROR(D19-D20, 0) -> 18658 | F21: =IFERROR(F19-F20, 0) -> 18658
B22: VAT (domestic reverse charge — customer to account to HMRC) | D22: 0 | F22: 0
B23: Net Payment Due | D23: =IFERROR(D21+D22, 0) -> 18658 | F23: =IFERROR(F21+F22, 0) -> 18658
B25: Applied = what we are applying for. Certified starts the same — the client changes the Certified % (green) and sends it back.

Sheet Main Roof
A1: OpHUB Key | B1: Ref | C1: Description | D1: Qty | E1: Unit | F1: Rate | G1: Amount | H1: Prev Certified % | I1: Prev Certified | J1: Applied % | K1: Applied | L1: Certified % | M1: Certified | N1: Difference | O1: Notes | P1: Include in Summary
A2: H:h1 | B2: Main Roof
A3: L:i1 | C3: Tiling | D3: 300 | E3: m2 | F3: 120 | G3: =IFERROR(D3*F3, 0) -> 36000 | H3: 0 | I3: =IFERROR(G3*H3, 0) -> 0 | J3: 0.5 | K3: =IFERROR(G3*J3, 0) -> 18000 | L3: 0.5 | M3: =IFERROR(G3*L3, 0) -> 18000 | N3: =IFERROR(M3-K3, 0) -> 0 | P3: 1
A4: L:i2 | C4: Ridge | D4: 60 | E4: m | F4: 200 | G4: =IFERROR(D4*F4, 0) -> 12000 | H4: 0 | I4: =IFERROR(G4*H4, 0) -> 0 | J4: 0.1 | K4: =IFERROR(G4*J4, 0) -> 0 | L4: 0 | M4: =IFERROR(G4*L4, 0) -> 0 | N4: =IFERROR(M4-K4, 0) -> 0 | P4: 1
C5: Lead flashing | G5: 500 | H5: 0 | J5: 1 | L5: 1 | P5: 1

Sheet Variations
A1: OpHUB Key | B1: Ref | C1: Description | D1: Qty | E1: Unit | F1: Rate | G1: Amount | H1: Prev Certified % | I1: Prev Certified | J1: Applied % | K1: Applied | L1: Certified % | M1: Certified | N1: Difference | O1: Notes | P1: Include in Summary
B2: Variations
A3: V:x0 | C3: V01 Extra flashing | D3: 1 | E3: item | F3: 1000 | G3: =IFERROR(D3*F3, 0) -> 1000 | H3: 0 | I3: =IFERROR(G3*H3, 0) -> 0 | J3: 1 | K3: =IFERROR(G3*J3, 0) -> 1000 | L3: 1 | M3: =IFERROR(G3*L3, 0) -> 1000 | N3: =IFERROR(M3-K3, 0) -> 0 | P3: 1

Sheet Dayworks
A1: OpHUB Key | B1: Ref | C1: Description | D1: Qty | E1: Unit | F1: Rate | G1: Amount | H1: Prev Certified % | I1: Prev Certified | J1: Applied % | K1: Applied | L1: Certified % | M1: Certified | N1: Difference | O1: Notes | P1: Include in Summary
B2: Dayworks
A3: D:0 | C3: DW01 Storm repairs | G3: 640 | H3: 0 | I3: =IFERROR(G3*H3, 0) -> 0 | J3: 1 | K3: =IFERROR(G3*J3, 0) -> 640 | L3: 1 | M3: =IFERROR(G3*L3, 0) -> 640 | N3: =IFERROR(M3-K3, 0) -> 0 | P3: 1
